{"gitdate":"2015-02-09 22:52:26 +0100","exit_code":"255","name":"GLWindow","jlver":"0.4","gitsha":"d94a6a2693e7dfbae9dc6f3f4f8785bae857745b","status":"not_possible","version":"0.0.5","url":"http://github.com/JuliaGL/GLWindow.jl","log":">>> 'Pkg.add(\"GLWindow\")' log\nINFO: Installing Calculus v0.1.10\nINFO: Installing Color v0.4.8\nINFO: Installing ColorTypes v0.1.4\nINFO: Installing ColorVectorSpace v0.0.3\nINFO: Installing Colors v0.5.3\nINFO: Installing Dates v0.4.4\nINFO: Installing DualNumbers v0.1.3\nINFO: Installing FactCheck v0.4.0\nINFO: Installing FixedPointNumbers v0.0.10\nINFO: Installing GLAbstraction v0.0.5\nINFO: Installing GLFW v1.0.0-alpha.7\nINFO: Installing GLWindow v0.0.5\nINFO: Installing Graphics v0.1.3\nINFO: Installing Images v0.4.47\nINFO: Installing ImmutableArrays v0.0.10\nINFO: Installing Lumberjack v1.0.0\nINFO: Installing MacroTools v0.2.0\nINFO: Installing ModernGL v0.0.5\nINFO: Installing Mustache v0.0.12\nINFO: Installing NaNMath v0.1.0\nINFO: Installing Quaternions v0.0.4\nINFO: Installing Reactive v0.2.2\nINFO: Installing Requires v0.2.0\nINFO: Installing SIUnits v0.0.5\nINFO: Installing TexExtensions v0.0.2\nINFO: Installing UUID v0.1.0\nINFO: Building Images\nWARNING: Base.Uint8 is deprecated, use UInt8 instead.\nWARNING: Base.Uint8 is deprecated, use UInt8 instead.\nWARNING: Base.Uint8 is deprecated, use UInt8 instead.\nWARNING: Base.Uint8 is deprecated, use UInt8 instead.\nWARNING: Base.Uint8 is deprecated, use UInt8 instead.\nWARNING: Base.Uint8 is deprecated, use UInt8 instead.\nWARNING: Base.Uint8 is deprecated, use UInt8 instead.\nINFO: Building GLFW\nINFO: Building GLFW 3.1.1 library from source\n-- Looking for XOpenDisplay in /usr/lib/x86_64-linux-gnu/libX11.so;/usr/lib/x86_64-linux-gnu/libXext.so\n-- Looking for XOpenDisplay in /usr/lib/x86_64-linux-gnu/libX11.so;/usr/lib/x86_64-linux-gnu/libXext.so - found\n-- Looking for gethostbyname\n-- Looking for gethostbyname - found\n-- Looking for connect\n-- Looking for connect - found\n-- Looking for remove\n-- Looking for remove - found\n-- Looking for shmat\n-- Looking for shmat - found\n-- Looking for IceConnectionNumber in ICE\n-- Looking for IceConnectionNumber in ICE - found\n-- Found X11: /usr/lib/x86_64-linux-gnu/libX11.so\n-- Found OpenGL: /usr/lib/x86_64-linux-gnu/libGL.so  \n-- Looking for include file pthread.h\n-- Looking for include file pthread.h - found\n-- Looking for pthread_create\n-- Looking for pthread_create - not found\n-- Looking for pthread_create in pthreads\n-- Looking for pthread_create in pthreads - not found\n-- Looking for pthread_create in pthread\n-- Looking for pthread_create in pthread - found\n-- Found Threads: TRUE  \n-- Using X11 for window creation\n-- Using GLX for context creation\nCMake Error at CMakeLists.txt:259 (message):\n  The RandR library and headers were not found\n\n\n-- Configuring incomplete, errors occurred!\nSee also \"/home/vagrant/.julia/v0.4/GLFW/deps/builds/glfw-3.1.1/CMakeFiles/CMakeOutput.log\".\nSee also \"/home/vagrant/.julia/v0.4/GLFW/deps/builds/glfw-3.1.1/CMakeFiles/CMakeError.log\".\nERROR: failed process: Process(`cmake -DBUILD_SHARED_LIBS=ON -DCMAKE_INSTALL_PREFIX=../../usr64 -DGLFW_BUILD_DOCS=OFF -DGLFW_BUILD_EXAMPLES=OFF -DGLFW_BUILD_TESTS=OFF ../../src/glfw-3.1.1`, ProcessExited(1)) [1]\nWARNING: On Linux, you might not have xorg-dev and libglu1-mesa-dev installed, which you can get via the commandline with for example\nsudo apt-get install  xorg-dev libglu1-mesa-dev\nIf that doesn't help, try to install GLFW manually\n(see http://www.glfw.org/download.html for more information)\nINFO: Package database updated\nINFO: METADATA is out-of-date — you may not have the latest version of GLWindow\nINFO: Use `Pkg.update()` to get the latest versions of your packages\n\n>>> 'Pkg.test(\"GLWindow\")' log\nPackage was unable to be tested.\n>>> End of log","licfile":"LICENSE.md","license":"MIT"}