{"gitdate":"2015-09-17 21:00:54 +0900","exit_code":"1","name":"IndexableBitVectors","jlver":"0.4","gitsha":"d0d96b9695b0fd6faaf72c68244eb41fa8f5555c","status":"tests_fail","version":"0.1.0","url":"http://github.com/BioJulia/IndexableBitVectors.jl","log":">>> 'Pkg.add(\"IndexableBitVectors\")' log\nINFO: Installing IndexableBitVectors v0.1.0\nINFO: Installing Switch v0.0.1\nINFO: Package database updated\n\n>>> 'Pkg.test(\"IndexableBitVectors\")' log\nJulia Version 0.4.0-rc2+10\nCommit d8930a0 (2015-09-20 15:38 UTC)\nPlatform Info:\n  System: Linux (x86_64-unknown-linux-gnu)\n  CPU: Intel(R) Core(TM) i7-6700K CPU @ 4.00GHz\n  WORD_SIZE: 64\n  BLAS: libopenblas (USE64BITINT DYNAMIC_ARCH NO_AFFINITY Prescott)\n  LAPACK: libopenblas\n  LIBM: libopenlibm\n  LLVM: libLLVM-3.3\nINFO: Computing test dependencies for IndexableBitVectors...\nINFO: Installing FactCheck v0.4.0\nINFO: Testing IndexableBitVectors\nBitVector\n  > access\n  > rank\n  > select\n13454 facts verified.\nSucVector\n  > access\n  > rank\n  > select\n  > long\nERROR: LoadError: OutOfMemoryError()\n in call at ./bitarray.jl:21\n in test_long at /home/vagrant/.julia/v0.4/IndexableBitVectors/test/runtests.jl:175\n in anonymous at /home/vagrant/.julia/v0.4/IndexableBitVectors/test/runtests.jl:208\n in context at /home/vagrant/.julia/v0.4/FactCheck/src/FactCheck.jl:474\n in anonymous at /home/vagrant/.julia/v0.4/IndexableBitVectors/test/runtests.jl:207\n in facts at /home/vagrant/.julia/v0.4/FactCheck/src/FactCheck.jl:448\n in include at ./boot.jl:261\n in include_from_node1 at ./loading.jl:304\n in process_options at ./client.jl:308\n in _start at ./client.jl:411\nwhile loading /home/vagrant/.julia/v0.4/IndexableBitVectors/test/runtests.jl, in expression starting on line 197\n=========================[ ERROR: IndexableBitVectors ]=========================\n\nfailed process: Process(`/home/vagrant/julia/bin/julia --check-bounds=yes --code-coverage=none --color=no /home/vagrant/.julia/v0.4/IndexableBitVectors/test/runtests.jl`, ProcessExited(1)) [1]\n\n================================================================================\nINFO: Removing FactCheck v0.4.0\nERROR: IndexableBitVectors had test errors\n in error at ./error.jl:21\n in test at pkg/entry.jl:753\n in anonymous at pkg/dir.jl:31\n in cd at file.jl:22\n in cd at pkg/dir.jl:31\n in test at pkg.jl:71\n in process_options at ./client.jl:284\n in _start at ./client.jl:411\n\n>>> End of log","licfile":"LICENSE.md","license":"MIT"}