{"gitdate":"2015-08-06 23:19:44 -0400","exit_code":"0","name":"LaTeXStrings","jlver":"0.4","gitsha":"4116883a8ec408cf18613bab05efe917859c67f5","status":"tests_pass","version":"0.1.4","url":"http://github.com/stevengj/LaTeXStrings.jl","log":">>> 'Pkg.add(\"LaTeXStrings\")' log\nINFO: Installing LaTeXStrings v0.1.4\nINFO: Package database updated\n\n>>> 'Pkg.test(\"LaTeXStrings\")' log\nJulia Version 0.4.0-rc2+10\nCommit d8930a0 (2015-09-20 15:38 UTC)\nPlatform Info:\n  System: Linux (x86_64-unknown-linux-gnu)\n  CPU: Intel(R) Core(TM) i7-6700K CPU @ 4.00GHz\n  WORD_SIZE: 64\n  BLAS: libopenblas (USE64BITINT DYNAMIC_ARCH NO_AFFINITY Prescott)\n  LAPACK: libopenblas\n  LIBM: libopenlibm\n  LLVM: libLLVM-3.3\nINFO: Computing test dependencies for LaTeXStrings...\nINFO: No packages to install, update or remove\nINFO: Testing LaTeXStrings\nINFO: LaTeXStrings tests passed\nINFO: No packages to install, update or remove\n\n>>> End of log","licfile":"LICENSE.md","license":"MIT"}