{"gitdate":"2015-08-20 01:53:57 +0900","exit_code":"0","name":"MelGeneralizedCepstrums","jlver":"0.4","gitsha":"246d0a390e99b8993372b581dec8e0d38f6ae73e","status":"tests_pass","version":"0.0.1","url":"http://github.com/r9y9/MelGeneralizedCepstrums.jl","log":">>> 'Pkg.add(\"MelGeneralizedCepstrums\")' log\nINFO: Cloning cache of MelGeneralizedCepstrums from git://github.com/r9y9/MelGeneralizedCepstrums.jl.git\nINFO: Cloning cache of SPTK from git://github.com/r9y9/SPTK.jl.git\nINFO: Installing MelGeneralizedCepstrums v0.0.1\nINFO: Installing SPTK v0.0.1\nINFO: Building SPTK\nINFO: Attempting to Create directory /home/vagrant/.julia/v0.4/SPTK/deps/downloads\nINFO: Downloading file https://github.com/r9y9/SPTK/archive/v3.8.7.tar.gz\n  % Total    % Received % Xferd  Average Speed   Time    Time     Time  Current\n                                 Dload  Upload   Total   Spent    Left  Speed\n\r  0     0    0     0    0     0      0      0 --:--:-- --:--:-- --:--:--     0\r100   117    0   117    0     0    716      0 --:--:-- --:--:-- --:--:--   717\n\r  0     0    0 14567    0     0  28944      0 --:--:-- --:--:-- --:--:-- 28944\r  0     0    0 1273k    0     0  1709k      0 --:--:-- --:--:-- --:--:-- 5223k\nINFO: Done downloading file https://github.com/r9y9/SPTK/archive/v3.8.7.tar.gz\nINFO: Attempting to Create directory /home/vagrant/.julia/v0.4/SPTK/deps/src\nINFO: Attempting to Create directory /home/vagrant/.julia/v0.4/SPTK/deps\nINFO: Directory /home/vagrant/.julia/v0.4/SPTK/deps already created\nINFO: Changing Directory to /home/vagrant/.julia/v0.4/SPTK/deps/src/SPTK-3.8.7\nSetting top to                           : /home/vagrant/.julia/v0.4/SPTK/deps/src/SPTK-3.8.7 \nSetting out to                           : /home/vagrant/.julia/v0.4/SPTK/deps/src/SPTK-3.8.7/build \nChecking for 'gcc' (C compiler)          : /usr/bin/gcc \nChecking for header fcntl.h              : yes \nChecking for header limits.h             : yes \nChecking for header stdlib.h             : yes \nChecking for header string.h             : yes \nChecking for header strings.h            : yes \n\nSPTK has been configured as follows:\n\n[Build information]\nPackage:                 SPTK-3.8.7\nbuild (compile on):      x86_64-linux\nhost endian:             little\nCompiler:                gcc\nCompiler version:        4.8.4\nCFLAGS:                  -O2 -Wall\nGenerate python bindings False\n\n'configure' finished successfully (0.136s)\nINFO: Changing Directory to /home/vagrant/.julia/v0.4/SPTK/deps/src/SPTK-3.8.7\nWaf: Entering directory `/home/vagrant/.julia/v0.4/SPTK/deps/src/SPTK-3.8.7/build'\n[ 1/98] Compiling bin/acep/_acep.c\n[ 2/98] Compiling bin/acorr/_acorr.c\n[ 3/98] Compiling bin/agcep/_agcep.c\n[ 4/98] Compiling bin/amcep/_amcep.c\n[ 5/98] Compiling bin/average/_average.c\n[ 6/98] Compiling bin/b2mc/_b2mc.c\n[ 7/98] Compiling bin/c2acr/_c2acr.c\n[ 8/98] Compiling bin/c2ir/_c2ir.c\n[ 9/98] Compiling bin/c2ndps/_c2ndps.c\n[10/98] Compiling bin/c2sp/_c2sp.c\n[11/98] Compiling bin/clip/_clip.c\n[12/98] Compiling bin/dct/_dct.c\n[13/98] Compiling bin/df2/_df2.c\n[14/98] Compiling bin/dfs/_dfs.c\n[15/98] Compiling bin/fft/_fft.c\n[16/98] Compiling bin/fft2/_fft2.c\n[17/98] Compiling bin/fftcep/_fftcep.c\n[18/98] Compiling bin/fftr/_fftr.c\n[19/98] Compiling bin/fftr2/_fftr2.c\n[20/98] Compiling bin/freqt/_freqt.c\n[21/98] Compiling bin/gc2gc/_gc2gc.c\n[22/98] Compiling bin/gcep/_gcep.c\n[23/98] Compiling bin/glsadf/_glsadf.c\n[24/98] Compiling bin/gmm/_gmm.c\n[25/98] Compiling bin/gnorm/_gnorm.c\n[26/98] Compiling bin/grpdelay/_grpdelay.c\n[27/98] Compiling bin/histogram/_histogram.c\n[28/98] Compiling bin/ifft/_ifft.c\n[29/98] Compiling bin/ifft2/_ifft2.c\n[30/98] Compiling bin/ifftr/_ifftr.c\n[31/98] Compiling bin/ignorm/_ignorm.c\n[32/98] Compiling bin/imsvq/_imsvq.c\n[33/98] Compiling bin/ivq/_ivq.c\n[34/98] Compiling bin/lbg/_lbg.c\n[35/98] Compiling bin/levdur/_levdur.c\n[36/98] Compiling bin/lmadf/_lmadf.c\n[37/98] Compiling bin/lpc/_lpc.c\n[38/98] Compiling bin/lpc2c/_lpc2c.c\n[39/98] Compiling bin/lpc2lsp/_lpc2lsp.c\n[40/98] Compiling bin/lpc2par/_lpc2par.c\n[41/98] Compiling bin/lsp2lpc/_lsp2lpc.c\n[42/98] Compiling bin/lsp2sp/_lsp2sp.c\n[43/98] Compiling bin/lspcheck/_lspcheck.c\n[44/98] Compiling bin/lspdf/_lspdf.c\n[45/98] Compiling bin/ltcdf/_ltcdf.c\n[46/98] Compiling bin/mc2b/_mc2b.c\n[47/98] Compiling bin/mcep/_mcep.c\n[48/98] Compiling bin/mfcc/_mfcc.c\n[49/98] Compiling bin/mgc2mgc/_mgc2mgc.c\n[50/98] Compiling bin/mgc2sp/_mgc2sp.c\n[51/98] Compiling bin/mgcep/_mgcep.c\n[52/98] Compiling bin/mgclsp2sp/_mgclsp2sp.c\n[53/98] Compiling bin/mglsadf/_mglsadf.c\n[54/98] Compiling bin/mlpg/_mlpg.c\n../bin/mlpg/_mlpg.c: In function ‘str2darray’:\n../bin/mlpg/_mlpg.c:97:4: warning: implicit declaration of function ‘strlen’ [-Wimplicit-function-declaration]\n    buf = getmem(strlen(c), sizeof(*buf));\n    ^\n../bin/mlpg/_mlpg.c:97:17: warning: incompatible implicit declaration of built-in function ‘strlen’ [enabled by default]\n    buf = getmem(strlen(c), sizeof(*buf));\n                 ^\n../bin/mlpg/_mlpg.c: In function ‘isfloat’:\n../bin/mlpg/_mlpg.c:109:8: warning: incompatible implicit declaration of built-in function ‘strlen’ [enabled by default]\n    if (strlen(c) == 0)\n        ^\n\n[55/98] Compiling bin/mlsadf/_mlsadf.c\n[56/98] Compiling bin/msvq/_msvq.c\n[57/98] Compiling bin/ndps2c/_ndps2c.c\n[58/98] Compiling bin/norm0/_norm0.c\n[59/98] Compiling bin/nrand/_nrand.c\n[60/98] Compiling bin/par2lpc/_par2lpc.c\n[61/98] Compiling bin/phase/_phase.c\n[62/98] Compiling bin/poledf/_poledf.c\n[63/98] Compiling bin/reverse/_reverse.c\n[64/98] Compiling bin/rmse/_rmse.c\n[65/98] Compiling bin/root_pol/_root_pol.c\n[66/98] Compiling bin/smcep/_smcep.c\n[67/98] Compiling bin/transpose/_transpose.c\n[68/98] Compiling bin/uels/_uels.c\n[69/98] Compiling bin/ulaw/_ulaw.c\n[70/98] Compiling bin/vc/_vc.c\n[71/98] Compiling bin/vq/_vq.c\n[72/98] Compiling bin/wavjoin/_wavjoin.c\n[73/98] Compiling bin/wavsplit/_wavsplit.c\n[74/98] Compiling bin/window/_window.c\n[75/98] Compiling bin/zcross/_zcross.c\n[76/98] Compiling bin/zerodf/_zerodf.c\n[77/98] Compiling bin/pitch/swipe/swipe.c\n[78/98] Compiling bin/pitch/swipe/vector.c\n[79/98] Compiling bin/vc/hts_engine_API/HTS_misc.c\n[80/98] Compiling bin/vc/hts_engine_API/HTS_pstream.c\n[81/98] Compiling bin/vc/hts_engine_API/HTS_sstream.c\n[82/98] Compiling lib/agexp.c\n[83/98] Compiling lib/cholesky.c\n[84/98] Compiling lib/fileio.c\n[85/98] Compiling lib/fillz.c\n[86/98] Compiling lib/getfp.c\n[87/98] Compiling lib/getmem.c\n[88/98] Compiling lib/gexp.c\n[89/98] Compiling lib/glog.c\n[90/98] Compiling lib/invert.c\n[91/98] Compiling lib/matrix.c\n[92/98] Compiling lib/movem.c\n[93/98] Compiling lib/mseq.c\n[94/98] Compiling lib/theq.c\n[95/98] Compiling lib/toeplitz.c\n[96/98] Linking build/bin/libSPTK.so\n[97/98] Symlinking build/bin/libSPTK.so\n[98/98] Compiling SPTK.pc.in\nWaf: Leaving directory `/home/vagrant/.julia/v0.4/SPTK/deps/src/SPTK-3.8.7/build'\n'build' finished successfully (3.822s)\nINFO: Changing Directory to /home/vagrant/.julia/v0.4/SPTK/deps/src/SPTK-3.8.7\nWaf: Entering directory `/home/vagrant/.julia/v0.4/SPTK/deps/src/SPTK-3.8.7/build'\n+ install /home/vagrant/.julia/v0.4/SPTK/deps/usr/include/SPTK/SPTK.h (from include/SPTK.h)\n+ install /home/vagrant/.julia/v0.4/SPTK/deps/usr/lib/libSPTK.so.3.8.7 (from build/bin/libSPTK.so)\n+ symlink /home/vagrant/.julia/v0.4/SPTK/deps/usr/lib/libSPTK.so (to libSPTK.so.3.8.7)\n+ symlink /home/vagrant/.julia/v0.4/SPTK/deps/usr/lib/libSPTK.so.3 (to libSPTK.so.3.8.7)\n+ install /home/vagrant/.julia/v0.4/SPTK/deps/usr/lib/pkgconfig/SPTK.pc (from build/SPTK.pc)\nWaf: Leaving directory `/home/vagrant/.julia/v0.4/SPTK/deps/src/SPTK-3.8.7/build'\n'install' finished successfully (0.038s)\nINFO: Package database updated\n\n>>> 'Pkg.test(\"MelGeneralizedCepstrums\")' log\nJulia Version 0.4.0-rc2+10\nCommit d8930a0 (2015-09-20 15:38 UTC)\nPlatform Info:\n  System: Linux (x86_64-unknown-linux-gnu)\n  CPU: Intel(R) Core(TM) i7-6700K CPU @ 4.00GHz\n  WORD_SIZE: 64\n  BLAS: libopenblas (USE64BITINT DYNAMIC_ARCH NO_AFFINITY Prescott)\n  LAPACK: libopenblas\n  LIBM: libopenlibm\n  LLVM: libLLVM-3.3\nINFO: Testing MelGeneralizedCepstrums\nWARNING: Base.FloatingPoint is deprecated, use AbstractFloat instead.\nWARNING: Base.FloatingPoint is deprecated, use AbstractFloat instead.\nWARNING: Base.FloatingPoint is deprecated, use AbstractFloat instead.\nWARNING: Base.FloatingPoint is deprecated, use AbstractFloat instead.\nWARNING: Base.FloatingPoint is deprecated, use AbstractFloat instead.\nWARNING: Base.FloatingPoint is deprecated, use AbstractFloat instead.\nWARNING: Base.FloatingPoint is deprecated, use AbstractFloat instead.\nWARNING: Base.FloatingPoint is deprecated, use AbstractFloat instead.\nWARNING: Base.FloatingPoint is deprecated, use AbstractFloat instead.\nWARNING: Base.FloatingPoint is deprecated, use AbstractFloat instead.\nWARNING: Base.FloatingPoint is deprecated, use AbstractFloat instead.\nWARNING: Base.FloatingPoint is deprecated, use AbstractFloat instead.\nWARNING: Base.FloatingPoint is deprecated, use AbstractFloat instead.\nWARNING: Base.FloatingPoint is deprecated, use AbstractFloat instead.\nWARNING: Base.FloatingPoint is deprecated, use AbstractFloat instead.\nWARNING: Base.FloatingPoint is deprecated, use AbstractFloat instead.\nWARNING: Base.FloatingPoint is deprecated, use AbstractFloat instead.\nWARNING: Base.FloatingPoint is deprecated, use AbstractFloat instead.\nWARNING: Base.FloatingPoint is deprecated, use AbstractFloat instead.\nWARNING: Base.FloatingPoint is deprecated, use AbstractFloat instead.\nWARNING: Base.FloatingPoint is deprecated, use AbstractFloat instead.\nWARNING: Base.FloatingPoint is deprecated, use AbstractFloat instead.\nWARNING: Base.FloatingPoint is deprecated, use AbstractFloat instead.\nWARNING: Base.FloatingPoint is deprecated, use AbstractFloat instead.\nWARNING: Base.FloatingPoint is deprecated, use AbstractFloat instead.\nWARNING: Base.FloatingPoint is deprecated, use AbstractFloat instead.\nWARNING: Base.FloatingPoint is deprecated, use AbstractFloat instead.\nWARNING: Base.FloatingPoint is deprecated, use AbstractFloat instead.\nWARNING: Base.FloatingPoint is deprecated, use AbstractFloat instead.\nWARNING: Base.FloatingPoint is deprecated, use AbstractFloat instead.\nWARNING: Base.FloatingPoint is deprecated, use AbstractFloat instead.\nWARNING: Base.FloatingPoint is deprecated, use AbstractFloat instead.\nWARNING: Base.FloatingPoint is deprecated, use AbstractFloat instead.\nWARNING: Base.FloatingPoint is deprecated, use AbstractFloat instead.\nWARNING: Base.FloatingPoint is deprecated, use AbstractFloat instead.\nWARNING: Base.FloatingPoint is deprecated, use AbstractFloat instead.\nWARNING: Base.FloatingPoint is deprecated, use AbstractFloat instead.\nWARNING: Base.FloatingPoint is deprecated, use AbstractFloat instead.\nWARNING: Base.FloatingPoint is deprecated, use AbstractFloat instead.\nWARNING: Base.FloatingPoint is deprecated, use AbstractFloat instead.\nWARNING: Base.FloatingPoint is deprecated, use AbstractFloat instead.\nWARNING: Base.FloatingPoint is deprecated, use AbstractFloat instead.\nWARNING: Base.FloatingPoint is deprecated, use AbstractFloat instead.\nWARNING: Base.FloatingPoint is deprecated, use AbstractFloat instead.\nWARNING: Base.FloatingPoint is deprecated, use AbstractFloat instead.\nWARNING: Base.FloatingPoint is deprecated, use AbstractFloat instead.\nWARNING: Base.FloatingPoint is deprecated, use AbstractFloat instead.\nWARNING: Base.FloatingPoint is deprecated, use AbstractFloat instead.\nWARNING: Base.FloatingPoint is deprecated, use AbstractFloat instead.\nWARNING: Base.FloatingPoint is deprecated, use AbstractFloat instead.\nWARNING: Base.FloatingPoint is deprecated, use AbstractFloat instead.\nmcep: testing with order=10, α=-0.544\nmcep: testing with order=10, α=-0.41\nmcep: testing with order=10, α=-0.35\nmcep: testing with order=10, α=0.0\nmcep: testing with order=10, α=0.35\nmcep: testing with order=10, α=0.41\nmcep: testing with order=10, α=0.544\nmcep: testing with order=12, α=-0.544\nmcep: testing with order=12, α=-0.41\nmcep: testing with order=12, α=-0.35\nmcep: testing with order=12, α=0.0\nmcep: testing with order=12, α=0.35\nmcep: testing with order=12, α=0.41\nmcep: testing with order=12, α=0.544\nmcep: testing with order=14, α=-0.544\nmcep: testing with order=14, α=-0.41\nmcep: testing with order=14, α=-0.35\nmcep: testing with order=14, α=0.0\nmcep: testing with order=14, α=0.35\nmcep: testing with order=14, α=0.41\nmcep: testing with order=14, α=0.544\nmcep: testing with order=16, α=-0.544\nmcep: testing with order=16, α=-0.41\nmcep: testing with order=16, α=-0.35\nmcep: testing with order=16, α=0.0\nmcep: testing with order=16, α=0.35\nmcep: testing with order=16, α=0.41\nmcep: testing with order=16, α=0.544\nmcep: testing with order=18, α=-0.544\nmcep: testing with order=18, α=-0.41\nmcep: testing with order=18, α=-0.35\nmcep: testing with order=18, α=0.0\nmcep: testing with order=18, α=0.35\nmcep: testing with order=18, α=0.41\nmcep: testing with order=18, α=0.544\nmcep: testing with order=20, α=-0.544\nmcep: testing with order=20, α=-0.41\nmcep: testing with order=20, α=-0.35\nmcep: testing with order=20, α=0.0\nmcep: testing with order=20, α=0.35\nmcep: testing with order=20, α=0.41\nmcep: testing with order=20, α=0.544\nmcep: testing with order=22, α=-0.544\nmcep: testing with order=22, α=-0.41\nmcep: testing with order=22, α=-0.35\nmcep: testing with order=22, α=0.0\nmcep: testing with order=22, α=0.35\nmcep: testing with order=22, α=0.41\nmcep: testing with order=22, α=0.544\nmcep: testing with order=24, α=-0.544\nmcep: testing with order=24, α=-0.41\nmcep: testing with order=24, α=-0.35\nmcep: testing with order=24, α=0.0\nmcep: testing with order=24, α=0.35\nmcep: testing with order=24, α=0.41\nmcep: testing with order=24, α=0.544\nmcep: testing with order=26, α=-0.544\nmcep: testing with order=26, α=-0.41\nmcep: testing with order=26, α=-0.35\nmcep: testing with order=26, α=0.0\nmcep: testing with order=26, α=0.35\nmcep: testing with order=26, α=0.41\nmcep: testing with order=26, α=0.544\nmcep: testing with order=28, α=-0.544\nmcep: testing with order=28, α=-0.41\nmcep: testing with order=28, α=-0.35\nmcep: testing with order=28, α=0.0\nmcep: testing with order=28, α=0.35\nmcep: testing with order=28, α=0.41\nmcep: testing with order=28, α=0.544\nmcep: testing with order=30, α=-0.544\nmcep: testing with order=30, α=-0.41\nmcep: testing with order=30, α=-0.35\nmcep: testing with order=30, α=0.0\nmcep: testing with order=30, α=0.35\nmcep: testing with order=30, α=0.41\nmcep: testing with order=30, α=0.544\nWARNING: Base.FloatingPoint is deprecated, use AbstractFloat instead.\nWARNING: Base.FloatingPoint is deprecated, use AbstractFloat instead.\nWARNING: Base.FloatingPoint is deprecated, use AbstractFloat instead.\nWARNING: Base.FloatingPoint is deprecated, use AbstractFloat instead.\nmgcep: testing with order=25, α=-0.544, γ=-1.0\nWARNING: Base.FloatingPoint is deprecated, use AbstractFloat instead.\nin _mgcep at :0\nWARNING: Base.FloatingPoint is deprecated, use AbstractFloat instead.\nin _mgcep at :0\nmgcep: testing with order=25, α=-0.544, γ=-0.75\nmgcep: testing with order=25, α=-0.544, γ=-0.5\nmgcep: testing with order=25, α=-0.544, γ=-0.25\nmgcep: testing with order=25, α=-0.544, γ=0.0\nmgcep: testing with order=25, α=-0.41, γ=-1.0\nmgcep: testing with order=25, α=-0.41, γ=-0.75\nmgcep: testing with order=25, α=-0.41, γ=-0.5\nmgcep: testing with order=25, α=-0.41, γ=-0.25\nmgcep: testing with order=25, α=-0.41, γ=0.0\nmgcep: testing with order=25, α=-0.35, γ=-1.0\nmgcep: testing with order=25, α=-0.35, γ=-0.75\nmgcep: testing with order=25, α=-0.35, γ=-0.5\nmgcep: testing with order=25, α=-0.35, γ=-0.25\nmgcep: testing with order=25, α=-0.35, γ=0.0\nmgcep: testing with order=25, α=0.0, γ=-1.0\nmgcep: testing with order=25, α=0.0, γ=-0.75\nmgcep: testing with order=25, α=0.0, γ=-0.5\nmgcep: testing with order=25, α=0.0, γ=-0.25\nmgcep: testing with order=25, α=0.0, γ=0.0\nmgcep: testing with order=25, α=0.35, γ=-1.0\nmgcep: testing with order=25, α=0.35, γ=-0.75\nmgcep: testing with order=25, α=0.35, γ=-0.5\nmgcep: testing with order=25, α=0.35, γ=-0.25\nmgcep: testing with order=25, α=0.35, γ=0.0\nmgcep: testing with order=25, α=0.41, γ=-1.0\nmgcep: testing with order=25, α=0.41, γ=-0.75\nmgcep: testing with order=25, α=0.41, γ=-0.5\nmgcep: testing with order=25, α=0.41, γ=-0.25\nmgcep: testing with order=25, α=0.41, γ=0.0\nmgcep: testing with order=25, α=0.544, γ=-1.0\nmgcep: testing with order=25, α=0.544, γ=-0.75\nmgcep: testing with order=25, α=0.544, γ=-0.5\nmgcep: testing with order=25, α=0.544, γ=-0.25\nmgcep: testing with order=25, α=0.544, γ=0.0\nmgcep: testing with order=30, α=-0.544, γ=-1.0\nmgcep: testing with order=30, α=-0.544, γ=-0.75\nmgcep: testing with order=30, α=-0.544, γ=-0.5\nmgcep: testing with order=30, α=-0.544, γ=-0.25\nmgcep: testing with order=30, α=-0.544, γ=0.0\nmgcep: testing with order=30, α=-0.41, γ=-1.0\nmgcep: testing with order=30, α=-0.41, γ=-0.75\nmgcep: testing with order=30, α=-0.41, γ=-0.5\nmgcep: testing with order=30, α=-0.41, γ=-0.25\nmgcep: testing with order=30, α=-0.41, γ=0.0\nmgcep: testing with order=30, α=-0.35, γ=-1.0\nmgcep: testing with order=30, α=-0.35, γ=-0.75\nmgcep: testing with order=30, α=-0.35, γ=-0.5\nmgcep: testing with order=30, α=-0.35, γ=-0.25\nmgcep: testing with order=30, α=-0.35, γ=0.0\nmgcep: testing with order=30, α=0.0, γ=-1.0\nmgcep: testing with order=30, α=0.0, γ=-0.75\nmgcep: testing with order=30, α=0.0, γ=-0.5\nmgcep: testing with order=30, α=0.0, γ=-0.25\nmgcep: testing with order=30, α=0.0, γ=0.0\nmgcep: testing with order=30, α=0.35, γ=-1.0\nmgcep: testing with order=30, α=0.35, γ=-0.75\nmgcep: testing with order=30, α=0.35, γ=-0.5\nmgcep: testing with order=30, α=0.35, γ=-0.25\nmgcep: testing with order=30, α=0.35, γ=0.0\nmgcep: testing with order=30, α=0.41, γ=-1.0\nmgcep: testing with order=30, α=0.41, γ=-0.75\nmgcep: testing with order=30, α=0.41, γ=-0.5\nmgcep: testing with order=30, α=0.41, γ=-0.25\nmgcep: testing with order=30, α=0.41, γ=0.0\nmgcep: testing with order=30, α=0.544, γ=-1.0\nmgcep: testing with order=30, α=0.544, γ=-0.75\nmgcep: testing with order=30, α=0.544, γ=-0.5\nmgcep: testing with order=30, α=0.544, γ=-0.25\nmgcep: testing with order=30, α=0.544, γ=0.0\nmgcep: testing with order=35, α=-0.544, γ=-1.0\nmgcep: testing with order=35, α=-0.544, γ=-0.75\nmgcep: testing with order=35, α=-0.544, γ=-0.5\nmgcep: testing with order=35, α=-0.544, γ=-0.25\nmgcep: testing with order=35, α=-0.544, γ=0.0\nmgcep: testing with order=35, α=-0.41, γ=-1.0\nmgcep: testing with order=35, α=-0.41, γ=-0.75\nmgcep: testing with order=35, α=-0.41, γ=-0.5\nmgcep: testing with order=35, α=-0.41, γ=-0.25\nmgcep: testing with order=35, α=-0.41, γ=0.0\nmgcep: testing with order=35, α=-0.35, γ=-1.0\nmgcep: testing with order=35, α=-0.35, γ=-0.75\nmgcep: testing with order=35, α=-0.35, γ=-0.5\nmgcep: testing with order=35, α=-0.35, γ=-0.25\nmgcep: testing with order=35, α=-0.35, γ=0.0\nmgcep: testing with order=35, α=0.0, γ=-1.0\nmgcep: testing with order=35, α=0.0, γ=-0.75\nmgcep: testing with order=35, α=0.0, γ=-0.5\nmgcep: testing with order=35, α=0.0, γ=-0.25\nmgcep: testing with order=35, α=0.0, γ=0.0\nmgcep: testing with order=35, α=0.35, γ=-1.0\nmgcep: testing with order=35, α=0.35, γ=-0.75\nmgcep: testing with order=35, α=0.35, γ=-0.5\nmgcep: testing with order=35, α=0.35, γ=-0.25\nmgcep: testing with order=35, α=0.35, γ=0.0\nmgcep: testing with order=35, α=0.41, γ=-1.0\nmgcep: testing with order=35, α=0.41, γ=-0.75\nmgcep: testing with order=35, α=0.41, γ=-0.5\nmgcep: testing with order=35, α=0.41, γ=-0.25\nmgcep: testing with order=35, α=0.41, γ=0.0\nmgcep: testing with order=35, α=0.544, γ=-1.0\nmgcep: testing with order=35, α=0.544, γ=-0.75\nmgcep: testing with order=35, α=0.544, γ=-0.5\nmgcep: testing with order=35, α=0.544, γ=-0.25\nmgcep: testing with order=35, α=0.544, γ=0.0\ngnorm: testing with γ=-1.0\ngnorm: testing with γ=-0.75\ngnorm: testing with γ=-0.5\ngnorm: testing with γ=-0.25\ngnorm: testing with γ=0.0\nignorm: testing with γ=-1.0\nignorm: testing with γ=-0.75\nignorm: testing with γ=-0.5\nignorm: testing with γ=-0.25\nignorm: testing with γ=0.0\nmc2b: testing with α=-0.544\nmc2b: testing with α=-0.41\nmc2b: testing with α=-0.35\nmc2b: testing with α=0.0\nmc2b: testing with α=0.35\nmc2b: testing with α=0.41\nmc2b: testing with α=0.544\nmc2b: testing with α=-0.544\nmc2b: testing with α=-0.41\nmc2b: testing with α=-0.35\nmc2b: testing with α=0.0\nmc2b: testing with α=0.35\nmc2b: testing with α=0.41\nmc2b: testing with α=0.544\nc2ir: testing with len=128\nc2ir: testing with len=256\nc2ir: testing with len=512\nc2ir: testing with len=1024\nfreqt: testing with order=10, α=-0.544\nfreqt: testing with order=10, α=-0.41\nfreqt: testing with order=10, α=-0.35\nfreqt: testing with order=10, α=0.0\nfreqt: testing with order=10, α=0.35\nfreqt: testing with order=10, α=0.41\nfreqt: testing with order=10, α=0.544\nfreqt: testing with order=12, α=-0.544\nfreqt: testing with order=12, α=-0.41\nfreqt: testing with order=12, α=-0.35\nfreqt: testing with order=12, α=0.0\nfreqt: testing with order=12, α=0.35\nfreqt: testing with order=12, α=0.41\nfreqt: testing with order=12, α=0.544\nfreqt: testing with order=14, α=-0.544\nfreqt: testing with order=14, α=-0.41\nfreqt: testing with order=14, α=-0.35\nfreqt: testing with order=14, α=0.0\nfreqt: testing with order=14, α=0.35\nfreqt: testing with order=14, α=0.41\nfreqt: testing with order=14, α=0.544\nfreqt: testing with order=16, α=-0.544\nfreqt: testing with order=16, α=-0.41\nfreqt: testing with order=16, α=-0.35\nfreqt: testing with order=16, α=0.0\nfreqt: testing with order=16, α=0.35\nfreqt: testing with order=16, α=0.41\nfreqt: testing with order=16, α=0.544\nfreqt: testing with order=18, α=-0.544\nfreqt: testing with order=18, α=-0.41\nfreqt: testing with order=18, α=-0.35\nfreqt: testing with order=18, α=0.0\nfreqt: testing with order=18, α=0.35\nfreqt: testing with order=18, α=0.41\nfreqt: testing with order=18, α=0.544\nfreqt: testing with order=20, α=-0.544\nfreqt: testing with order=20, α=-0.41\nfreqt: testing with order=20, α=-0.35\nfreqt: testing with order=20, α=0.0\nfreqt: testing with order=20, α=0.35\nfreqt: testing with order=20, α=0.41\nfreqt: testing with order=20, α=0.544\nfreqt: testing with order=22, α=-0.544\nfreqt: testing with order=22, α=-0.41\nfreqt: testing with order=22, α=-0.35\nfreqt: testing with order=22, α=0.0\nfreqt: testing with order=22, α=0.35\nfreqt: testing with order=22, α=0.41\nfreqt: testing with order=22, α=0.544\nfreqt: testing with order=24, α=-0.544\nfreqt: testing with order=24, α=-0.41\nfreqt: testing with order=24, α=-0.35\nfreqt: testing with order=24, α=0.0\nfreqt: testing with order=24, α=0.35\nfreqt: testing with order=24, α=0.41\nfreqt: testing with order=24, α=0.544\nfreqt: testing with order=26, α=-0.544\nfreqt: testing with order=26, α=-0.41\nfreqt: testing with order=26, α=-0.35\nfreqt: testing with order=26, α=0.0\nfreqt: testing with order=26, α=0.35\nfreqt: testing with order=26, α=0.41\nfreqt: testing with order=26, α=0.544\nfreqt: testing with order=28, α=-0.544\nfreqt: testing with order=28, α=-0.41\nfreqt: testing with order=28, α=-0.35\nfreqt: testing with order=28, α=0.0\nfreqt: testing with order=28, α=0.35\nfreqt: testing with order=28, α=0.41\nfreqt: testing with order=28, α=0.544\nfreqt: testing with order=30, α=-0.544\nfreqt: testing with order=30, α=-0.41\nfreqt: testing with order=30, α=-0.35\nfreqt: testing with order=30, α=0.0\nfreqt: testing with order=30, α=0.35\nfreqt: testing with order=30, α=0.41\nfreqt: testing with order=30, α=0.544\nb2c: testing with order=10, α=-0.544\nb2c: testing with order=10, α=-0.41\nb2c: testing with order=10, α=-0.35\nb2c: testing with order=10, α=0.0\nb2c: testing with order=10, α=0.35\nb2c: testing with order=10, α=0.41\nb2c: testing with order=10, α=0.544\nb2c: testing with order=12, α=-0.544\nb2c: testing with order=12, α=-0.41\nb2c: testing with order=12, α=-0.35\nb2c: testing with order=12, α=0.0\nb2c: testing with order=12, α=0.35\nb2c: testing with order=12, α=0.41\nb2c: testing with order=12, α=0.544\nb2c: testing with order=14, α=-0.544\nb2c: testing with order=14, α=-0.41\nb2c: testing with order=14, α=-0.35\nb2c: testing with order=14, α=0.0\nb2c: testing with order=14, α=0.35\nb2c: testing with order=14, α=0.41\nb2c: testing with order=14, α=0.544\nb2c: testing with order=16, α=-0.544\nb2c: testing with order=16, α=-0.41\nb2c: testing with order=16, α=-0.35\nb2c: testing with order=16, α=0.0\nb2c: testing with order=16, α=0.35\nb2c: testing with order=16, α=0.41\nb2c: testing with order=16, α=0.544\nb2c: testing with order=18, α=-0.544\nb2c: testing with order=18, α=-0.41\nb2c: testing with order=18, α=-0.35\nb2c: testing with order=18, α=0.0\nb2c: testing with order=18, α=0.35\nb2c: testing with order=18, α=0.41\nb2c: testing with order=18, α=0.544\nb2c: testing with order=20, α=-0.544\nb2c: testing with order=20, α=-0.41\nb2c: testing with order=20, α=-0.35\nb2c: testing with order=20, α=0.0\nb2c: testing with order=20, α=0.35\nb2c: testing with order=20, α=0.41\nb2c: testing with order=20, α=0.544\nb2c: testing with order=22, α=-0.544\nb2c: testing with order=22, α=-0.41\nb2c: testing with order=22, α=-0.35\nb2c: testing with order=22, α=0.0\nb2c: testing with order=22, α=0.35\nb2c: testing with order=22, α=0.41\nb2c: testing with order=22, α=0.544\nb2c: testing with order=24, α=-0.544\nb2c: testing with order=24, α=-0.41\nb2c: testing with order=24, α=-0.35\nb2c: testing with order=24, α=0.0\nb2c: testing with order=24, α=0.35\nb2c: testing with order=24, α=0.41\nb2c: testing with order=24, α=0.544\nb2c: testing with order=26, α=-0.544\nb2c: testing with order=26, α=-0.41\nb2c: testing with order=26, α=-0.35\nb2c: testing with order=26, α=0.0\nb2c: testing with order=26, α=0.35\nb2c: testing with order=26, α=0.41\nb2c: testing with order=26, α=0.544\nb2c: testing with order=28, α=-0.544\nb2c: testing with order=28, α=-0.41\nb2c: testing with order=28, α=-0.35\nb2c: testing with order=28, α=0.0\nb2c: testing with order=28, α=0.35\nb2c: testing with order=28, α=0.41\nb2c: testing with order=28, α=0.544\nb2c: testing with order=30, α=-0.544\nb2c: testing with order=30, α=-0.41\nb2c: testing with order=30, α=-0.35\nb2c: testing with order=30, α=0.0\nb2c: testing with order=30, α=0.35\nb2c: testing with order=30, α=0.41\nb2c: testing with order=30, α=0.544\nfrqtr: testing with order=10, α=-0.544\nfrqtr: testing with order=10, α=-0.41\nfrqtr: testing with order=10, α=-0.35\nfrqtr: testing with order=10, α=0.0\nfrqtr: testing with order=10, α=0.35\nfrqtr: testing with order=10, α=0.41\nfrqtr: testing with order=10, α=0.544\nfrqtr: testing with order=12, α=-0.544\nfrqtr: testing with order=12, α=-0.41\nfrqtr: testing with order=12, α=-0.35\nfrqtr: testing with order=12, α=0.0\nfrqtr: testing with order=12, α=0.35\nfrqtr: testing with order=12, α=0.41\nfrqtr: testing with order=12, α=0.544\nfrqtr: testing with order=14, α=-0.544\nfrqtr: testing with order=14, α=-0.41\nfrqtr: testing with order=14, α=-0.35\nfrqtr: testing with order=14, α=0.0\nfrqtr: testing with order=14, α=0.35\nfrqtr: testing with order=14, α=0.41\nfrqtr: testing with order=14, α=0.544\nfrqtr: testing with order=16, α=-0.544\nfrqtr: testing with order=16, α=-0.41\nfrqtr: testing with order=16, α=-0.35\nfrqtr: testing with order=16, α=0.0\nfrqtr: testing with order=16, α=0.35\nfrqtr: testing with order=16, α=0.41\nfrqtr: testing with order=16, α=0.544\nfrqtr: testing with order=18, α=-0.544\nfrqtr: testing with order=18, α=-0.41\nfrqtr: testing with order=18, α=-0.35\nfrqtr: testing with order=18, α=0.0\nfrqtr: testing with order=18, α=0.35\nfrqtr: testing with order=18, α=0.41\nfrqtr: testing with order=18, α=0.544\nfrqtr: testing with order=20, α=-0.544\nfrqtr: testing with order=20, α=-0.41\nfrqtr: testing with order=20, α=-0.35\nfrqtr: testing with order=20, α=0.0\nfrqtr: testing with order=20, α=0.35\nfrqtr: testing with order=20, α=0.41\nfrqtr: testing with order=20, α=0.544\nfrqtr: testing with order=22, α=-0.544\nfrqtr: testing with order=22, α=-0.41\nfrqtr: testing with order=22, α=-0.35\nfrqtr: testing with order=22, α=0.0\nfrqtr: testing with order=22, α=0.35\nfrqtr: testing with order=22, α=0.41\nfrqtr: testing with order=22, α=0.544\nfrqtr: testing with order=24, α=-0.544\nfrqtr: testing with order=24, α=-0.41\nfrqtr: testing with order=24, α=-0.35\nfrqtr: testing with order=24, α=0.0\nfrqtr: testing with order=24, α=0.35\nfrqtr: testing with order=24, α=0.41\nfrqtr: testing with order=24, α=0.544\nfrqtr: testing with order=26, α=-0.544\nfrqtr: testing with order=26, α=-0.41\nfrqtr: testing with order=26, α=-0.35\nfrqtr: testing with order=26, α=0.0\nfrqtr: testing with order=26, α=0.35\nfrqtr: testing with order=26, α=0.41\nfrqtr: testing with order=26, α=0.544\nfrqtr: testing with order=28, α=-0.544\nfrqtr: testing with order=28, α=-0.41\nfrqtr: testing with order=28, α=-0.35\nfrqtr: testing with order=28, α=0.0\nfrqtr: testing with order=28, α=0.35\nfrqtr: testing with order=28, α=0.41\nfrqtr: testing with order=28, α=0.544\nfrqtr: testing with order=30, α=-0.544\nfrqtr: testing with order=30, α=-0.41\nfrqtr: testing with order=30, α=-0.35\nfrqtr: testing with order=30, α=0.0\nfrqtr: testing with order=30, α=0.35\nfrqtr: testing with order=30, α=0.41\nfrqtr: testing with order=30, α=0.544\ngc2gc: testing with order=15, γ=-1.0\ngc2gc: testing with order=15, γ=-0.75\ngc2gc: testing with order=15, γ=-0.5\ngc2gc: testing with order=15, γ=-0.25\ngc2gc: testing with order=15, γ=0.0\ngc2gc: testing with order=20, γ=-1.0\ngc2gc: testing with order=20, γ=-0.75\ngc2gc: testing with order=20, γ=-0.5\ngc2gc: testing with order=20, γ=-0.25\ngc2gc: testing with order=20, γ=0.0\ngc2gc: testing with order=25, γ=-1.0\ngc2gc: testing with order=25, γ=-0.75\ngc2gc: testing with order=25, γ=-0.5\ngc2gc: testing with order=25, γ=-0.25\ngc2gc: testing with order=25, γ=0.0\ngc2gc: testing with order=30, γ=-1.0\ngc2gc: testing with order=30, γ=-0.75\ngc2gc: testing with order=30, γ=-0.5\ngc2gc: testing with order=30, γ=-0.25\ngc2gc: testing with order=30, γ=0.0\ngc2gc: testing with order=35, γ=-1.0\ngc2gc: testing with order=35, γ=-0.75\ngc2gc: testing with order=35, γ=-0.5\ngc2gc: testing with order=35, γ=-0.25\ngc2gc: testing with order=35, γ=0.0\nmgc2mgc: testing with order=15, α=-0.544, γ=-1.0\nmgc2mgc: testing with order=15, α=-0.544, γ=-0.75\nmgc2mgc: testing with order=15, α=-0.544, γ=-0.5\nmgc2mgc: testing with order=15, α=-0.544, γ=-0.25\nmgc2mgc: testing with order=15, α=-0.544, γ=0.0\nmgc2mgc: testing with order=15, α=-0.41, γ=-1.0\nmgc2mgc: testing with order=15, α=-0.41, γ=-0.75\nmgc2mgc: testing with order=15, α=-0.41, γ=-0.5\nmgc2mgc: testing with order=15, α=-0.41, γ=-0.25\nmgc2mgc: testing with order=15, α=-0.41, γ=0.0\nmgc2mgc: testing with order=15, α=-0.35, γ=-1.0\nmgc2mgc: testing with order=15, α=-0.35, γ=-0.75\nmgc2mgc: testing with order=15, α=-0.35, γ=-0.5\nmgc2mgc: testing with order=15, α=-0.35, γ=-0.25\nmgc2mgc: testing with order=15, α=-0.35, γ=0.0\nmgc2mgc: testing with order=15, α=0.35, γ=-1.0\nmgc2mgc: testing with order=15, α=0.35, γ=-0.75\nmgc2mgc: testing with order=15, α=0.35, γ=-0.5\nmgc2mgc: testing with order=15, α=0.35, γ=-0.25\nmgc2mgc: testing with order=15, α=0.35, γ=0.0\nmgc2mgc: testing with order=15, α=0.41, γ=-1.0\nmgc2mgc: testing with order=15, α=0.41, γ=-0.75\nmgc2mgc: testing with order=15, α=0.41, γ=-0.5\nmgc2mgc: testing with order=15, α=0.41, γ=-0.25\nmgc2mgc: testing with order=15, α=0.41, γ=0.0\nmgc2mgc: testing with order=15, α=0.544, γ=-1.0\nmgc2mgc: testing with order=15, α=0.544, γ=-0.75\nmgc2mgc: testing with order=15, α=0.544, γ=-0.5\nmgc2mgc: testing with order=15, α=0.544, γ=-0.25\nmgc2mgc: testing with order=15, α=0.544, γ=0.0\nmgc2mgc: testing with order=20, α=-0.544, γ=-1.0\nmgc2mgc: testing with order=20, α=-0.544, γ=-0.75\nmgc2mgc: testing with order=20, α=-0.544, γ=-0.5\nmgc2mgc: testing with order=20, α=-0.544, γ=-0.25\nmgc2mgc: testing with order=20, α=-0.544, γ=0.0\nmgc2mgc: testing with order=20, α=-0.41, γ=-1.0\nmgc2mgc: testing with order=20, α=-0.41, γ=-0.75\nmgc2mgc: testing with order=20, α=-0.41, γ=-0.5\nmgc2mgc: testing with order=20, α=-0.41, γ=-0.25\nmgc2mgc: testing with order=20, α=-0.41, γ=0.0\nmgc2mgc: testing with order=20, α=-0.35, γ=-1.0\nmgc2mgc: testing with order=20, α=-0.35, γ=-0.75\nmgc2mgc: testing with order=20, α=-0.35, γ=-0.5\nmgc2mgc: testing with order=20, α=-0.35, γ=-0.25\nmgc2mgc: testing with order=20, α=-0.35, γ=0.0\nmgc2mgc: testing with order=20, α=0.35, γ=-1.0\nmgc2mgc: testing with order=20, α=0.35, γ=-0.75\nmgc2mgc: testing with order=20, α=0.35, γ=-0.5\nmgc2mgc: testing with order=20, α=0.35, γ=-0.25\nmgc2mgc: testing with order=20, α=0.35, γ=0.0\nmgc2mgc: testing with order=20, α=0.41, γ=-1.0\nmgc2mgc: testing with order=20, α=0.41, γ=-0.75\nmgc2mgc: testing with order=20, α=0.41, γ=-0.5\nmgc2mgc: testing with order=20, α=0.41, γ=-0.25\nmgc2mgc: testing with order=20, α=0.41, γ=0.0\nmgc2mgc: testing with order=20, α=0.544, γ=-1.0\nmgc2mgc: testing with order=20, α=0.544, γ=-0.75\nmgc2mgc: testing with order=20, α=0.544, γ=-0.5\nmgc2mgc: testing with order=20, α=0.544, γ=-0.25\nmgc2mgc: testing with order=20, α=0.544, γ=0.0\nmgc2mgc: testing with order=25, α=-0.544, γ=-1.0\nmgc2mgc: testing with order=25, α=-0.544, γ=-0.75\nmgc2mgc: testing with order=25, α=-0.544, γ=-0.5\nmgc2mgc: testing with order=25, α=-0.544, γ=-0.25\nmgc2mgc: testing with order=25, α=-0.544, γ=0.0\nmgc2mgc: testing with order=25, α=-0.41, γ=-1.0\nmgc2mgc: testing with order=25, α=-0.41, γ=-0.75\nmgc2mgc: testing with order=25, α=-0.41, γ=-0.5\nmgc2mgc: testing with order=25, α=-0.41, γ=-0.25\nmgc2mgc: testing with order=25, α=-0.41, γ=0.0\nmgc2mgc: testing with order=25, α=-0.35, γ=-1.0\nmgc2mgc: testing with order=25, α=-0.35, γ=-0.75\nmgc2mgc: testing with order=25, α=-0.35, γ=-0.5\nmgc2mgc: testing with order=25, α=-0.35, γ=-0.25\nmgc2mgc: testing with order=25, α=-0.35, γ=0.0\nmgc2mgc: testing with order=25, α=0.35, γ=-1.0\nmgc2mgc: testing with order=25, α=0.35, γ=-0.75\nmgc2mgc: testing with order=25, α=0.35, γ=-0.5\nmgc2mgc: testing with order=25, α=0.35, γ=-0.25\nmgc2mgc: testing with order=25, α=0.35, γ=0.0\nmgc2mgc: testing with order=25, α=0.41, γ=-1.0\nmgc2mgc: testing with order=25, α=0.41, γ=-0.75\nmgc2mgc: testing with order=25, α=0.41, γ=-0.5\nmgc2mgc: testing with order=25, α=0.41, γ=-0.25\nmgc2mgc: testing with order=25, α=0.41, γ=0.0\nmgc2mgc: testing with order=25, α=0.544, γ=-1.0\nmgc2mgc: testing with order=25, α=0.544, γ=-0.75\nmgc2mgc: testing with order=25, α=0.544, γ=-0.5\nmgc2mgc: testing with order=25, α=0.544, γ=-0.25\nmgc2mgc: testing with order=25, α=0.544, γ=0.0\nmgc2mgc: testing with order=30, α=-0.544, γ=-1.0\nmgc2mgc: testing with order=30, α=-0.544, γ=-0.75\nmgc2mgc: testing with order=30, α=-0.544, γ=-0.5\nmgc2mgc: testing with order=30, α=-0.544, γ=-0.25\nmgc2mgc: testing with order=30, α=-0.544, γ=0.0\nmgc2mgc: testing with order=30, α=-0.41, γ=-1.0\nmgc2mgc: testing with order=30, α=-0.41, γ=-0.75\nmgc2mgc: testing with order=30, α=-0.41, γ=-0.5\nmgc2mgc: testing with order=30, α=-0.41, γ=-0.25\nmgc2mgc: testing with order=30, α=-0.41, γ=0.0\nmgc2mgc: testing with order=30, α=-0.35, γ=-1.0\nmgc2mgc: testing with order=30, α=-0.35, γ=-0.75\nmgc2mgc: testing with order=30, α=-0.35, γ=-0.5\nmgc2mgc: testing with order=30, α=-0.35, γ=-0.25\nmgc2mgc: testing with order=30, α=-0.35, γ=0.0\nmgc2mgc: testing with order=30, α=0.35, γ=-1.0\nmgc2mgc: testing with order=30, α=0.35, γ=-0.75\nmgc2mgc: testing with order=30, α=0.35, γ=-0.5\nmgc2mgc: testing with order=30, α=0.35, γ=-0.25\nmgc2mgc: testing with order=30, α=0.35, γ=0.0\nmgc2mgc: testing with order=30, α=0.41, γ=-1.0\nmgc2mgc: testing with order=30, α=0.41, γ=-0.75\nmgc2mgc: testing with order=30, α=0.41, γ=-0.5\nmgc2mgc: testing with order=30, α=0.41, γ=-0.25\nmgc2mgc: testing with order=30, α=0.41, γ=0.0\nmgc2mgc: testing with order=30, α=0.544, γ=-1.0\nmgc2mgc: testing with order=30, α=0.544, γ=-0.75\nmgc2mgc: testing with order=30, α=0.544, γ=-0.5\nmgc2mgc: testing with order=30, α=0.544, γ=-0.25\nmgc2mgc: testing with order=30, α=0.544, γ=0.0\nmgc2mgc: testing with order=35, α=-0.544, γ=-1.0\nmgc2mgc: testing with order=35, α=-0.544, γ=-0.75\nmgc2mgc: testing with order=35, α=-0.544, γ=-0.5\nmgc2mgc: testing with order=35, α=-0.544, γ=-0.25\nmgc2mgc: testing with order=35, α=-0.544, γ=0.0\nmgc2mgc: testing with order=35, α=-0.41, γ=-1.0\nmgc2mgc: testing with order=35, α=-0.41, γ=-0.75\nmgc2mgc: testing with order=35, α=-0.41, γ=-0.5\nmgc2mgc: testing with order=35, α=-0.41, γ=-0.25\nmgc2mgc: testing with order=35, α=-0.41, γ=0.0\nmgc2mgc: testing with order=35, α=-0.35, γ=-1.0\nmgc2mgc: testing with order=35, α=-0.35, γ=-0.75\nmgc2mgc: testing with order=35, α=-0.35, γ=-0.5\nmgc2mgc: testing with order=35, α=-0.35, γ=-0.25\nmgc2mgc: testing with order=35, α=-0.35, γ=0.0\nmgc2mgc: testing with order=35, α=0.35, γ=-1.0\nmgc2mgc: testing with order=35, α=0.35, γ=-0.75\nmgc2mgc: testing with order=35, α=0.35, γ=-0.5\nmgc2mgc: testing with order=35, α=0.35, γ=-0.25\nmgc2mgc: testing with order=35, α=0.35, γ=0.0\nmgc2mgc: testing with order=35, α=0.41, γ=-1.0\nmgc2mgc: testing with order=35, α=0.41, γ=-0.75\nmgc2mgc: testing with order=35, α=0.41, γ=-0.5\nmgc2mgc: testing with order=35, α=0.41, γ=-0.25\nmgc2mgc: testing with order=35, α=0.41, γ=0.0\nmgc2mgc: testing with order=35, α=0.544, γ=-1.0\nmgc2mgc: testing with order=35, α=0.544, γ=-0.75\nmgc2mgc: testing with order=35, α=0.544, γ=-0.5\nmgc2mgc: testing with order=35, α=0.544, γ=-0.25\nmgc2mgc: testing with order=35, α=0.544, γ=0.0\nmgc2sp: testing with α=-0.544 and γ=-0.75\nmgc2sp: testing with α=-0.544 and γ=-0.5\nmgc2sp: testing with α=-0.544 and γ=-0.25\nmgc2sp: testing with α=-0.544 and γ=0.0\nmgc2sp: testing with α=-0.41 and γ=-0.75\nmgc2sp: testing with α=-0.41 and γ=-0.5\nmgc2sp: testing with α=-0.41 and γ=-0.25\nmgc2sp: testing with α=-0.41 and γ=0.0\nmgc2sp: testing with α=-0.35 and γ=-0.75\nmgc2sp: testing with α=-0.35 and γ=-0.5\nmgc2sp: testing with α=-0.35 and γ=-0.25\nmgc2sp: testing with α=-0.35 and γ=0.0\nmgc2sp: testing with α=0.35 and γ=-0.75\nmgc2sp: testing with α=0.35 and γ=-0.5\nmgc2sp: testing with α=0.35 and γ=-0.25\nmgc2sp: testing with α=0.35 and γ=0.0\nmgc2sp: testing with α=0.41 and γ=-0.75\nmgc2sp: testing with α=0.41 and γ=-0.5\nmgc2sp: testing with α=0.41 and γ=-0.25\nmgc2sp: testing with α=0.41 and γ=0.0\nmgc2sp: testing with α=0.544 and γ=-0.75\nmgc2sp: testing with α=0.544 and γ=-0.5\nmgc2sp: testing with α=0.544 and γ=-0.25\nmgc2sp: testing with α=0.544 and γ=0.0\nlpc2c: testing\ntesting: spectral param state\ntesting: gcep\ntesting: gcep\ntesting: mgcep\nmgcep: testing with α=-0.35 and γ=-1.0\nmgcep: testing with α=-0.35 and γ=-0.5\nmgcep: testing with α=-0.35 and γ=0.0\nmgcep: testing with α=0.0 and γ=-1.0\nmgcep: testing with α=0.0 and γ=-0.5\nmgcep: testing with α=0.0 and γ=0.0\nmgcep: testing with α=0.35 and γ=-1.0\nmgcep: testing with α=0.35 and γ=-0.5\nmgcep: testing with α=0.35 and γ=0.0\ntesting: mcepalpha\nWARNING: Base.FloatingPoint is deprecated, use AbstractFloat instead.\nWARNING: Base.FloatingPoint is deprecated, use AbstractFloat instead.\nWARNING: Base.FloatingPoint is deprecated, use AbstractFloat instead.\nWARNING: Base.FloatingPoint is deprecated, use AbstractFloat instead.\nlpc2c: testing with order=15\nlpc2c: testing with order=20\nlpc2c: testing with order=25\nmc2b: testing with order=15, α=0.0\nmc2b: testing with order=15, α=0.35\nmc2b: testing with order=20, α=0.0\nmc2b: testing with order=20, α=0.35\nmc2b: testing with order=25, α=0.0\nmc2b: testing with order=25, α=0.35\ntesting: mc2b exceptions\nmc2e: testing with order=20, α=0.0, fftlen=256\nmc2e: testing with order=20, α=0.0, fftlen=512\nmc2e: testing with order=20, α=0.35, fftlen=256\nmc2e: testing with order=20, α=0.35, fftlen=512\nmc2e: testing with order=20, α=0.41, fftlen=256\nmc2e: testing with order=20, α=0.41, fftlen=512\nmc2e: testing with order=20, α=0.544, fftlen=256\nmc2e: testing with order=20, α=0.544, fftlen=512\nmc2e: testing with order=25, α=0.0, fftlen=256\nmc2e: testing with order=25, α=0.0, fftlen=512\nmc2e: testing with order=25, α=0.35, fftlen=256\nmc2e: testing with order=25, α=0.35, fftlen=512\nmc2e: testing with order=25, α=0.41, fftlen=256\nmc2e: testing with order=25, α=0.41, fftlen=512\nmc2e: testing with order=25, α=0.544, fftlen=256\nmc2e: testing with order=25, α=0.544, fftlen=512\nmc2e: testing with order=30, α=0.0, fftlen=256\nmc2e: testing with order=30, α=0.0, fftlen=512\nmc2e: testing with order=30, α=0.35, fftlen=256\nmc2e: testing with order=30, α=0.35, fftlen=512\nmc2e: testing with order=30, α=0.41, fftlen=256\nmc2e: testing with order=30, α=0.41, fftlen=512\nmc2e: testing with order=30, α=0.544, fftlen=256\nmc2e: testing with order=30, α=0.544, fftlen=512\ntesting: mc2e exceptions\nmgc2b: testing with order=20, α=-0.554, γ=-1.0\nmgc2b: testing with order=20, α=-0.554, γ=-0.5\nmgc2b: testing with order=20, α=-0.554, γ=0.0\nmgc2b: testing with order=20, α=-0.41, γ=-1.0\nmgc2b: testing with order=20, α=-0.41, γ=-0.5\nmgc2b: testing with order=20, α=-0.41, γ=0.0\nmgc2b: testing with order=20, α=0.0, γ=-1.0\nmgc2b: testing with order=20, α=0.0, γ=-0.5\nmgc2b: testing with order=20, α=0.0, γ=0.0\nmgc2b: testing with order=20, α=0.41, γ=-1.0\nmgc2b: testing with order=20, α=0.41, γ=-0.5\nmgc2b: testing with order=20, α=0.41, γ=0.0\nmgc2b: testing with order=20, α=0.544, γ=-1.0\nmgc2b: testing with order=20, α=0.544, γ=-0.5\nmgc2b: testing with order=20, α=0.544, γ=0.0\nmgc2b: testing with order=25, α=-0.554, γ=-1.0\nmgc2b: testing with order=25, α=-0.554, γ=-0.5\nmgc2b: testing with order=25, α=-0.554, γ=0.0\nmgc2b: testing with order=25, α=-0.41, γ=-1.0\nmgc2b: testing with order=25, α=-0.41, γ=-0.5\nmgc2b: testing with order=25, α=-0.41, γ=0.0\nmgc2b: testing with order=25, α=0.0, γ=-1.0\nmgc2b: testing with order=25, α=0.0, γ=-0.5\nmgc2b: testing with order=25, α=0.0, γ=0.0\nmgc2b: testing with order=25, α=0.41, γ=-1.0\nmgc2b: testing with order=25, α=0.41, γ=-0.5\nmgc2b: testing with order=25, α=0.41, γ=0.0\nmgc2b: testing with order=25, α=0.544, γ=-1.0\nmgc2b: testing with order=25, α=0.544, γ=-0.5\nmgc2b: testing with order=25, α=0.544, γ=0.0\nmgc2b: testing with order=30, α=-0.554, γ=-1.0\nmgc2b: testing with order=30, α=-0.554, γ=-0.5\nmgc2b: testing with order=30, α=-0.554, γ=0.0\nmgc2b: testing with order=30, α=-0.41, γ=-1.0\nmgc2b: testing with order=30, α=-0.41, γ=-0.5\nmgc2b: testing with order=30, α=-0.41, γ=0.0\nmgc2b: testing with order=30, α=0.0, γ=-1.0\nmgc2b: testing with order=30, α=0.0, γ=-0.5\nmgc2b: testing with order=30, α=0.0, γ=0.0\nmgc2b: testing with order=30, α=0.41, γ=-1.0\nmgc2b: testing with order=30, α=0.41, γ=-0.5\nmgc2b: testing with order=30, α=0.41, γ=0.0\nmgc2b: testing with order=30, α=0.544, γ=-1.0\nmgc2b: testing with order=30, α=0.544, γ=-0.5\nmgc2b: testing with order=30, α=0.544, γ=0.0\ntesting: mgc2b exceptions\nmgc2sp: testing with order=20, α=-0.554, γ=-1.0, fftlen=256\nmgc2sp: testing with order=20, α=-0.554, γ=-1.0, fftlen=512\nmgc2sp: testing with order=20, α=-0.554, γ=-0.5, fftlen=256\nmgc2sp: testing with order=20, α=-0.554, γ=-0.5, fftlen=512\nmgc2sp: testing with order=20, α=-0.554, γ=0.0, fftlen=256\nmgc2sp: testing with order=20, α=-0.554, γ=0.0, fftlen=512\nmgc2sp: testing with order=20, α=-0.41, γ=-1.0, fftlen=256\nmgc2sp: testing with order=20, α=-0.41, γ=-1.0, fftlen=512\nmgc2sp: testing with order=20, α=-0.41, γ=-0.5, fftlen=256\nmgc2sp: testing with order=20, α=-0.41, γ=-0.5, fftlen=512\nmgc2sp: testing with order=20, α=-0.41, γ=0.0, fftlen=256\nmgc2sp: testing with order=20, α=-0.41, γ=0.0, fftlen=512\nmgc2sp: testing with order=20, α=0.0, γ=-1.0, fftlen=256\nmgc2sp: testing with order=20, α=0.0, γ=-1.0, fftlen=512\nmgc2sp: testing with order=20, α=0.0, γ=-0.5, fftlen=256\nmgc2sp: testing with order=20, α=0.0, γ=-0.5, fftlen=512\nmgc2sp: testing with order=20, α=0.0, γ=0.0, fftlen=256\nmgc2sp: testing with order=20, α=0.0, γ=0.0, fftlen=512\nmgc2sp: testing with order=20, α=0.41, γ=-1.0, fftlen=256\nmgc2sp: testing with order=20, α=0.41, γ=-1.0, fftlen=512\nmgc2sp: testing with order=20, α=0.41, γ=-0.5, fftlen=256\nmgc2sp: testing with order=20, α=0.41, γ=-0.5, fftlen=512\nmgc2sp: testing with order=20, α=0.41, γ=0.0, fftlen=256\nmgc2sp: testing with order=20, α=0.41, γ=0.0, fftlen=512\nmgc2sp: testing with order=20, α=0.544, γ=-1.0, fftlen=256\nmgc2sp: testing with order=20, α=0.544, γ=-1.0, fftlen=512\nmgc2sp: testing with order=20, α=0.544, γ=-0.5, fftlen=256\nmgc2sp: testing with order=20, α=0.544, γ=-0.5, fftlen=512\nmgc2sp: testing with order=20, α=0.544, γ=0.0, fftlen=256\nmgc2sp: testing with order=20, α=0.544, γ=0.0, fftlen=512\nmgc2sp: testing with order=25, α=-0.554, γ=-1.0, fftlen=256\nmgc2sp: testing with order=25, α=-0.554, γ=-1.0, fftlen=512\nmgc2sp: testing with order=25, α=-0.554, γ=-0.5, fftlen=256\nmgc2sp: testing with order=25, α=-0.554, γ=-0.5, fftlen=512\nmgc2sp: testing with order=25, α=-0.554, γ=0.0, fftlen=256\nmgc2sp: testing with order=25, α=-0.554, γ=0.0, fftlen=512\nmgc2sp: testing with order=25, α=-0.41, γ=-1.0, fftlen=256\nmgc2sp: testing with order=25, α=-0.41, γ=-1.0, fftlen=512\nmgc2sp: testing with order=25, α=-0.41, γ=-0.5, fftlen=256\nmgc2sp: testing with order=25, α=-0.41, γ=-0.5, fftlen=512\nmgc2sp: testing with order=25, α=-0.41, γ=0.0, fftlen=256\nmgc2sp: testing with order=25, α=-0.41, γ=0.0, fftlen=512\nmgc2sp: testing with order=25, α=0.0, γ=-1.0, fftlen=256\nmgc2sp: testing with order=25, α=0.0, γ=-1.0, fftlen=512\nmgc2sp: testing with order=25, α=0.0, γ=-0.5, fftlen=256\nmgc2sp: testing with order=25, α=0.0, γ=-0.5, fftlen=512\nmgc2sp: testing with order=25, α=0.0, γ=0.0, fftlen=256\nmgc2sp: testing with order=25, α=0.0, γ=0.0, fftlen=512\nmgc2sp: testing with order=25, α=0.41, γ=-1.0, fftlen=256\nmgc2sp: testing with order=25, α=0.41, γ=-1.0, fftlen=512\nmgc2sp: testing with order=25, α=0.41, γ=-0.5, fftlen=256\nmgc2sp: testing with order=25, α=0.41, γ=-0.5, fftlen=512\nmgc2sp: testing with order=25, α=0.41, γ=0.0, fftlen=256\nmgc2sp: testing with order=25, α=0.41, γ=0.0, fftlen=512\nmgc2sp: testing with order=25, α=0.544, γ=-1.0, fftlen=256\nmgc2sp: testing with order=25, α=0.544, γ=-1.0, fftlen=512\nmgc2sp: testing with order=25, α=0.544, γ=-0.5, fftlen=256\nmgc2sp: testing with order=25, α=0.544, γ=-0.5, fftlen=512\nmgc2sp: testing with order=25, α=0.544, γ=0.0, fftlen=256\nmgc2sp: testing with order=25, α=0.544, γ=0.0, fftlen=512\nmgc2sp: testing with order=30, α=-0.554, γ=-1.0, fftlen=256\nmgc2sp: testing with order=30, α=-0.554, γ=-1.0, fftlen=512\nmgc2sp: testing with order=30, α=-0.554, γ=-0.5, fftlen=256\nmgc2sp: testing with order=30, α=-0.554, γ=-0.5, fftlen=512\nmgc2sp: testing with order=30, α=-0.554, γ=0.0, fftlen=256\nmgc2sp: testing with order=30, α=-0.554, γ=0.0, fftlen=512\nmgc2sp: testing with order=30, α=-0.41, γ=-1.0, fftlen=256\nmgc2sp: testing with order=30, α=-0.41, γ=-1.0, fftlen=512\nmgc2sp: testing with order=30, α=-0.41, γ=-0.5, fftlen=256\nmgc2sp: testing with order=30, α=-0.41, γ=-0.5, fftlen=512\nmgc2sp: testing with order=30, α=-0.41, γ=0.0, fftlen=256\nmgc2sp: testing with order=30, α=-0.41, γ=0.0, fftlen=512\nmgc2sp: testing with order=30, α=0.0, γ=-1.0, fftlen=256\nmgc2sp: testing with order=30, α=0.0, γ=-1.0, fftlen=512\nmgc2sp: testing with order=30, α=0.0, γ=-0.5, fftlen=256\nmgc2sp: testing with order=30, α=0.0, γ=-0.5, fftlen=512\nmgc2sp: testing with order=30, α=0.0, γ=0.0, fftlen=256\nmgc2sp: testing with order=30, α=0.0, γ=0.0, fftlen=512\nmgc2sp: testing with order=30, α=0.41, γ=-1.0, fftlen=256\nmgc2sp: testing with order=30, α=0.41, γ=-1.0, fftlen=512\nmgc2sp: testing with order=30, α=0.41, γ=-0.5, fftlen=256\nmgc2sp: testing with order=30, α=0.41, γ=-0.5, fftlen=512\nmgc2sp: testing with order=30, α=0.41, γ=0.0, fftlen=256\nmgc2sp: testing with order=30, α=0.41, γ=0.0, fftlen=512\nmgc2sp: testing with order=30, α=0.544, γ=-1.0, fftlen=256\nmgc2sp: testing with order=30, α=0.544, γ=-1.0, fftlen=512\nmgc2sp: testing with order=30, α=0.544, γ=-0.5, fftlen=256\nmgc2sp: testing with order=30, α=0.544, γ=-0.5, fftlen=512\nmgc2sp: testing with order=30, α=0.544, γ=0.0, fftlen=256\nmgc2sp: testing with order=30, α=0.544, γ=0.0, fftlen=512\ntesting: mgc2sp exceptions\nb2mc: testing with order=15, α=0.0\nb2mc: testing with order=15, α=0.35\nb2mc: testing with order=20, α=0.0\nb2mc: testing with order=20, α=0.35\nb2mc: testing with order=25, α=0.0\nb2mc: testing with order=25, α=0.35\ntesting: b2mc exceptions\ngnorm and ignorm: testing with order=20, γ=-1.0\ngnorm and ignorm: testing with order=20, γ=-0.5\ngnorm and ignorm: testing with order=20, γ=0.0\ngnorm and ignorm: testing with order=25, γ=-1.0\ngnorm and ignorm: testing with order=25, γ=-0.5\ngnorm and ignorm: testing with order=25, γ=0.0\ngnorm and ignorm: testing with order=30, γ=-1.0\ngnorm and ignorm: testing with order=30, γ=-0.5\ngnorm and ignorm: testing with order=30, γ=0.0\ntesting: gnorm and ignorm exceptions\nfreqt: testing with src_order=15, src_α=0.0, dst_order=15, dst_α=0.0\nfreqt: testing with src_order=15, src_α=0.0, dst_order=15, dst_α=0.35\nfreqt: testing with src_order=15, src_α=0.0, dst_order=20, dst_α=0.0\nfreqt: testing with src_order=15, src_α=0.0, dst_order=20, dst_α=0.35\nfreqt: testing with src_order=15, src_α=0.0, dst_order=25, dst_α=0.0\nfreqt: testing with src_order=15, src_α=0.0, dst_order=25, dst_α=0.35\nfreqt: testing with src_order=15, src_α=0.35, dst_order=15, dst_α=0.0\nfreqt: testing with src_order=15, src_α=0.35, dst_order=15, dst_α=0.35\nfreqt: testing with src_order=15, src_α=0.35, dst_order=20, dst_α=0.0\nfreqt: testing with src_order=15, src_α=0.35, dst_order=20, dst_α=0.35\nfreqt: testing with src_order=15, src_α=0.35, dst_order=25, dst_α=0.0\nfreqt: testing with src_order=15, src_α=0.35, dst_order=25, dst_α=0.35\nfreqt: testing with src_order=20, src_α=0.0, dst_order=15, dst_α=0.0\nfreqt: testing with src_order=20, src_α=0.0, dst_order=15, dst_α=0.35\nfreqt: testing with src_order=20, src_α=0.0, dst_order=20, dst_α=0.0\nfreqt: testing with src_order=20, src_α=0.0, dst_order=20, dst_α=0.35\nfreqt: testing with src_order=20, src_α=0.0, dst_order=25, dst_α=0.0\nfreqt: testing with src_order=20, src_α=0.0, dst_order=25, dst_α=0.35\nfreqt: testing with src_order=20, src_α=0.35, dst_order=15, dst_α=0.0\nfreqt: testing with src_order=20, src_α=0.35, dst_order=15, dst_α=0.35\nfreqt: testing with src_order=20, src_α=0.35, dst_order=20, dst_α=0.0\nfreqt: testing with src_order=20, src_α=0.35, dst_order=20, dst_α=0.35\nfreqt: testing with src_order=20, src_α=0.35, dst_order=25, dst_α=0.0\nfreqt: testing with src_order=20, src_α=0.35, dst_order=25, dst_α=0.35\nfreqt: testing with src_order=25, src_α=0.0, dst_order=15, dst_α=0.0\nfreqt: testing with src_order=25, src_α=0.0, dst_order=15, dst_α=0.35\nfreqt: testing with src_order=25, src_α=0.0, dst_order=20, dst_α=0.0\nfreqt: testing with src_order=25, src_α=0.0, dst_order=20, dst_α=0.35\nfreqt: testing with src_order=25, src_α=0.0, dst_order=25, dst_α=0.0\nfreqt: testing with src_order=25, src_α=0.0, dst_order=25, dst_α=0.35\nfreqt: testing with src_order=25, src_α=0.35, dst_order=15, dst_α=0.0\nfreqt: testing with src_order=25, src_α=0.35, dst_order=15, dst_α=0.35\nfreqt: testing with src_order=25, src_α=0.35, dst_order=20, dst_α=0.0\nfreqt: testing with src_order=25, src_α=0.35, dst_order=20, dst_α=0.35\nfreqt: testing with src_order=25, src_α=0.35, dst_order=25, dst_α=0.0\nfreqt: testing with src_order=25, src_α=0.35, dst_order=25, dst_α=0.35\ntesting: freqt exceptions\ngc2gc: testing with src_order=15, src_α=0.0, src_γ=-1.0, dst_order=15, dst_γ=-1.0\ngc2gc: testing with src_order=15, src_α=0.0, src_γ=-1.0, dst_order=15, dst_γ=-0.5\ngc2gc: testing with src_order=15, src_α=0.0, src_γ=-1.0, dst_order=15, dst_γ=0.0\ngc2gc: testing with src_order=15, src_α=0.0, src_γ=-1.0, dst_order=20, dst_γ=-1.0\ngc2gc: testing with src_order=15, src_α=0.0, src_γ=-1.0, dst_order=20, dst_γ=-0.5\ngc2gc: testing with src_order=15, src_α=0.0, src_γ=-1.0, dst_order=20, dst_γ=0.0\ngc2gc: testing with src_order=15, src_α=0.0, src_γ=-1.0, dst_order=25, dst_γ=-1.0\ngc2gc: testing with src_order=15, src_α=0.0, src_γ=-1.0, dst_order=25, dst_γ=-0.5\ngc2gc: testing with src_order=15, src_α=0.0, src_γ=-1.0, dst_order=25, dst_γ=0.0\ngc2gc: testing with src_order=15, src_α=0.0, src_γ=-0.5, dst_order=15, dst_γ=-1.0\ngc2gc: testing with src_order=15, src_α=0.0, src_γ=-0.5, dst_order=15, dst_γ=-0.5\ngc2gc: testing with src_order=15, src_α=0.0, src_γ=-0.5, dst_order=15, dst_γ=0.0\ngc2gc: testing with src_order=15, src_α=0.0, src_γ=-0.5, dst_order=20, dst_γ=-1.0\ngc2gc: testing with src_order=15, src_α=0.0, src_γ=-0.5, dst_order=20, dst_γ=-0.5\ngc2gc: testing with src_order=15, src_α=0.0, src_γ=-0.5, dst_order=20, dst_γ=0.0\ngc2gc: testing with src_order=15, src_α=0.0, src_γ=-0.5, dst_order=25, dst_γ=-1.0\ngc2gc: testing with src_order=15, src_α=0.0, src_γ=-0.5, dst_order=25, dst_γ=-0.5\ngc2gc: testing with src_order=15, src_α=0.0, src_γ=-0.5, dst_order=25, dst_γ=0.0\ngc2gc: testing with src_order=15, src_α=0.0, src_γ=0.0, dst_order=15, dst_γ=-1.0\ngc2gc: testing with src_order=15, src_α=0.0, src_γ=0.0, dst_order=15, dst_γ=-0.5\ngc2gc: testing with src_order=15, src_α=0.0, src_γ=0.0, dst_order=15, dst_γ=0.0\ngc2gc: testing with src_order=15, src_α=0.0, src_γ=0.0, dst_order=20, dst_γ=-1.0\ngc2gc: testing with src_order=15, src_α=0.0, src_γ=0.0, dst_order=20, dst_γ=-0.5\ngc2gc: testing with src_order=15, src_α=0.0, src_γ=0.0, dst_order=20, dst_γ=0.0\ngc2gc: testing with src_order=15, src_α=0.0, src_γ=0.0, dst_order=25, dst_γ=-1.0\ngc2gc: testing with src_order=15, src_α=0.0, src_γ=0.0, dst_order=25, dst_γ=-0.5\ngc2gc: testing with src_order=15, src_α=0.0, src_γ=0.0, dst_order=25, dst_γ=0.0\ngc2gc: testing with src_order=15, src_α=0.35, src_γ=-1.0, dst_order=15, dst_γ=-1.0\ngc2gc: testing with src_order=15, src_α=0.35, src_γ=-1.0, dst_order=15, dst_γ=-0.5\ngc2gc: testing with src_order=15, src_α=0.35, src_γ=-1.0, dst_order=15, dst_γ=0.0\ngc2gc: testing with src_order=15, src_α=0.35, src_γ=-1.0, dst_order=20, dst_γ=-1.0\ngc2gc: testing with src_order=15, src_α=0.35, src_γ=-1.0, dst_order=20, dst_γ=-0.5\ngc2gc: testing with src_order=15, src_α=0.35, src_γ=-1.0, dst_order=20, dst_γ=0.0\ngc2gc: testing with src_order=15, src_α=0.35, src_γ=-1.0, dst_order=25, dst_γ=-1.0\ngc2gc: testing with src_order=15, src_α=0.35, src_γ=-1.0, dst_order=25, dst_γ=-0.5\ngc2gc: testing with src_order=15, src_α=0.35, src_γ=-1.0, dst_order=25, dst_γ=0.0\ngc2gc: testing with src_order=15, src_α=0.35, src_γ=-0.5, dst_order=15, dst_γ=-1.0\ngc2gc: testing with src_order=15, src_α=0.35, src_γ=-0.5, dst_order=15, dst_γ=-0.5\ngc2gc: testing with src_order=15, src_α=0.35, src_γ=-0.5, dst_order=15, dst_γ=0.0\ngc2gc: testing with src_order=15, src_α=0.35, src_γ=-0.5, dst_order=20, dst_γ=-1.0\ngc2gc: testing with src_order=15, src_α=0.35, src_γ=-0.5, dst_order=20, dst_γ=-0.5\ngc2gc: testing with src_order=15, src_α=0.35, src_γ=-0.5, dst_order=20, dst_γ=0.0\ngc2gc: testing with src_order=15, src_α=0.35, src_γ=-0.5, dst_order=25, dst_γ=-1.0\ngc2gc: testing with src_order=15, src_α=0.35, src_γ=-0.5, dst_order=25, dst_γ=-0.5\ngc2gc: testing with src_order=15, src_α=0.35, src_γ=-0.5, dst_order=25, dst_γ=0.0\ngc2gc: testing with src_order=15, src_α=0.35, src_γ=0.0, dst_order=15, dst_γ=-1.0\ngc2gc: testing with src_order=15, src_α=0.35, src_γ=0.0, dst_order=15, dst_γ=-0.5\ngc2gc: testing with src_order=15, src_α=0.35, src_γ=0.0, dst_order=15, dst_γ=0.0\ngc2gc: testing with src_order=15, src_α=0.35, src_γ=0.0, dst_order=20, dst_γ=-1.0\ngc2gc: testing with src_order=15, src_α=0.35, src_γ=0.0, dst_order=20, dst_γ=-0.5\ngc2gc: testing with src_order=15, src_α=0.35, src_γ=0.0, dst_order=20, dst_γ=0.0\ngc2gc: testing with src_order=15, src_α=0.35, src_γ=0.0, dst_order=25, dst_γ=-1.0\ngc2gc: testing with src_order=15, src_α=0.35, src_γ=0.0, dst_order=25, dst_γ=-0.5\ngc2gc: testing with src_order=15, src_α=0.35, src_γ=0.0, dst_order=25, dst_γ=0.0\ngc2gc: testing with src_order=20, src_α=0.0, src_γ=-1.0, dst_order=15, dst_γ=-1.0\ngc2gc: testing with src_order=20, src_α=0.0, src_γ=-1.0, dst_order=15, dst_γ=-0.5\ngc2gc: testing with src_order=20, src_α=0.0, src_γ=-1.0, dst_order=15, dst_γ=0.0\ngc2gc: testing with src_order=20, src_α=0.0, src_γ=-1.0, dst_order=20, dst_γ=-1.0\ngc2gc: testing with src_order=20, src_α=0.0, src_γ=-1.0, dst_order=20, dst_γ=-0.5\ngc2gc: testing with src_order=20, src_α=0.0, src_γ=-1.0, dst_order=20, dst_γ=0.0\ngc2gc: testing with src_order=20, src_α=0.0, src_γ=-1.0, dst_order=25, dst_γ=-1.0\ngc2gc: testing with src_order=20, src_α=0.0, src_γ=-1.0, dst_order=25, dst_γ=-0.5\ngc2gc: testing with src_order=20, src_α=0.0, src_γ=-1.0, dst_order=25, dst_γ=0.0\ngc2gc: testing with src_order=20, src_α=0.0, src_γ=-0.5, dst_order=15, dst_γ=-1.0\ngc2gc: testing with src_order=20, src_α=0.0, src_γ=-0.5, dst_order=15, dst_γ=-0.5\ngc2gc: testing with src_order=20, src_α=0.0, src_γ=-0.5, dst_order=15, dst_γ=0.0\ngc2gc: testing with src_order=20, src_α=0.0, src_γ=-0.5, dst_order=20, dst_γ=-1.0\ngc2gc: testing with src_order=20, src_α=0.0, src_γ=-0.5, dst_order=20, dst_γ=-0.5\ngc2gc: testing with src_order=20, src_α=0.0, src_γ=-0.5, dst_order=20, dst_γ=0.0\ngc2gc: testing with src_order=20, src_α=0.0, src_γ=-0.5, dst_order=25, dst_γ=-1.0\ngc2gc: testing with src_order=20, src_α=0.0, src_γ=-0.5, dst_order=25, dst_γ=-0.5\ngc2gc: testing with src_order=20, src_α=0.0, src_γ=-0.5, dst_order=25, dst_γ=0.0\ngc2gc: testing with src_order=20, src_α=0.0, src_γ=0.0, dst_order=15, dst_γ=-1.0\ngc2gc: testing with src_order=20, src_α=0.0, src_γ=0.0, dst_order=15, dst_γ=-0.5\ngc2gc: testing with src_order=20, src_α=0.0, src_γ=0.0, dst_order=15, dst_γ=0.0\ngc2gc: testing with src_order=20, src_α=0.0, src_γ=0.0, dst_order=20, dst_γ=-1.0\ngc2gc: testing with src_order=20, src_α=0.0, src_γ=0.0, dst_order=20, dst_γ=-0.5\ngc2gc: testing with src_order=20, src_α=0.0, src_γ=0.0, dst_order=20, dst_γ=0.0\ngc2gc: testing with src_order=20, src_α=0.0, src_γ=0.0, dst_order=25, dst_γ=-1.0\ngc2gc: testing with src_order=20, src_α=0.0, src_γ=0.0, dst_order=25, dst_γ=-0.5\ngc2gc: testing with src_order=20, src_α=0.0, src_γ=0.0, dst_order=25, dst_γ=0.0\ngc2gc: testing with src_order=20, src_α=0.35, src_γ=-1.0, dst_order=15, dst_γ=-1.0\ngc2gc: testing with src_order=20, src_α=0.35, src_γ=-1.0, dst_order=15, dst_γ=-0.5\ngc2gc: testing with src_order=20, src_α=0.35, src_γ=-1.0, dst_order=15, dst_γ=0.0\ngc2gc: testing with src_order=20, src_α=0.35, src_γ=-1.0, dst_order=20, dst_γ=-1.0\ngc2gc: testing with src_order=20, src_α=0.35, src_γ=-1.0, dst_order=20, dst_γ=-0.5\ngc2gc: testing with src_order=20, src_α=0.35, src_γ=-1.0, dst_order=20, dst_γ=0.0\ngc2gc: testing with src_order=20, src_α=0.35, src_γ=-1.0, dst_order=25, dst_γ=-1.0\ngc2gc: testing with src_order=20, src_α=0.35, src_γ=-1.0, dst_order=25, dst_γ=-0.5\ngc2gc: testing with src_order=20, src_α=0.35, src_γ=-1.0, dst_order=25, dst_γ=0.0\ngc2gc: testing with src_order=20, src_α=0.35, src_γ=-0.5, dst_order=15, dst_γ=-1.0\ngc2gc: testing with src_order=20, src_α=0.35, src_γ=-0.5, dst_order=15, dst_γ=-0.5\ngc2gc: testing with src_order=20, src_α=0.35, src_γ=-0.5, dst_order=15, dst_γ=0.0\ngc2gc: testing with src_order=20, src_α=0.35, src_γ=-0.5, dst_order=20, dst_γ=-1.0\ngc2gc: testing with src_order=20, src_α=0.35, src_γ=-0.5, dst_order=20, dst_γ=-0.5\ngc2gc: testing with src_order=20, src_α=0.35, src_γ=-0.5, dst_order=20, dst_γ=0.0\ngc2gc: testing with src_order=20, src_α=0.35, src_γ=-0.5, dst_order=25, dst_γ=-1.0\ngc2gc: testing with src_order=20, src_α=0.35, src_γ=-0.5, dst_order=25, dst_γ=-0.5\ngc2gc: testing with src_order=20, src_α=0.35, src_γ=-0.5, dst_order=25, dst_γ=0.0\ngc2gc: testing with src_order=20, src_α=0.35, src_γ=0.0, dst_order=15, dst_γ=-1.0\ngc2gc: testing with src_order=20, src_α=0.35, src_γ=0.0, dst_order=15, dst_γ=-0.5\ngc2gc: testing with src_order=20, src_α=0.35, src_γ=0.0, dst_order=15, dst_γ=0.0\ngc2gc: testing with src_order=20, src_α=0.35, src_γ=0.0, dst_order=20, dst_γ=-1.0\ngc2gc: testing with src_order=20, src_α=0.35, src_γ=0.0, dst_order=20, dst_γ=-0.5\ngc2gc: testing with src_order=20, src_α=0.35, src_γ=0.0, dst_order=20, dst_γ=0.0\ngc2gc: testing with src_order=20, src_α=0.35, src_γ=0.0, dst_order=25, dst_γ=-1.0\ngc2gc: testing with src_order=20, src_α=0.35, src_γ=0.0, dst_order=25, dst_γ=-0.5\ngc2gc: testing with src_order=20, src_α=0.35, src_γ=0.0, dst_order=25, dst_γ=0.0\ngc2gc: testing with src_order=25, src_α=0.0, src_γ=-1.0, dst_order=15, dst_γ=-1.0\ngc2gc: testing with src_order=25, src_α=0.0, src_γ=-1.0, dst_order=15, dst_γ=-0.5\ngc2gc: testing with src_order=25, src_α=0.0, src_γ=-1.0, dst_order=15, dst_γ=0.0\ngc2gc: testing with src_order=25, src_α=0.0, src_γ=-1.0, dst_order=20, dst_γ=-1.0\ngc2gc: testing with src_order=25, src_α=0.0, src_γ=-1.0, dst_order=20, dst_γ=-0.5\ngc2gc: testing with src_order=25, src_α=0.0, src_γ=-1.0, dst_order=20, dst_γ=0.0\ngc2gc: testing with src_order=25, src_α=0.0, src_γ=-1.0, dst_order=25, dst_γ=-1.0\ngc2gc: testing with src_order=25, src_α=0.0, src_γ=-1.0, dst_order=25, dst_γ=-0.5\ngc2gc: testing with src_order=25, src_α=0.0, src_γ=-1.0, dst_order=25, dst_γ=0.0\ngc2gc: testing with src_order=25, src_α=0.0, src_γ=-0.5, dst_order=15, dst_γ=-1.0\ngc2gc: testing with src_order=25, src_α=0.0, src_γ=-0.5, dst_order=15, dst_γ=-0.5\ngc2gc: testing with src_order=25, src_α=0.0, src_γ=-0.5, dst_order=15, dst_γ=0.0\ngc2gc: testing with src_order=25, src_α=0.0, src_γ=-0.5, dst_order=20, dst_γ=-1.0\ngc2gc: testing with src_order=25, src_α=0.0, src_γ=-0.5, dst_order=20, dst_γ=-0.5\ngc2gc: testing with src_order=25, src_α=0.0, src_γ=-0.5, dst_order=20, dst_γ=0.0\ngc2gc: testing with src_order=25, src_α=0.0, src_γ=-0.5, dst_order=25, dst_γ=-1.0\ngc2gc: testing with src_order=25, src_α=0.0, src_γ=-0.5, dst_order=25, dst_γ=-0.5\ngc2gc: testing with src_order=25, src_α=0.0, src_γ=-0.5, dst_order=25, dst_γ=0.0\ngc2gc: testing with src_order=25, src_α=0.0, src_γ=0.0, dst_order=15, dst_γ=-1.0\ngc2gc: testing with src_order=25, src_α=0.0, src_γ=0.0, dst_order=15, dst_γ=-0.5\ngc2gc: testing with src_order=25, src_α=0.0, src_γ=0.0, dst_order=15, dst_γ=0.0\ngc2gc: testing with src_order=25, src_α=0.0, src_γ=0.0, dst_order=20, dst_γ=-1.0\ngc2gc: testing with src_order=25, src_α=0.0, src_γ=0.0, dst_order=20, dst_γ=-0.5\ngc2gc: testing with src_order=25, src_α=0.0, src_γ=0.0, dst_order=20, dst_γ=0.0\ngc2gc: testing with src_order=25, src_α=0.0, src_γ=0.0, dst_order=25, dst_γ=-1.0\ngc2gc: testing with src_order=25, src_α=0.0, src_γ=0.0, dst_order=25, dst_γ=-0.5\ngc2gc: testing with src_order=25, src_α=0.0, src_γ=0.0, dst_order=25, dst_γ=0.0\ngc2gc: testing with src_order=25, src_α=0.35, src_γ=-1.0, dst_order=15, dst_γ=-1.0\ngc2gc: testing with src_order=25, src_α=0.35, src_γ=-1.0, dst_order=15, dst_γ=-0.5\ngc2gc: testing with src_order=25, src_α=0.35, src_γ=-1.0, dst_order=15, dst_γ=0.0\ngc2gc: testing with src_order=25, src_α=0.35, src_γ=-1.0, dst_order=20, dst_γ=-1.0\ngc2gc: testing with src_order=25, src_α=0.35, src_γ=-1.0, dst_order=20, dst_γ=-0.5\ngc2gc: testing with src_order=25, src_α=0.35, src_γ=-1.0, dst_order=20, dst_γ=0.0\ngc2gc: testing with src_order=25, src_α=0.35, src_γ=-1.0, dst_order=25, dst_γ=-1.0\ngc2gc: testing with src_order=25, src_α=0.35, src_γ=-1.0, dst_order=25, dst_γ=-0.5\ngc2gc: testing with src_order=25, src_α=0.35, src_γ=-1.0, dst_order=25, dst_γ=0.0\ngc2gc: testing with src_order=25, src_α=0.35, src_γ=-0.5, dst_order=15, dst_γ=-1.0\ngc2gc: testing with src_order=25, src_α=0.35, src_γ=-0.5, dst_order=15, dst_γ=-0.5\ngc2gc: testing with src_order=25, src_α=0.35, src_γ=-0.5, dst_order=15, dst_γ=0.0\ngc2gc: testing with src_order=25, src_α=0.35, src_γ=-0.5, dst_order=20, dst_γ=-1.0\ngc2gc: testing with src_order=25, src_α=0.35, src_γ=-0.5, dst_order=20, dst_γ=-0.5\ngc2gc: testing with src_order=25, src_α=0.35, src_γ=-0.5, dst_order=20, dst_γ=0.0\ngc2gc: testing with src_order=25, src_α=0.35, src_γ=-0.5, dst_order=25, dst_γ=-1.0\ngc2gc: testing with src_order=25, src_α=0.35, src_γ=-0.5, dst_order=25, dst_γ=-0.5\ngc2gc: testing with src_order=25, src_α=0.35, src_γ=-0.5, dst_order=25, dst_γ=0.0\ngc2gc: testing with src_order=25, src_α=0.35, src_γ=0.0, dst_order=15, dst_γ=-1.0\ngc2gc: testing with src_order=25, src_α=0.35, src_γ=0.0, dst_order=15, dst_γ=-0.5\ngc2gc: testing with src_order=25, src_α=0.35, src_γ=0.0, dst_order=15, dst_γ=0.0\ngc2gc: testing with src_order=25, src_α=0.35, src_γ=0.0, dst_order=20, dst_γ=-1.0\ngc2gc: testing with src_order=25, src_α=0.35, src_γ=0.0, dst_order=20, dst_γ=-0.5\ngc2gc: testing with src_order=25, src_α=0.35, src_γ=0.0, dst_order=20, dst_γ=0.0\ngc2gc: testing with src_order=25, src_α=0.35, src_γ=0.0, dst_order=25, dst_γ=-1.0\ngc2gc: testing with src_order=25, src_α=0.35, src_γ=0.0, dst_order=25, dst_γ=-0.5\ngc2gc: testing with src_order=25, src_α=0.35, src_γ=0.0, dst_order=25, dst_γ=0.0\nmgc2mgc: testing with src_order=15, src_α, src_γ=-1.0, dst_order=15, dst_α=0.0, dst_γ=-1.0\nmgc2mgc: testing with src_order=15, src_α, src_γ=-1.0, dst_order=15, dst_α=0.0, dst_γ=-0.5\nmgc2mgc: testing with src_order=15, src_α, src_γ=-1.0, dst_order=15, dst_α=0.0, dst_γ=0.0\nmgc2mgc: testing with src_order=15, src_α, src_γ=-1.0, dst_order=15, dst_α=0.35, dst_γ=-1.0\nmgc2mgc: testing with src_order=15, src_α, src_γ=-1.0, dst_order=15, dst_α=0.35, dst_γ=-0.5\nmgc2mgc: testing with src_order=15, src_α, src_γ=-1.0, dst_order=15, dst_α=0.35, dst_γ=0.0\nmgc2mgc: testing with src_order=15, src_α, src_γ=-1.0, dst_order=20, dst_α=0.0, dst_γ=-1.0\nmgc2mgc: testing with src_order=15, src_α, src_γ=-1.0, dst_order=20, dst_α=0.0, dst_γ=-0.5\nmgc2mgc: testing with src_order=15, src_α, src_γ=-1.0, dst_order=20, dst_α=0.0, dst_γ=0.0\nmgc2mgc: testing with src_order=15, src_α, src_γ=-1.0, dst_order=20, dst_α=0.35, dst_γ=-1.0\nmgc2mgc: testing with src_order=15, src_α, src_γ=-1.0, dst_order=20, dst_α=0.35, dst_γ=-0.5\nmgc2mgc: testing with src_order=15, src_α, src_γ=-1.0, dst_order=20, dst_α=0.35, dst_γ=0.0\nmgc2mgc: testing with src_order=15, src_α, src_γ=-1.0, dst_order=25, dst_α=0.0, dst_γ=-1.0\nmgc2mgc: testing with src_order=15, src_α, src_γ=-1.0, dst_order=25, dst_α=0.0, dst_γ=-0.5\nmgc2mgc: testing with src_order=15, src_α, src_γ=-1.0, dst_order=25, dst_α=0.0, dst_γ=0.0\nmgc2mgc: testing with src_order=15, src_α, src_γ=-1.0, dst_order=25, dst_α=0.35, dst_γ=-1.0\nmgc2mgc: testing with src_order=15, src_α, src_γ=-1.0, dst_order=25, dst_α=0.35, dst_γ=-0.5\nmgc2mgc: testing with src_order=15, src_α, src_γ=-1.0, dst_order=25, dst_α=0.35, dst_γ=0.0\nmgc2mgc: testing with src_order=15, src_α, src_γ=-0.5, dst_order=15, dst_α=0.0, dst_γ=-1.0\nmgc2mgc: testing with src_order=15, src_α, src_γ=-0.5, dst_order=15, dst_α=0.0, dst_γ=-0.5\nmgc2mgc: testing with src_order=15, src_α, src_γ=-0.5, dst_order=15, dst_α=0.0, dst_γ=0.0\nmgc2mgc: testing with src_order=15, src_α, src_γ=-0.5, dst_order=15, dst_α=0.35, dst_γ=-1.0\nmgc2mgc: testing with src_order=15, src_α, src_γ=-0.5, dst_order=15, dst_α=0.35, dst_γ=-0.5\nmgc2mgc: testing with src_order=15, src_α, src_γ=-0.5, dst_order=15, dst_α=0.35, dst_γ=0.0\nmgc2mgc: testing with src_order=15, src_α, src_γ=-0.5, dst_order=20, dst_α=0.0, dst_γ=-1.0\nmgc2mgc: testing with src_order=15, src_α, src_γ=-0.5, dst_order=20, dst_α=0.0, dst_γ=-0.5\nmgc2mgc: testing with src_order=15, src_α, src_γ=-0.5, dst_order=20, dst_α=0.0, dst_γ=0.0\nmgc2mgc: testing with src_order=15, src_α, src_γ=-0.5, dst_order=20, dst_α=0.35, dst_γ=-1.0\nmgc2mgc: testing with src_order=15, src_α, src_γ=-0.5, dst_order=20, dst_α=0.35, dst_γ=-0.5\nmgc2mgc: testing with src_order=15, src_α, src_γ=-0.5, dst_order=20, dst_α=0.35, dst_γ=0.0\nmgc2mgc: testing with src_order=15, src_α, src_γ=-0.5, dst_order=25, dst_α=0.0, dst_γ=-1.0\nmgc2mgc: testing with src_order=15, src_α, src_γ=-0.5, dst_order=25, dst_α=0.0, dst_γ=-0.5\nmgc2mgc: testing with src_order=15, src_α, src_γ=-0.5, dst_order=25, dst_α=0.0, dst_γ=0.0\nmgc2mgc: testing with src_order=15, src_α, src_γ=-0.5, dst_order=25, dst_α=0.35, dst_γ=-1.0\nmgc2mgc: testing with src_order=15, src_α, src_γ=-0.5, dst_order=25, dst_α=0.35, dst_γ=-0.5\nmgc2mgc: testing with src_order=15, src_α, src_γ=-0.5, dst_order=25, dst_α=0.35, dst_γ=0.0\nmgc2mgc: testing with src_order=15, src_α, src_γ=0.0, dst_order=15, dst_α=0.0, dst_γ=-1.0\nmgc2mgc: testing with src_order=15, src_α, src_γ=0.0, dst_order=15, dst_α=0.0, dst_γ=-0.5\nmgc2mgc: testing with src_order=15, src_α, src_γ=0.0, dst_order=15, dst_α=0.0, dst_γ=0.0\nmgc2mgc: testing with src_order=15, src_α, src_γ=0.0, dst_order=15, dst_α=0.35, dst_γ=-1.0\nmgc2mgc: testing with src_order=15, src_α, src_γ=0.0, dst_order=15, dst_α=0.35, dst_γ=-0.5\nmgc2mgc: testing with src_order=15, src_α, src_γ=0.0, dst_order=15, dst_α=0.35, dst_γ=0.0\nmgc2mgc: testing with src_order=15, src_α, src_γ=0.0, dst_order=20, dst_α=0.0, dst_γ=-1.0\nmgc2mgc: testing with src_order=15, src_α, src_γ=0.0, dst_order=20, dst_α=0.0, dst_γ=-0.5\nmgc2mgc: testing with src_order=15, src_α, src_γ=0.0, dst_order=20, dst_α=0.0, dst_γ=0.0\nmgc2mgc: testing with src_order=15, src_α, src_γ=0.0, dst_order=20, dst_α=0.35, dst_γ=-1.0\nmgc2mgc: testing with src_order=15, src_α, src_γ=0.0, dst_order=20, dst_α=0.35, dst_γ=-0.5\nmgc2mgc: testing with src_order=15, src_α, src_γ=0.0, dst_order=20, dst_α=0.35, dst_γ=0.0\nmgc2mgc: testing with src_order=15, src_α, src_γ=0.0, dst_order=25, dst_α=0.0, dst_γ=-1.0\nmgc2mgc: testing with src_order=15, src_α, src_γ=0.0, dst_order=25, dst_α=0.0, dst_γ=-0.5\nmgc2mgc: testing with src_order=15, src_α, src_γ=0.0, dst_order=25, dst_α=0.0, dst_γ=0.0\nmgc2mgc: testing with src_order=15, src_α, src_γ=0.0, dst_order=25, dst_α=0.35, dst_γ=-1.0\nmgc2mgc: testing with src_order=15, src_α, src_γ=0.0, dst_order=25, dst_α=0.35, dst_γ=-0.5\nmgc2mgc: testing with src_order=15, src_α, src_γ=0.0, dst_order=25, dst_α=0.35, dst_γ=0.0\nmgc2mgc: testing with src_order=15, src_α, src_γ=-1.0, dst_order=15, dst_α=0.0, dst_γ=-1.0\nmgc2mgc: testing with src_order=15, src_α, src_γ=-1.0, dst_order=15, dst_α=0.0, dst_γ=-0.5\nmgc2mgc: testing with src_order=15, src_α, src_γ=-1.0, dst_order=15, dst_α=0.0, dst_γ=0.0\nmgc2mgc: testing with src_order=15, src_α, src_γ=-1.0, dst_order=15, dst_α=0.35, dst_γ=-1.0\nmgc2mgc: testing with src_order=15, src_α, src_γ=-1.0, dst_order=15, dst_α=0.35, dst_γ=-0.5\nmgc2mgc: testing with src_order=15, src_α, src_γ=-1.0, dst_order=15, dst_α=0.35, dst_γ=0.0\nmgc2mgc: testing with src_order=15, src_α, src_γ=-1.0, dst_order=20, dst_α=0.0, dst_γ=-1.0\nmgc2mgc: testing with src_order=15, src_α, src_γ=-1.0, dst_order=20, dst_α=0.0, dst_γ=-0.5\nmgc2mgc: testing with src_order=15, src_α, src_γ=-1.0, dst_order=20, dst_α=0.0, dst_γ=0.0\nmgc2mgc: testing with src_order=15, src_α, src_γ=-1.0, dst_order=20, dst_α=0.35, dst_γ=-1.0\nmgc2mgc: testing with src_order=15, src_α, src_γ=-1.0, dst_order=20, dst_α=0.35, dst_γ=-0.5\nmgc2mgc: testing with src_order=15, src_α, src_γ=-1.0, dst_order=20, dst_α=0.35, dst_γ=0.0\nmgc2mgc: testing with src_order=15, src_α, src_γ=-1.0, dst_order=25, dst_α=0.0, dst_γ=-1.0\nmgc2mgc: testing with src_order=15, src_α, src_γ=-1.0, dst_order=25, dst_α=0.0, dst_γ=-0.5\nmgc2mgc: testing with src_order=15, src_α, src_γ=-1.0, dst_order=25, dst_α=0.0, dst_γ=0.0\nmgc2mgc: testing with src_order=15, src_α, src_γ=-1.0, dst_order=25, dst_α=0.35, dst_γ=-1.0\nmgc2mgc: testing with src_order=15, src_α, src_γ=-1.0, dst_order=25, dst_α=0.35, dst_γ=-0.5\nmgc2mgc: testing with src_order=15, src_α, src_γ=-1.0, dst_order=25, dst_α=0.35, dst_γ=0.0\nmgc2mgc: testing with src_order=15, src_α, src_γ=-0.5, dst_order=15, dst_α=0.0, dst_γ=-1.0\nmgc2mgc: testing with src_order=15, src_α, src_γ=-0.5, dst_order=15, dst_α=0.0, dst_γ=-0.5\nmgc2mgc: testing with src_order=15, src_α, src_γ=-0.5, dst_order=15, dst_α=0.0, dst_γ=0.0\nmgc2mgc: testing with src_order=15, src_α, src_γ=-0.5, dst_order=15, dst_α=0.35, dst_γ=-1.0\nmgc2mgc: testing with src_order=15, src_α, src_γ=-0.5, dst_order=15, dst_α=0.35, dst_γ=-0.5\nmgc2mgc: testing with src_order=15, src_α, src_γ=-0.5, dst_order=15, dst_α=0.35, dst_γ=0.0\nmgc2mgc: testing with src_order=15, src_α, src_γ=-0.5, dst_order=20, dst_α=0.0, dst_γ=-1.0\nmgc2mgc: testing with src_order=15, src_α, src_γ=-0.5, dst_order=20, dst_α=0.0, dst_γ=-0.5\nmgc2mgc: testing with src_order=15, src_α, src_γ=-0.5, dst_order=20, dst_α=0.0, dst_γ=0.0\nmgc2mgc: testing with src_order=15, src_α, src_γ=-0.5, dst_order=20, dst_α=0.35, dst_γ=-1.0\nmgc2mgc: testing with src_order=15, src_α, src_γ=-0.5, dst_order=20, dst_α=0.35, dst_γ=-0.5\nmgc2mgc: testing with src_order=15, src_α, src_γ=-0.5, dst_order=20, dst_α=0.35, dst_γ=0.0\nmgc2mgc: testing with src_order=15, src_α, src_γ=-0.5, dst_order=25, dst_α=0.0, dst_γ=-1.0\nmgc2mgc: testing with src_order=15, src_α, src_γ=-0.5, dst_order=25, dst_α=0.0, dst_γ=-0.5\nmgc2mgc: testing with src_order=15, src_α, src_γ=-0.5, dst_order=25, dst_α=0.0, dst_γ=0.0\nmgc2mgc: testing with src_order=15, src_α, src_γ=-0.5, dst_order=25, dst_α=0.35, dst_γ=-1.0\nmgc2mgc: testing with src_order=15, src_α, src_γ=-0.5, dst_order=25, dst_α=0.35, dst_γ=-0.5\nmgc2mgc: testing with src_order=15, src_α, src_γ=-0.5, dst_order=25, dst_α=0.35, dst_γ=0.0\nmgc2mgc: testing with src_order=15, src_α, src_γ=0.0, dst_order=15, dst_α=0.0, dst_γ=-1.0\nmgc2mgc: testing with src_order=15, src_α, src_γ=0.0, dst_order=15, dst_α=0.0, dst_γ=-0.5\nmgc2mgc: testing with src_order=15, src_α, src_γ=0.0, dst_order=15, dst_α=0.0, dst_γ=0.0\nmgc2mgc: testing with src_order=15, src_α, src_γ=0.0, dst_order=15, dst_α=0.35, dst_γ=-1.0\nmgc2mgc: testing with src_order=15, src_α, src_γ=0.0, dst_order=15, dst_α=0.35, dst_γ=-0.5\nmgc2mgc: testing with src_order=15, src_α, src_γ=0.0, dst_order=15, dst_α=0.35, dst_γ=0.0\nmgc2mgc: testing with src_order=15, src_α, src_γ=0.0, dst_order=20, dst_α=0.0, dst_γ=-1.0\nmgc2mgc: testing with src_order=15, src_α, src_γ=0.0, dst_order=20, dst_α=0.0, dst_γ=-0.5\nmgc2mgc: testing with src_order=15, src_α, src_γ=0.0, dst_order=20, dst_α=0.0, dst_γ=0.0\nmgc2mgc: testing with src_order=15, src_α, src_γ=0.0, dst_order=20, dst_α=0.35, dst_γ=-1.0\nmgc2mgc: testing with src_order=15, src_α, src_γ=0.0, dst_order=20, dst_α=0.35, dst_γ=-0.5\nmgc2mgc: testing with src_order=15, src_α, src_γ=0.0, dst_order=20, dst_α=0.35, dst_γ=0.0\nmgc2mgc: testing with src_order=15, src_α, src_γ=0.0, dst_order=25, dst_α=0.0, dst_γ=-1.0\nmgc2mgc: testing with src_order=15, src_α, src_γ=0.0, dst_order=25, dst_α=0.0, dst_γ=-0.5\nmgc2mgc: testing with src_order=15, src_α, src_γ=0.0, dst_order=25, dst_α=0.0, dst_γ=0.0\nmgc2mgc: testing with src_order=15, src_α, src_γ=0.0, dst_order=25, dst_α=0.35, dst_γ=-1.0\nmgc2mgc: testing with src_order=15, src_α, src_γ=0.0, dst_order=25, dst_α=0.35, dst_γ=-0.5\nmgc2mgc: testing with src_order=15, src_α, src_γ=0.0, dst_order=25, dst_α=0.35, dst_γ=0.0\nmgc2mgc: testing with src_order=20, src_α, src_γ=-1.0, dst_order=15, dst_α=0.0, dst_γ=-1.0\nmgc2mgc: testing with src_order=20, src_α, src_γ=-1.0, dst_order=15, dst_α=0.0, dst_γ=-0.5\nmgc2mgc: testing with src_order=20, src_α, src_γ=-1.0, dst_order=15, dst_α=0.0, dst_γ=0.0\nmgc2mgc: testing with src_order=20, src_α, src_γ=-1.0, dst_order=15, dst_α=0.35, dst_γ=-1.0\nmgc2mgc: testing with src_order=20, src_α, src_γ=-1.0, dst_order=15, dst_α=0.35, dst_γ=-0.5\nmgc2mgc: testing with src_order=20, src_α, src_γ=-1.0, dst_order=15, dst_α=0.35, dst_γ=0.0\nmgc2mgc: testing with src_order=20, src_α, src_γ=-1.0, dst_order=20, dst_α=0.0, dst_γ=-1.0\nmgc2mgc: testing with src_order=20, src_α, src_γ=-1.0, dst_order=20, dst_α=0.0, dst_γ=-0.5\nmgc2mgc: testing with src_order=20, src_α, src_γ=-1.0, dst_order=20, dst_α=0.0, dst_γ=0.0\nmgc2mgc: testing with src_order=20, src_α, src_γ=-1.0, dst_order=20, dst_α=0.35, dst_γ=-1.0\nmgc2mgc: testing with src_order=20, src_α, src_γ=-1.0, dst_order=20, dst_α=0.35, dst_γ=-0.5\nmgc2mgc: testing with src_order=20, src_α, src_γ=-1.0, dst_order=20, dst_α=0.35, dst_γ=0.0\nmgc2mgc: testing with src_order=20, src_α, src_γ=-1.0, dst_order=25, dst_α=0.0, dst_γ=-1.0\nmgc2mgc: testing with src_order=20, src_α, src_γ=-1.0, dst_order=25, dst_α=0.0, dst_γ=-0.5\nmgc2mgc: testing with src_order=20, src_α, src_γ=-1.0, dst_order=25, dst_α=0.0, dst_γ=0.0\nmgc2mgc: testing with src_order=20, src_α, src_γ=-1.0, dst_order=25, dst_α=0.35, dst_γ=-1.0\nmgc2mgc: testing with src_order=20, src_α, src_γ=-1.0, dst_order=25, dst_α=0.35, dst_γ=-0.5\nmgc2mgc: testing with src_order=20, src_α, src_γ=-1.0, dst_order=25, dst_α=0.35, dst_γ=0.0\nmgc2mgc: testing with src_order=20, src_α, src_γ=-0.5, dst_order=15, dst_α=0.0, dst_γ=-1.0\nmgc2mgc: testing with src_order=20, src_α, src_γ=-0.5, dst_order=15, dst_α=0.0, dst_γ=-0.5\nmgc2mgc: testing with src_order=20, src_α, src_γ=-0.5, dst_order=15, dst_α=0.0, dst_γ=0.0\nmgc2mgc: testing with src_order=20, src_α, src_γ=-0.5, dst_order=15, dst_α=0.35, dst_γ=-1.0\nmgc2mgc: testing with src_order=20, src_α, src_γ=-0.5, dst_order=15, dst_α=0.35, dst_γ=-0.5\nmgc2mgc: testing with src_order=20, src_α, src_γ=-0.5, dst_order=15, dst_α=0.35, dst_γ=0.0\nmgc2mgc: testing with src_order=20, src_α, src_γ=-0.5, dst_order=20, dst_α=0.0, dst_γ=-1.0\nmgc2mgc: testing with src_order=20, src_α, src_γ=-0.5, dst_order=20, dst_α=0.0, dst_γ=-0.5\nmgc2mgc: testing with src_order=20, src_α, src_γ=-0.5, dst_order=20, dst_α=0.0, dst_γ=0.0\nmgc2mgc: testing with src_order=20, src_α, src_γ=-0.5, dst_order=20, dst_α=0.35, dst_γ=-1.0\nmgc2mgc: testing with src_order=20, src_α, src_γ=-0.5, dst_order=20, dst_α=0.35, dst_γ=-0.5\nmgc2mgc: testing with src_order=20, src_α, src_γ=-0.5, dst_order=20, dst_α=0.35, dst_γ=0.0\nmgc2mgc: testing with src_order=20, src_α, src_γ=-0.5, dst_order=25, dst_α=0.0, dst_γ=-1.0\nmgc2mgc: testing with src_order=20, src_α, src_γ=-0.5, dst_order=25, dst_α=0.0, dst_γ=-0.5\nmgc2mgc: testing with src_order=20, src_α, src_γ=-0.5, dst_order=25, dst_α=0.0, dst_γ=0.0\nmgc2mgc: testing with src_order=20, src_α, src_γ=-0.5, dst_order=25, dst_α=0.35, dst_γ=-1.0\nmgc2mgc: testing with src_order=20, src_α, src_γ=-0.5, dst_order=25, dst_α=0.35, dst_γ=-0.5\nmgc2mgc: testing with src_order=20, src_α, src_γ=-0.5, dst_order=25, dst_α=0.35, dst_γ=0.0\nmgc2mgc: testing with src_order=20, src_α, src_γ=0.0, dst_order=15, dst_α=0.0, dst_γ=-1.0\nmgc2mgc: testing with src_order=20, src_α, src_γ=0.0, dst_order=15, dst_α=0.0, dst_γ=-0.5\nmgc2mgc: testing with src_order=20, src_α, src_γ=0.0, dst_order=15, dst_α=0.0, dst_γ=0.0\nmgc2mgc: testing with src_order=20, src_α, src_γ=0.0, dst_order=15, dst_α=0.35, dst_γ=-1.0\nmgc2mgc: testing with src_order=20, src_α, src_γ=0.0, dst_order=15, dst_α=0.35, dst_γ=-0.5\nmgc2mgc: testing with src_order=20, src_α, src_γ=0.0, dst_order=15, dst_α=0.35, dst_γ=0.0\nmgc2mgc: testing with src_order=20, src_α, src_γ=0.0, dst_order=20, dst_α=0.0, dst_γ=-1.0\nmgc2mgc: testing with src_order=20, src_α, src_γ=0.0, dst_order=20, dst_α=0.0, dst_γ=-0.5\nmgc2mgc: testing with src_order=20, src_α, src_γ=0.0, dst_order=20, dst_α=0.0, dst_γ=0.0\nmgc2mgc: testing with src_order=20, src_α, src_γ=0.0, dst_order=20, dst_α=0.35, dst_γ=-1.0\nmgc2mgc: testing with src_order=20, src_α, src_γ=0.0, dst_order=20, dst_α=0.35, dst_γ=-0.5\nmgc2mgc: testing with src_order=20, src_α, src_γ=0.0, dst_order=20, dst_α=0.35, dst_γ=0.0\nmgc2mgc: testing with src_order=20, src_α, src_γ=0.0, dst_order=25, dst_α=0.0, dst_γ=-1.0\nmgc2mgc: testing with src_order=20, src_α, src_γ=0.0, dst_order=25, dst_α=0.0, dst_γ=-0.5\nmgc2mgc: testing with src_order=20, src_α, src_γ=0.0, dst_order=25, dst_α=0.0, dst_γ=0.0\nmgc2mgc: testing with src_order=20, src_α, src_γ=0.0, dst_order=25, dst_α=0.35, dst_γ=-1.0\nmgc2mgc: testing with src_order=20, src_α, src_γ=0.0, dst_order=25, dst_α=0.35, dst_γ=-0.5\nmgc2mgc: testing with src_order=20, src_α, src_γ=0.0, dst_order=25, dst_α=0.35, dst_γ=0.0\nmgc2mgc: testing with src_order=20, src_α, src_γ=-1.0, dst_order=15, dst_α=0.0, dst_γ=-1.0\nmgc2mgc: testing with src_order=20, src_α, src_γ=-1.0, dst_order=15, dst_α=0.0, dst_γ=-0.5\nmgc2mgc: testing with src_order=20, src_α, src_γ=-1.0, dst_order=15, dst_α=0.0, dst_γ=0.0\nmgc2mgc: testing with src_order=20, src_α, src_γ=-1.0, dst_order=15, dst_α=0.35, dst_γ=-1.0\nmgc2mgc: testing with src_order=20, src_α, src_γ=-1.0, dst_order=15, dst_α=0.35, dst_γ=-0.5\nmgc2mgc: testing with src_order=20, src_α, src_γ=-1.0, dst_order=15, dst_α=0.35, dst_γ=0.0\nmgc2mgc: testing with src_order=20, src_α, src_γ=-1.0, dst_order=20, dst_α=0.0, dst_γ=-1.0\nmgc2mgc: testing with src_order=20, src_α, src_γ=-1.0, dst_order=20, dst_α=0.0, dst_γ=-0.5\nmgc2mgc: testing with src_order=20, src_α, src_γ=-1.0, dst_order=20, dst_α=0.0, dst_γ=0.0\nmgc2mgc: testing with src_order=20, src_α, src_γ=-1.0, dst_order=20, dst_α=0.35, dst_γ=-1.0\nmgc2mgc: testing with src_order=20, src_α, src_γ=-1.0, dst_order=20, dst_α=0.35, dst_γ=-0.5\nmgc2mgc: testing with src_order=20, src_α, src_γ=-1.0, dst_order=20, dst_α=0.35, dst_γ=0.0\nmgc2mgc: testing with src_order=20, src_α, src_γ=-1.0, dst_order=25, dst_α=0.0, dst_γ=-1.0\nmgc2mgc: testing with src_order=20, src_α, src_γ=-1.0, dst_order=25, dst_α=0.0, dst_γ=-0.5\nmgc2mgc: testing with src_order=20, src_α, src_γ=-1.0, dst_order=25, dst_α=0.0, dst_γ=0.0\nmgc2mgc: testing with src_order=20, src_α, src_γ=-1.0, dst_order=25, dst_α=0.35, dst_γ=-1.0\nmgc2mgc: testing with src_order=20, src_α, src_γ=-1.0, dst_order=25, dst_α=0.35, dst_γ=-0.5\nmgc2mgc: testing with src_order=20, src_α, src_γ=-1.0, dst_order=25, dst_α=0.35, dst_γ=0.0\nmgc2mgc: testing with src_order=20, src_α, src_γ=-0.5, dst_order=15, dst_α=0.0, dst_γ=-1.0\nmgc2mgc: testing with src_order=20, src_α, src_γ=-0.5, dst_order=15, dst_α=0.0, dst_γ=-0.5\nmgc2mgc: testing with src_order=20, src_α, src_γ=-0.5, dst_order=15, dst_α=0.0, dst_γ=0.0\nmgc2mgc: testing with src_order=20, src_α, src_γ=-0.5, dst_order=15, dst_α=0.35, dst_γ=-1.0\nmgc2mgc: testing with src_order=20, src_α, src_γ=-0.5, dst_order=15, dst_α=0.35, dst_γ=-0.5\nmgc2mgc: testing with src_order=20, src_α, src_γ=-0.5, dst_order=15, dst_α=0.35, dst_γ=0.0\nmgc2mgc: testing with src_order=20, src_α, src_γ=-0.5, dst_order=20, dst_α=0.0, dst_γ=-1.0\nmgc2mgc: testing with src_order=20, src_α, src_γ=-0.5, dst_order=20, dst_α=0.0, dst_γ=-0.5\nmgc2mgc: testing with src_order=20, src_α, src_γ=-0.5, dst_order=20, dst_α=0.0, dst_γ=0.0\nmgc2mgc: testing with src_order=20, src_α, src_γ=-0.5, dst_order=20, dst_α=0.35, dst_γ=-1.0\nmgc2mgc: testing with src_order=20, src_α, src_γ=-0.5, dst_order=20, dst_α=0.35, dst_γ=-0.5\nmgc2mgc: testing with src_order=20, src_α, src_γ=-0.5, dst_order=20, dst_α=0.35, dst_γ=0.0\nmgc2mgc: testing with src_order=20, src_α, src_γ=-0.5, dst_order=25, dst_α=0.0, dst_γ=-1.0\nmgc2mgc: testing with src_order=20, src_α, src_γ=-0.5, dst_order=25, dst_α=0.0, dst_γ=-0.5\nmgc2mgc: testing with src_order=20, src_α, src_γ=-0.5, dst_order=25, dst_α=0.0, dst_γ=0.0\nmgc2mgc: testing with src_order=20, src_α, src_γ=-0.5, dst_order=25, dst_α=0.35, dst_γ=-1.0\nmgc2mgc: testing with src_order=20, src_α, src_γ=-0.5, dst_order=25, dst_α=0.35, dst_γ=-0.5\nmgc2mgc: testing with src_order=20, src_α, src_γ=-0.5, dst_order=25, dst_α=0.35, dst_γ=0.0\nmgc2mgc: testing with src_order=20, src_α, src_γ=0.0, dst_order=15, dst_α=0.0, dst_γ=-1.0\nmgc2mgc: testing with src_order=20, src_α, src_γ=0.0, dst_order=15, dst_α=0.0, dst_γ=-0.5\nmgc2mgc: testing with src_order=20, src_α, src_γ=0.0, dst_order=15, dst_α=0.0, dst_γ=0.0\nmgc2mgc: testing with src_order=20, src_α, src_γ=0.0, dst_order=15, dst_α=0.35, dst_γ=-1.0\nmgc2mgc: testing with src_order=20, src_α, src_γ=0.0, dst_order=15, dst_α=0.35, dst_γ=-0.5\nmgc2mgc: testing with src_order=20, src_α, src_γ=0.0, dst_order=15, dst_α=0.35, dst_γ=0.0\nmgc2mgc: testing with src_order=20, src_α, src_γ=0.0, dst_order=20, dst_α=0.0, dst_γ=-1.0\nmgc2mgc: testing with src_order=20, src_α, src_γ=0.0, dst_order=20, dst_α=0.0, dst_γ=-0.5\nmgc2mgc: testing with src_order=20, src_α, src_γ=0.0, dst_order=20, dst_α=0.0, dst_γ=0.0\nmgc2mgc: testing with src_order=20, src_α, src_γ=0.0, dst_order=20, dst_α=0.35, dst_γ=-1.0\nmgc2mgc: testing with src_order=20, src_α, src_γ=0.0, dst_order=20, dst_α=0.35, dst_γ=-0.5\nmgc2mgc: testing with src_order=20, src_α, src_γ=0.0, dst_order=20, dst_α=0.35, dst_γ=0.0\nmgc2mgc: testing with src_order=20, src_α, src_γ=0.0, dst_order=25, dst_α=0.0, dst_γ=-1.0\nmgc2mgc: testing with src_order=20, src_α, src_γ=0.0, dst_order=25, dst_α=0.0, dst_γ=-0.5\nmgc2mgc: testing with src_order=20, src_α, src_γ=0.0, dst_order=25, dst_α=0.0, dst_γ=0.0\nmgc2mgc: testing with src_order=20, src_α, src_γ=0.0, dst_order=25, dst_α=0.35, dst_γ=-1.0\nmgc2mgc: testing with src_order=20, src_α, src_γ=0.0, dst_order=25, dst_α=0.35, dst_γ=-0.5\nmgc2mgc: testing with src_order=20, src_α, src_γ=0.0, dst_order=25, dst_α=0.35, dst_γ=0.0\nmgc2mgc: testing with src_order=25, src_α, src_γ=-1.0, dst_order=15, dst_α=0.0, dst_γ=-1.0\nmgc2mgc: testing with src_order=25, src_α, src_γ=-1.0, dst_order=15, dst_α=0.0, dst_γ=-0.5\nmgc2mgc: testing with src_order=25, src_α, src_γ=-1.0, dst_order=15, dst_α=0.0, dst_γ=0.0\nmgc2mgc: testing with src_order=25, src_α, src_γ=-1.0, dst_order=15, dst_α=0.35, dst_γ=-1.0\nmgc2mgc: testing with src_order=25, src_α, src_γ=-1.0, dst_order=15, dst_α=0.35, dst_γ=-0.5\nmgc2mgc: testing with src_order=25, src_α, src_γ=-1.0, dst_order=15, dst_α=0.35, dst_γ=0.0\nmgc2mgc: testing with src_order=25, src_α, src_γ=-1.0, dst_order=20, dst_α=0.0, dst_γ=-1.0\nmgc2mgc: testing with src_order=25, src_α, src_γ=-1.0, dst_order=20, dst_α=0.0, dst_γ=-0.5\nmgc2mgc: testing with src_order=25, src_α, src_γ=-1.0, dst_order=20, dst_α=0.0, dst_γ=0.0\nmgc2mgc: testing with src_order=25, src_α, src_γ=-1.0, dst_order=20, dst_α=0.35, dst_γ=-1.0\nmgc2mgc: testing with src_order=25, src_α, src_γ=-1.0, dst_order=20, dst_α=0.35, dst_γ=-0.5\nmgc2mgc: testing with src_order=25, src_α, src_γ=-1.0, dst_order=20, dst_α=0.35, dst_γ=0.0\nmgc2mgc: testing with src_order=25, src_α, src_γ=-1.0, dst_order=25, dst_α=0.0, dst_γ=-1.0\nmgc2mgc: testing with src_order=25, src_α, src_γ=-1.0, dst_order=25, dst_α=0.0, dst_γ=-0.5\nmgc2mgc: testing with src_order=25, src_α, src_γ=-1.0, dst_order=25, dst_α=0.0, dst_γ=0.0\nmgc2mgc: testing with src_order=25, src_α, src_γ=-1.0, dst_order=25, dst_α=0.35, dst_γ=-1.0\nmgc2mgc: testing with src_order=25, src_α, src_γ=-1.0, dst_order=25, dst_α=0.35, dst_γ=-0.5\nmgc2mgc: testing with src_order=25, src_α, src_γ=-1.0, dst_order=25, dst_α=0.35, dst_γ=0.0\nmgc2mgc: testing with src_order=25, src_α, src_γ=-0.5, dst_order=15, dst_α=0.0, dst_γ=-1.0\nmgc2mgc: testing with src_order=25, src_α, src_γ=-0.5, dst_order=15, dst_α=0.0, dst_γ=-0.5\nmgc2mgc: testing with src_order=25, src_α, src_γ=-0.5, dst_order=15, dst_α=0.0, dst_γ=0.0\nmgc2mgc: testing with src_order=25, src_α, src_γ=-0.5, dst_order=15, dst_α=0.35, dst_γ=-1.0\nmgc2mgc: testing with src_order=25, src_α, src_γ=-0.5, dst_order=15, dst_α=0.35, dst_γ=-0.5\nmgc2mgc: testing with src_order=25, src_α, src_γ=-0.5, dst_order=15, dst_α=0.35, dst_γ=0.0\nmgc2mgc: testing with src_order=25, src_α, src_γ=-0.5, dst_order=20, dst_α=0.0, dst_γ=-1.0\nmgc2mgc: testing with src_order=25, src_α, src_γ=-0.5, dst_order=20, dst_α=0.0, dst_γ=-0.5\nmgc2mgc: testing with src_order=25, src_α, src_γ=-0.5, dst_order=20, dst_α=0.0, dst_γ=0.0\nmgc2mgc: testing with src_order=25, src_α, src_γ=-0.5, dst_order=20, dst_α=0.35, dst_γ=-1.0\nmgc2mgc: testing with src_order=25, src_α, src_γ=-0.5, dst_order=20, dst_α=0.35, dst_γ=-0.5\nmgc2mgc: testing with src_order=25, src_α, src_γ=-0.5, dst_order=20, dst_α=0.35, dst_γ=0.0\nmgc2mgc: testing with src_order=25, src_α, src_γ=-0.5, dst_order=25, dst_α=0.0, dst_γ=-1.0\nmgc2mgc: testing with src_order=25, src_α, src_γ=-0.5, dst_order=25, dst_α=0.0, dst_γ=-0.5\nmgc2mgc: testing with src_order=25, src_α, src_γ=-0.5, dst_order=25, dst_α=0.0, dst_γ=0.0\nmgc2mgc: testing with src_order=25, src_α, src_γ=-0.5, dst_order=25, dst_α=0.35, dst_γ=-1.0\nmgc2mgc: testing with src_order=25, src_α, src_γ=-0.5, dst_order=25, dst_α=0.35, dst_γ=-0.5\nmgc2mgc: testing with src_order=25, src_α, src_γ=-0.5, dst_order=25, dst_α=0.35, dst_γ=0.0\nmgc2mgc: testing with src_order=25, src_α, src_γ=0.0, dst_order=15, dst_α=0.0, dst_γ=-1.0\nmgc2mgc: testing with src_order=25, src_α, src_γ=0.0, dst_order=15, dst_α=0.0, dst_γ=-0.5\nmgc2mgc: testing with src_order=25, src_α, src_γ=0.0, dst_order=15, dst_α=0.0, dst_γ=0.0\nmgc2mgc: testing with src_order=25, src_α, src_γ=0.0, dst_order=15, dst_α=0.35, dst_γ=-1.0\nmgc2mgc: testing with src_order=25, src_α, src_γ=0.0, dst_order=15, dst_α=0.35, dst_γ=-0.5\nmgc2mgc: testing with src_order=25, src_α, src_γ=0.0, dst_order=15, dst_α=0.35, dst_γ=0.0\nmgc2mgc: testing with src_order=25, src_α, src_γ=0.0, dst_order=20, dst_α=0.0, dst_γ=-1.0\nmgc2mgc: testing with src_order=25, src_α, src_γ=0.0, dst_order=20, dst_α=0.0, dst_γ=-0.5\nmgc2mgc: testing with src_order=25, src_α, src_γ=0.0, dst_order=20, dst_α=0.0, dst_γ=0.0\nmgc2mgc: testing with src_order=25, src_α, src_γ=0.0, dst_order=20, dst_α=0.35, dst_γ=-1.0\nmgc2mgc: testing with src_order=25, src_α, src_γ=0.0, dst_order=20, dst_α=0.35, dst_γ=-0.5\nmgc2mgc: testing with src_order=25, src_α, src_γ=0.0, dst_order=20, dst_α=0.35, dst_γ=0.0\nmgc2mgc: testing with src_order=25, src_α, src_γ=0.0, dst_order=25, dst_α=0.0, dst_γ=-1.0\nmgc2mgc: testing with src_order=25, src_α, src_γ=0.0, dst_order=25, dst_α=0.0, dst_γ=-0.5\nmgc2mgc: testing with src_order=25, src_α, src_γ=0.0, dst_order=25, dst_α=0.0, dst_γ=0.0\nmgc2mgc: testing with src_order=25, src_α, src_γ=0.0, dst_order=25, dst_α=0.35, dst_γ=-1.0\nmgc2mgc: testing with src_order=25, src_α, src_γ=0.0, dst_order=25, dst_α=0.35, dst_γ=-0.5\nmgc2mgc: testing with src_order=25, src_α, src_γ=0.0, dst_order=25, dst_α=0.35, dst_γ=0.0\nmgc2mgc: testing with src_order=25, src_α, src_γ=-1.0, dst_order=15, dst_α=0.0, dst_γ=-1.0\nmgc2mgc: testing with src_order=25, src_α, src_γ=-1.0, dst_order=15, dst_α=0.0, dst_γ=-0.5\nmgc2mgc: testing with src_order=25, src_α, src_γ=-1.0, dst_order=15, dst_α=0.0, dst_γ=0.0\nmgc2mgc: testing with src_order=25, src_α, src_γ=-1.0, dst_order=15, dst_α=0.35, dst_γ=-1.0\nmgc2mgc: testing with src_order=25, src_α, src_γ=-1.0, dst_order=15, dst_α=0.35, dst_γ=-0.5\nmgc2mgc: testing with src_order=25, src_α, src_γ=-1.0, dst_order=15, dst_α=0.35, dst_γ=0.0\nmgc2mgc: testing with src_order=25, src_α, src_γ=-1.0, dst_order=20, dst_α=0.0, dst_γ=-1.0\nmgc2mgc: testing with src_order=25, src_α, src_γ=-1.0, dst_order=20, dst_α=0.0, dst_γ=-0.5\nmgc2mgc: testing with src_order=25, src_α, src_γ=-1.0, dst_order=20, dst_α=0.0, dst_γ=0.0\nmgc2mgc: testing with src_order=25, src_α, src_γ=-1.0, dst_order=20, dst_α=0.35, dst_γ=-1.0\nmgc2mgc: testing with src_order=25, src_α, src_γ=-1.0, dst_order=20, dst_α=0.35, dst_γ=-0.5\nmgc2mgc: testing with src_order=25, src_α, src_γ=-1.0, dst_order=20, dst_α=0.35, dst_γ=0.0\nmgc2mgc: testing with src_order=25, src_α, src_γ=-1.0, dst_order=25, dst_α=0.0, dst_γ=-1.0\nmgc2mgc: testing with src_order=25, src_α, src_γ=-1.0, dst_order=25, dst_α=0.0, dst_γ=-0.5\nmgc2mgc: testing with src_order=25, src_α, src_γ=-1.0, dst_order=25, dst_α=0.0, dst_γ=0.0\nmgc2mgc: testing with src_order=25, src_α, src_γ=-1.0, dst_order=25, dst_α=0.35, dst_γ=-1.0\nmgc2mgc: testing with src_order=25, src_α, src_γ=-1.0, dst_order=25, dst_α=0.35, dst_γ=-0.5\nmgc2mgc: testing with src_order=25, src_α, src_γ=-1.0, dst_order=25, dst_α=0.35, dst_γ=0.0\nmgc2mgc: testing with src_order=25, src_α, src_γ=-0.5, dst_order=15, dst_α=0.0, dst_γ=-1.0\nmgc2mgc: testing with src_order=25, src_α, src_γ=-0.5, dst_order=15, dst_α=0.0, dst_γ=-0.5\nmgc2mgc: testing with src_order=25, src_α, src_γ=-0.5, dst_order=15, dst_α=0.0, dst_γ=0.0\nmgc2mgc: testing with src_order=25, src_α, src_γ=-0.5, dst_order=15, dst_α=0.35, dst_γ=-1.0\nmgc2mgc: testing with src_order=25, src_α, src_γ=-0.5, dst_order=15, dst_α=0.35, dst_γ=-0.5\nmgc2mgc: testing with src_order=25, src_α, src_γ=-0.5, dst_order=15, dst_α=0.35, dst_γ=0.0\nmgc2mgc: testing with src_order=25, src_α, src_γ=-0.5, dst_order=20, dst_α=0.0, dst_γ=-1.0\nmgc2mgc: testing with src_order=25, src_α, src_γ=-0.5, dst_order=20, dst_α=0.0, dst_γ=-0.5\nmgc2mgc: testing with src_order=25, src_α, src_γ=-0.5, dst_order=20, dst_α=0.0, dst_γ=0.0\nmgc2mgc: testing with src_order=25, src_α, src_γ=-0.5, dst_order=20, dst_α=0.35, dst_γ=-1.0\nmgc2mgc: testing with src_order=25, src_α, src_γ=-0.5, dst_order=20, dst_α=0.35, dst_γ=-0.5\nmgc2mgc: testing with src_order=25, src_α, src_γ=-0.5, dst_order=20, dst_α=0.35, dst_γ=0.0\nmgc2mgc: testing with src_order=25, src_α, src_γ=-0.5, dst_order=25, dst_α=0.0, dst_γ=-1.0\nmgc2mgc: testing with src_order=25, src_α, src_γ=-0.5, dst_order=25, dst_α=0.0, dst_γ=-0.5\nmgc2mgc: testing with src_order=25, src_α, src_γ=-0.5, dst_order=25, dst_α=0.0, dst_γ=0.0\nmgc2mgc: testing with src_order=25, src_α, src_γ=-0.5, dst_order=25, dst_α=0.35, dst_γ=-1.0\nmgc2mgc: testing with src_order=25, src_α, src_γ=-0.5, dst_order=25, dst_α=0.35, dst_γ=-0.5\nmgc2mgc: testing with src_order=25, src_α, src_γ=-0.5, dst_order=25, dst_α=0.35, dst_γ=0.0\nmgc2mgc: testing with src_order=25, src_α, src_γ=0.0, dst_order=15, dst_α=0.0, dst_γ=-1.0\nmgc2mgc: testing with src_order=25, src_α, src_γ=0.0, dst_order=15, dst_α=0.0, dst_γ=-0.5\nmgc2mgc: testing with src_order=25, src_α, src_γ=0.0, dst_order=15, dst_α=0.0, dst_γ=0.0\nmgc2mgc: testing with src_order=25, src_α, src_γ=0.0, dst_order=15, dst_α=0.35, dst_γ=-1.0\nmgc2mgc: testing with src_order=25, src_α, src_γ=0.0, dst_order=15, dst_α=0.35, dst_γ=-0.5\nmgc2mgc: testing with src_order=25, src_α, src_γ=0.0, dst_order=15, dst_α=0.35, dst_γ=0.0\nmgc2mgc: testing with src_order=25, src_α, src_γ=0.0, dst_order=20, dst_α=0.0, dst_γ=-1.0\nmgc2mgc: testing with src_order=25, src_α, src_γ=0.0, dst_order=20, dst_α=0.0, dst_γ=-0.5\nmgc2mgc: testing with src_order=25, src_α, src_γ=0.0, dst_order=20, dst_α=0.0, dst_γ=0.0\nmgc2mgc: testing with src_order=25, src_α, src_γ=0.0, dst_order=20, dst_α=0.35, dst_γ=-1.0\nmgc2mgc: testing with src_order=25, src_α, src_γ=0.0, dst_order=20, dst_α=0.35, dst_γ=-0.5\nmgc2mgc: testing with src_order=25, src_α, src_γ=0.0, dst_order=20, dst_α=0.35, dst_γ=0.0\nmgc2mgc: testing with src_order=25, src_α, src_γ=0.0, dst_order=25, dst_α=0.0, dst_γ=-1.0\nmgc2mgc: testing with src_order=25, src_α, src_γ=0.0, dst_order=25, dst_α=0.0, dst_γ=-0.5\nmgc2mgc: testing with src_order=25, src_α, src_γ=0.0, dst_order=25, dst_α=0.0, dst_γ=0.0\nmgc2mgc: testing with src_order=25, src_α, src_γ=0.0, dst_order=25, dst_α=0.35, dst_γ=-1.0\nmgc2mgc: testing with src_order=25, src_α, src_γ=0.0, dst_order=25, dst_α=0.35, dst_γ=-0.5\nmgc2mgc: testing with src_order=25, src_α, src_γ=0.0, dst_order=25, dst_α=0.35, dst_γ=0.0\ntesting: mgc2mgc exceptions\ntesting: mat2mat functions\nINFO: MelGeneralizedCepstrums tests passed\n\n>>> End of log","licfile":"LICENSE.md","license":"MIT"}