{"gitdate":"2015-09-01 20:41:00 -0400","exit_code":"255","name":"Mongo","jlver":"0.4","gitsha":"a78754cb1a4413c1572cde9c16b98de55790bf61","status":"not_possible","version":"0.1.4","url":"http://github.com/pzion/Mongo.jl","log":">>> 'Pkg.add(\"Mongo\")' log\nINFO: Cloning cache of Mongo from git://github.com/pzion/Mongo.jl.git\nINFO: Installing LibBSON v0.1.6\nINFO: Installing Mongo v0.1.4\nINFO: Building LibBSON\n\nWARNING: deprecated syntax \"{a=>b, ...}\" at /home/vagrant/.julia/v0.4/LibBSON/deps/build.jl:12.\nUse \"Dict{Any,Any}(a=>b, ...)\" instead.\n\nWARNING: deprecated syntax \"{a=>b, ...}\" at /home/vagrant/.julia/v0.4/LibBSON/deps/build.jl:23.\nUse \"Dict{Any,Any}(a=>b, ...)\" instead.\n\nWARNING: deprecated syntax \"[a=>b, ...]\" at /home/vagrant/.julia/v0.4/LibBSON/deps/build.jl:26.\nUse \"Dict(a=>b, ...)\" instead.\nINFO: Building Mongo\n\nWARNING: deprecated syntax \"{a=>b, ...}\" at /home/vagrant/.julia/v0.4/Mongo/deps/build.jl:12.\nUse \"Dict{Any,Any}(a=>b, ...)\" instead.\n\nWARNING: deprecated syntax \"{a=>b, ...}\" at /home/vagrant/.julia/v0.4/Mongo/deps/build.jl:23.\nUse \"Dict{Any,Any}(a=>b, ...)\" instead.\n\nWARNING: deprecated syntax \"[a=>b, ...]\" at /home/vagrant/.julia/v0.4/Mongo/deps/build.jl:26.\nUse \"Dict(a=>b, ...)\" instead.\nINFO: Attempting to Create directory /home/vagrant/.julia/v0.4/Mongo/deps/downloads\nINFO: Downloading file http://github.com/mongodb/mongo-c-driver/releases/download/1.0.0/mongo-c-driver-1.0.0.tar.gz\n  % Total    % Received % Xferd  Average Speed   Time    Time     Time  Current\n                                 Dload  Upload   Total   Spent    Left  Speed\n\r  0     0    0     0    0     0      0      0 --:--:-- --:--:-- --:--:--     0\r  0     0    0     0    0     0      0      0 --:--:-- --:--:-- --:--:--     0\n\r  0     0    0     0    0     0      0      0 --:--:-- --:--:-- --:--:--     0\n\r  0     0    0   588    0     0   2498      0 --:--:-- --:--:-- --:--:--  2498\n\r  0 5217k    0 17416    0     0  23611      0  0:03:46 --:--:--  0:03:46 23611\r 26 5217k   26 1379k    0     0   783k      0  0:00:06  0:00:01  0:00:05 1331k\r 90 5217k   90 4745k    0     0  1734k      0  0:00:03  0:00:02  0:00:01 2365k\r100 5217k  100 5217k    0     0  1845k      0  0:00:02  0:00:02 --:--:-- 2489k\nINFO: Done downloading file http://github.com/mongodb/mongo-c-driver/releases/download/1.0.0/mongo-c-driver-1.0.0.tar.gz\nINFO: Attempting to Create directory /home/vagrant/.julia/v0.4/Mongo/deps/src\nINFO: Attempting to Create directory /home/vagrant/.julia/v0.4/Mongo/deps\nINFO: Directory /home/vagrant/.julia/v0.4/Mongo/deps already created\nINFO: Attempting to Create directory /home/vagrant/.julia/v0.4/Mongo/deps/builds/libmongoc\nINFO: Changing Directory to /home/vagrant/.julia/v0.4/Mongo/deps/builds/libmongoc\nchecking for gcc... gcc\nchecking whether the C compiler works... yes\nchecking for C compiler default output file name... a.out\nchecking for suffix of executables... \nchecking whether we are cross compiling... no\nchecking for suffix of object files... o\nchecking whether we are using the GNU C compiler... yes\nchecking whether gcc accepts -g... yes\nchecking for gcc option to accept ISO C89... none needed\nchecking whether gcc understands -c and -o together... yes\nchecking for g++... g++\nchecking whether we are using the GNU C++ compiler... yes\nchecking whether g++ accepts -g... yes\nchecking for an ANSI C-conforming const... yes\nchecking for inline... inline\nchecking for typeof syntax and keyword spelling... typeof\nchecking for perl... /usr/bin/perl\nchecking for mv... /bin/mv\nchecking for grep... /bin/grep\nchecking for python... /usr/bin/python\nchecking for yelp-build... no\nchecking for a BSD-compatible install... /usr/bin/install -c\nchecking build system type... x86_64-unknown-linux-gnu\nchecking host system type... x86_64-unknown-linux-gnu\nchecking target system type... x86_64-unknown-linux-gnu\nchecking how to print strings... printf\nchecking for a sed that does not truncate output... /bin/sed\nchecking for grep that handles long lines and -e... (cached) /bin/grep\nchecking for egrep... /bin/grep -E\nchecking for fgrep... /bin/grep -F\nchecking for ld used by gcc... /usr/bin/ld\nchecking if the linker (/usr/bin/ld) is GNU ld... yes\nchecking for BSD- or MS-compatible name lister (nm)... /usr/bin/nm -B\nchecking the name lister (/usr/bin/nm -B) interface... BSD nm\nchecking whether ln -s works... yes\nchecking the maximum length of command line arguments... 1572864\nchecking whether the shell understands some XSI constructs... yes\nchecking whether the shell understands \"+=\"... yes\nchecking how to convert x86_64-unknown-linux-gnu file names to x86_64-unknown-linux-gnu format... func_convert_file_noop\nchecking how to convert x86_64-unknown-linux-gnu file names to toolchain format... func_convert_file_noop\nchecking for /usr/bin/ld option to reload object files... -r\nchecking for objdump... objdump\nchecking how to recognize dependent libraries... pass_all\nchecking for dlltool... dlltool\nchecking how to associate runtime and link libraries... printf %s\\n\nchecking for ar... ar\nchecking for archiver @FILE support... @\nchecking for strip... strip\nchecking for ranlib... ranlib\nchecking for gawk... gawk\nchecking command to parse /usr/bin/nm -B output from gcc object... ok\nchecking for sysroot... no\nchecking for mt... mt\nchecking if mt is a manifest tool... no\nchecking how to run the C preprocessor... gcc -E\nchecking for ANSI C header files... yes\nchecking for sys/types.h... yes\nchecking for sys/stat.h... yes\nchecking for stdlib.h... yes\nchecking for string.h... yes\nchecking for memory.h... yes\nchecking for strings.h... yes\nchecking for inttypes.h... yes\nchecking for stdint.h... yes\nchecking for unistd.h... yes\nchecking for dlfcn.h... yes\nchecking for objdir... .libs\nchecking if gcc supports -fno-rtti -fno-exceptions... no\nchecking for gcc option to produce PIC... -fPIC -DPIC\nchecking if gcc PIC flag -fPIC -DPIC works... yes\nchecking if gcc static flag -static works... yes\nchecking if gcc supports -c -o file.o... yes\nchecking if gcc supports -c -o file.o... (cached) yes\nchecking whether the gcc linker (/usr/bin/ld -m elf_x86_64) supports shared libraries... yes\nchecking whether -lc should be explicitly linked in... no\nchecking dynamic linker characteristics... GNU/Linux ld.so\nchecking how to hardcode library paths into programs... immediate\nchecking whether stripping libraries is possible... yes\nchecking if libtool supports shared libraries... yes\nchecking whether to build shared libraries... yes\nchecking whether to build static libraries... no\nchecking how to run the C++ preprocessor... g++ -E\nchecking for ld used by g++... /usr/bin/ld -m elf_x86_64\nchecking if the linker (/usr/bin/ld -m elf_x86_64) is GNU ld... yes\nchecking whether the g++ linker (/usr/bin/ld -m elf_x86_64) supports shared libraries... yes\nchecking for g++ option to produce PIC... -fPIC -DPIC\nchecking if g++ PIC flag -fPIC -DPIC works... yes\nchecking if g++ static flag -static works... yes\nchecking if g++ supports -c -o file.o... yes\nchecking if g++ supports -c -o file.o... (cached) yes\nchecking whether the g++ linker (/usr/bin/ld -m elf_x86_64) supports shared libraries... yes\nchecking dynamic linker characteristics... (cached) GNU/Linux ld.so\nchecking how to hardcode library paths into programs... immediate\nchecking whether to do a debug build... no\nchecking whether to enable tracing... no\nchecking whether to enable optimized builds... yes\nchecking whether to enable code coverage support... no\nchecking whether to enable debug symbols... no\nchecking for pkg-config... /usr/bin/pkg-config\nchecking pkg-config is at least version 0.9.0... yes\nchecking for SASL... no\nchecking for sasl_client_init in -lsasl2... no\nchecking for sasl_client_init in -lsasl... no\nchecking sasl/sasl.h usability... no\nchecking sasl/sasl.h presence... no\nchecking for sasl/sasl.h... no\nchecking for SSL... no\nchecking for SSL_library_init in -lssl... no\nchecking for CRYPTO_set_locking_callback in -lcrypto... no\nchecking openssl/bio.h usability... no\nchecking openssl/bio.h presence... no\nchecking for openssl/bio.h... no\nchecking openssl/ssl.h usability... no\nchecking openssl/ssl.h presence... no\nchecking for openssl/ssl.h... no\nchecking openssl/err.h usability... no\nchecking openssl/err.h presence... no\nchecking for openssl/err.h... no\nchecking openssl/crypto.h usability... no\nchecking openssl/crypto.h presence... no\nchecking for openssl/crypto.h... no\nchecking for BSON... no\nchecking for shm_open... no\nchecking for shm_open in -lrt... yes\nchecking for sched_getcpu... yes\nchecking for library containing clock_gettime... none required\nchecking if compiler needs -Werror to reject unknown flags... no\nchecking for the pthreads library -lpthreads... no\nchecking whether pthreads work without any flags... no\nchecking whether pthreads work with -Kthread... no\nchecking whether pthreads work with -kthread... no\nchecking for the pthreads library -llthread... no\nchecking whether pthreads work with -pthread... yes\nchecking for joinable pthread attribute... PTHREAD_CREATE_JOINABLE\nchecking if more special flags are required for pthreads... no\nchecking for PTHREAD_PRIO_INHERIT... yes\nchecking whether C compiler accepts -fno-strict-overflow... no\nchecking whether C compiler accepts -D_FORTIFY_SOURCE=2... no\nchecking whether C compiler accepts -fstack-protector-all... no\nchecking whether C compiler accepts -fPIE... no\nchecking whether the linker accepts -Wl,-z,relro... no\nchecking whether the linker accepts -Wl,-Bsymbolic... yes\nchecking whether build environment is sane... yes\nchecking for a thread-safe mkdir -p... /bin/mkdir -p\nchecking whether make sets $(MAKE)... yes\nchecking for style of include used by make... GNU\nchecking whether make supports nested variables... yes\nchecking whether UID '1000' is supported by ustar format... yes\nchecking whether GID '1000' is supported by ustar format... yes\nchecking how to create a ustar tar archive... gnutar\nchecking dependency style of gcc... gcc3\nchecking dependency style of g++... gcc3\nchecking whether to enable maintainer-specific portions of Makefiles... yes\nchecking whether make supports nested variables... (cached) yes\nchecking that generated files are newer than configure... done\nconfigure: creating ./config.status\nconfig.status: creating Makefile\nconfig.status: creating build/version\nconfig.status: creating src/libmongoc-1.0.pc\nconfig.status: creating src/libmongoc-ssl-1.0.pc\nconfig.status: creating src/libmongoc-priv.pc\nconfig.status: creating src/mongoc/mongoc-config.h\nconfig.status: creating src/mongoc/mongoc-version.h\nconfig.status: executing libtool commands\nconfig.status: executing depfiles commands\n=== configuring in src/libbson (/home/vagrant/.julia/v0.4/Mongo/deps/builds/libmongoc/src/libbson)\nconfigure: running /bin/bash /home/vagrant/.julia/v0.4/Mongo/deps/src/mongo-c-driver-1.0.0/src/libbson/configure --disable-option-checking '--prefix=/home/vagrant/.julia/v0.4/Mongo/deps/usr'  'LDFLAGS= -L/home/vagrant/.julia/v0.4/Mongo/deps/usr/lib -Wl,-rpath -Wl,/home/vagrant/.julia/v0.4/Mongo/deps/usr/lib' 'CPPFLAGS= -I/home/vagrant/.julia/v0.4/Mongo/deps/usr/include' 'PKG_CONFIG_PATH=/home/vagrant/.julia/v0.4/Mongo/deps/usr/lib/pkgconfig' --cache-file=/dev/null --srcdir=/home/vagrant/.julia/v0.4/Mongo/deps/src/mongo-c-driver-1.0.0/src/libbson\nchecking for gcc... gcc\nchecking whether the C compiler works... yes\nchecking for C compiler default output file name... a.out\nchecking for suffix of executables... \nchecking whether we are cross compiling... no\nchecking for suffix of object files... o\nchecking whether we are using the GNU C compiler... yes\nchecking whether gcc accepts -g... yes\nchecking for gcc option to accept ISO C89... none needed\nchecking whether gcc understands -c and -o together... yes\nchecking for g++... g++\nchecking whether we are using the GNU C++ compiler... yes\nchecking whether g++ accepts -g... yes\nchecking for an ANSI C-conforming const... yes\nchecking for inline... inline\nchecking for typeof syntax and keyword spelling... typeof\nchecking how to run the C preprocessor... gcc -E\nchecking for grep that handles long lines and -e... /bin/grep\nchecking for egrep... /bin/grep -E\nchecking for ANSI C header files... yes\nchecking for sys/types.h... yes\nchecking for sys/stat.h... yes\nchecking for stdlib.h... yes\nchecking for string.h... yes\nchecking for memory.h... yes\nchecking for strings.h... yes\nchecking for inttypes.h... yes\nchecking for stdint.h... yes\nchecking for unistd.h... yes\nchecking for stdbool.h that conforms to C99... yes\nchecking for _Bool... yes\nchecking for stdint-types....... \"(putting them into src/bson/bson-stdint.h)\"\nchecking for uintptr_t... yes\nchecking for uint64_t... yes\n... seen our uintptr_t in stdint.h (uint64_t too)\ncreating src/bson/bson-stdint.h : _SRC_BSON_BSON_STDINT_H\nchecking for int_least32_t... yes\nchecking for int_fast32_t... yes\n..adding include stdint.h\n... seen good stdint.h inttypes\n... seen good uint64_t\n... DONE src/bson/bson-stdint.h\nchecking for perl... /usr/bin/perl\nchecking for mv... /bin/mv\nchecking for grep... (cached) /bin/grep\nchecking for python... /usr/bin/python\nchecking for yelp-build... no\nchecking for a BSD-compatible install... /usr/bin/install -c\nchecking build system type... x86_64-unknown-linux-gnu\nchecking host system type... x86_64-unknown-linux-gnu\nchecking target system type... x86_64-unknown-linux-gnu\nchecking whether byte ordering is bigendian... no\nchecking how to print strings... printf\nchecking for a sed that does not truncate output... /bin/sed\nchecking for fgrep... /bin/grep -F\nchecking for ld used by gcc... /usr/bin/ld\nchecking if the linker (/usr/bin/ld) is GNU ld... yes\nchecking for BSD- or MS-compatible name lister (nm)... /usr/bin/nm -B\nchecking the name lister (/usr/bin/nm -B) interface... BSD nm\nchecking whether ln -s works... yes\nchecking the maximum length of command line arguments... 1572864\nchecking whether the shell understands some XSI constructs... yes\nchecking whether the shell understands \"+=\"... yes\nchecking how to convert x86_64-unknown-linux-gnu file names to x86_64-unknown-linux-gnu format... func_convert_file_noop\nchecking how to convert x86_64-unknown-linux-gnu file names to toolchain format... func_convert_file_noop\nchecking for /usr/bin/ld option to reload object files... -r\nchecking for objdump... objdump\nchecking how to recognize dependent libraries... pass_all\nchecking for dlltool... dlltool\nchecking how to associate runtime and link libraries... printf %s\\n\nchecking for ar... ar\nchecking for archiver @FILE support... @\nchecking for strip... strip\nchecking for ranlib... ranlib\nchecking for gawk... gawk\nchecking command to parse /usr/bin/nm -B output from gcc object... ok\nchecking for sysroot... no\nchecking for mt... mt\nchecking if mt is a manifest tool... no\nchecking for dlfcn.h... yes\nchecking for objdir... .libs\nchecking if gcc supports -fno-rtti -fno-exceptions... no\nchecking for gcc option to produce PIC... -fPIC -DPIC\nchecking if gcc PIC flag -fPIC -DPIC works... yes\nchecking if gcc static flag -static works... yes\nchecking if gcc supports -c -o file.o... yes\nchecking if gcc supports -c -o file.o... (cached) yes\nchecking whether the gcc linker (/usr/bin/ld -m elf_x86_64) supports shared libraries... yes\nchecking whether -lc should be explicitly linked in... no\nchecking dynamic linker characteristics... GNU/Linux ld.so\nchecking how to hardcode library paths into programs... immediate\nchecking whether stripping libraries is possible... yes\nchecking if libtool supports shared libraries... yes\nchecking whether to build shared libraries... yes\nchecking whether to build static libraries... no\nchecking how to run the C++ preprocessor... g++ -E\nchecking for ld used by g++... /usr/bin/ld -m elf_x86_64\nchecking if the linker (/usr/bin/ld -m elf_x86_64) is GNU ld... yes\nchecking whether the g++ linker (/usr/bin/ld -m elf_x86_64) supports shared libraries... yes\nchecking for g++ option to produce PIC... -fPIC -DPIC\nchecking if g++ PIC flag -fPIC -DPIC works... yes\nchecking if g++ static flag -static works... yes\nchecking if g++ supports -c -o file.o... yes\nchecking if g++ supports -c -o file.o... (cached) yes\nchecking whether the g++ linker (/usr/bin/ld -m elf_x86_64) supports shared libraries... yes\nchecking dynamic linker characteristics... (cached) GNU/Linux ld.so\nchecking how to hardcode library paths into programs... immediate\nchecking whether to do a debug build... no\nchecking whether to enable optimized builds... yes\nchecking whether to enable code coverage support... no\nchecking whether to enable debug symbols... no\nchecking for strnlen... yes\nchecking for snprintf... yes\nchecking for library containing clock_gettime... none required\nchecking if compiler needs -Werror to reject unknown flags... no\nchecking for the pthreads library -lpthreads... no\nchecking whether pthreads work without any flags... no\nchecking whether pthreads work with -Kthread... no\nchecking whether pthreads work with -kthread... no\nchecking for the pthreads library -llthread... no\nchecking whether pthreads work with -pthread... yes\nchecking for joinable pthread attribute... PTHREAD_CREATE_JOINABLE\nchecking if more special flags are required for pthreads... no\nchecking for PTHREAD_PRIO_INHERIT... yes\nchecking whether PTHREAD_ONCE_INIT needs braces... no\nchecking for __sync_add_and_fetch_8... yes\nchecking whether C compiler accepts -fno-strict-overflow... no\nchecking whether C compiler accepts -D_FORTIFY_SOURCE=2... no\nchecking whether C compiler accepts -fstack-protector-all... no\nchecking whether C compiler accepts -fPIE... no\nchecking whether the linker accepts -Wl,-z,relro... no\nchecking whether the linker accepts -Wl,-Bsymbolic... yes\nchecking whether build environment is sane... yes\nchecking for a thread-safe mkdir -p... /bin/mkdir -p\nchecking whether make sets $(MAKE)... yes\nchecking for style of include used by make... GNU\nchecking whether make supports nested variables... yes\nchecking whether UID '1000' is supported by ustar format... yes\nchecking whether GID '1000' is supported by ustar format... yes\nchecking how to create a ustar tar archive... gnutar\nchecking dependency style of gcc... gcc3\nchecking dependency style of g++... gcc3\nchecking whether to enable maintainer-specific portions of Makefiles... yes\nchecking whether make supports nested variables... (cached) yes\nchecking that generated files are newer than configure... done\nconfigure: creating ./config.status\nconfig.status: creating Makefile\nconfig.status: creating src/libbson-1.0.pc\nconfig.status: creating src/bson/bson-config.h\nconfig.status: creating src/bson/bson-version.h\nconfig.status: executing libtool commands\nconfig.status: executing depfiles commands\n\nlibbson was configured with the following options:\n\nBuild configuration:\n  Enable debugging (slow)                          : no\n  Compile with debug symbols (slow)                : no\n  Enable GCC build optimization                    : yes\n  Enable automatic binary hardening                : yes\n  Code coverage support                            : no\n  Cross Compiling                                  : no\n  Big endian                                       : no\n  Link Time Optimization (experimental)            : no\n\nDocumentation:\n  man                                              : no\n  HTML                                             : no\n\n\nlibmongoc was configured with the following options:\n\nBuild configuration:\n  Enable debugging (slow)                          : no\n  Compile with debug symbols (slow)                : no\n  Enable GCC build optimization                    : yes\n  Enable automatic binary hardening                : yes\n  Code coverage support                            : no\n  Cross Compiling                                  : no\n  Fast counters                                    : no\n  SASL                                             : no\n  SSL                                              : no\n  Libbson                                          : bundled\n\nDocumentation:\n  man                                              : no\n  HTML                                             : no\n\nINFO: Changing Directory to /home/vagrant/.julia/v0.4/Mongo/deps/builds/libmongoc\nMaking all in src/libbson\nmake[1]: Entering directory `/home/vagrant/.julia/v0.4/Mongo/deps/builds/libmongoc/src/libbson'\n  CC       src/bson/libbson_la-bcon.lo\n  CC       src/bson/libbson_la-bson.lo\n  CC       src/bson/libbson_la-bson-atomic.lo\n  CC       src/bson/libbson_la-bson-clock.lo\n  CC       src/bson/libbson_la-bson-context.lo\n  CC       src/bson/libbson_la-bson-error.lo\n  CC       src/bson/libbson_la-bson-iter.lo\n  CC       src/bson/libbson_la-bson-json.lo\n  CC       src/bson/libbson_la-bson-keys.lo\n  CC       src/bson/libbson_la-bson-md5.lo\n  CC       src/bson/libbson_la-bson-memory.lo\n  CC       src/bson/libbson_la-bson-oid.lo\n  CC       src/bson/libbson_la-bson-reader.lo\n  CC       src/bson/libbson_la-bson-string.lo\n  CC       src/bson/libbson_la-bson-utf8.lo\n  CC       src/bson/libbson_la-bson-value.lo\n  CC       src/bson/libbson_la-bson-version.lo\n  CC       src/bson/libbson_la-bson-writer.lo\n  CC       src/yajl/libyajl_la-yajl_version.lo\n  CC       src/yajl/libyajl_la-yajl.lo\n  CC       src/yajl/libyajl_la-yajl_encode.lo\n  CC       src/yajl/libyajl_la-yajl_lex.lo\n  CC       src/yajl/libyajl_la-yajl_parser.lo\n  CC       src/yajl/libyajl_la-yajl_buf.lo\n  CC       src/yajl/libyajl_la-yajl_tree.lo\n  CC       src/yajl/libyajl_la-yajl_alloc.lo\n  CC       src/yajl/libyajl_la-yajl_gen.lo\n  CC       tests/test_libbson-TestSuite.o\n  CC       tests/test_libbson-test-libbson.o\n  CC       tests/test_libbson-test-atomic.o\n  CC       tests/test_libbson-test-bson.o\n  CC       tests/test_libbson-test-endian.o\n  CC       tests/test_libbson-test-clock.o\n  CC       tests/test_libbson-test-error.o\n  CC       tests/test_libbson-test-iter.o\n  CC       tests/test_libbson-test-json.o\n  CC       tests/test_libbson-test-oid.o\n  CC       tests/test_libbson-test-reader.o\n  CC       tests/test_libbson-test-string.o\n  CC       tests/test_libbson-test-utf8.o\n  CC       tests/test_libbson-test-value.o\n  CC       tests/test_libbson-test-writer.o\n  CC       tests/test_libbson-test-bcon-basic.o\n  CC       tests/test_libbson-test-bcon-extract.o\n  CC       examples/bson_to_json-bson-to-json.o\n  CC       examples/bson_validate-bson-validate.o\n  CC       examples/bcon_speed-bcon-speed.o\n  CC       examples/bcon_col_view-bcon-col-view.o\n  CC       examples/json_to_bson-json-to-bson.o\n  CC       examples/bson_metrics-bson-metrics.o\n  CCLD     libbson.la\n  CCLD     libyajl.la\n  CCLD     libbson-1.0.la\n  CCLD     bson-to-json\n  CCLD     bson-validate\n  CCLD     bcon-speed\n  CCLD     bcon-col-view\n  CCLD     json-to-bson\n  CCLD     bson-metrics\n  CCLD     test-libbson\nmake[1]: Leaving directory `/home/vagrant/.julia/v0.4/Mongo/deps/builds/libmongoc/src/libbson'\nmake[1]: Entering directory `/home/vagrant/.julia/v0.4/Mongo/deps/builds/libmongoc'\n  CC       src/mongoc/libmongoc_priv_la-mongoc-array.lo\n  CC       src/mongoc/libmongoc_priv_la-mongoc-buffer.lo\n  CC       src/mongoc/libmongoc_priv_la-mongoc-bulk-operation.lo\n  CC       src/mongoc/libmongoc_priv_la-mongoc-client.lo\n  CC       src/mongoc/libmongoc_priv_la-mongoc-client-pool.lo\n  CC       src/mongoc/libmongoc_priv_la-mongoc-cluster.lo\n  CC       src/mongoc/libmongoc_priv_la-mongoc-collection.lo\n  CC       src/mongoc/libmongoc_priv_la-mongoc-counters.lo\n  CC       src/mongoc/libmongoc_priv_la-mongoc-cursor.lo\n  CC       src/mongoc/libmongoc_priv_la-mongoc-cursor-array.lo\n  CC       src/mongoc/libmongoc_priv_la-mongoc-cursor-cursorid.lo\n  CC       src/mongoc/libmongoc_priv_la-mongoc-database.lo\n  CC       src/mongoc/libmongoc_priv_la-mongoc-init.lo\n  CC       src/mongoc/libmongoc_priv_la-mongoc-gridfs.lo\n  CC       src/mongoc/libmongoc_priv_la-mongoc-gridfs-file.lo\n  CC       src/mongoc/libmongoc_priv_la-mongoc-gridfs-file-page.lo\n  CC       src/mongoc/libmongoc_priv_la-mongoc-gridfs-file-list.lo\n  CC       src/mongoc/libmongoc_priv_la-mongoc-index.lo\n  CC       src/mongoc/libmongoc_priv_la-mongoc-list.lo\n  CC       src/mongoc/libmongoc_priv_la-mongoc-log.lo\n  CC       src/mongoc/libmongoc_priv_la-mongoc-matcher-op.lo\n  CC       src/mongoc/libmongoc_priv_la-mongoc-matcher.lo\n  CC       src/mongoc/libmongoc_priv_la-mongoc-queue.lo\n  CC       src/mongoc/libmongoc_priv_la-mongoc-read-prefs.lo\n  CC       src/mongoc/libmongoc_priv_la-mongoc-rpc.lo\n  CC       src/mongoc/libmongoc_priv_la-mongoc-socket.lo\n  CC       src/mongoc/libmongoc_priv_la-mongoc-stream.lo\n  CC       src/mongoc/libmongoc_priv_la-mongoc-stream-buffered.lo\n  CC       src/mongoc/libmongoc_priv_la-mongoc-stream-file.lo\n  CC       src/mongoc/libmongoc_priv_la-mongoc-stream-gridfs.lo\n  CC       src/mongoc/libmongoc_priv_la-mongoc-stream-socket.lo\n  CC       src/mongoc/libmongoc_priv_la-mongoc-uri.lo\n  CC       src/mongoc/libmongoc_priv_la-mongoc-util.lo\n  CC       src/mongoc/libmongoc_priv_la-mongoc-write-command.lo\n  CC       src/mongoc/libmongoc_priv_la-mongoc-write-concern.lo\n  CC       src/mongoc/libmongoc_1_0_la-mongoc-array.lo\n  CC       src/mongoc/libmongoc_1_0_la-mongoc-buffer.lo\n  CC       src/mongoc/libmongoc_1_0_la-mongoc-bulk-operation.lo\n  CC       src/mongoc/libmongoc_1_0_la-mongoc-client.lo\n  CC       src/mongoc/libmongoc_1_0_la-mongoc-client-pool.lo\n  CC       src/mongoc/libmongoc_1_0_la-mongoc-cluster.lo\n  CC       src/mongoc/libmongoc_1_0_la-mongoc-collection.lo\n  CC       src/mongoc/libmongoc_1_0_la-mongoc-counters.lo\n  CC       src/mongoc/libmongoc_1_0_la-mongoc-cursor.lo\n  CC       src/mongoc/libmongoc_1_0_la-mongoc-cursor-array.lo\n  CC       src/mongoc/libmongoc_1_0_la-mongoc-cursor-cursorid.lo\n  CC       src/mongoc/libmongoc_1_0_la-mongoc-database.lo\n  CC       src/mongoc/libmongoc_1_0_la-mongoc-init.lo\n  CC       src/mongoc/libmongoc_1_0_la-mongoc-gridfs.lo\n  CC       src/mongoc/libmongoc_1_0_la-mongoc-gridfs-file.lo\n  CC       src/mongoc/libmongoc_1_0_la-mongoc-gridfs-file-page.lo\n  CC       src/mongoc/libmongoc_1_0_la-mongoc-gridfs-file-list.lo\n  CC       src/mongoc/libmongoc_1_0_la-mongoc-index.lo\n  CC       src/mongoc/libmongoc_1_0_la-mongoc-list.lo\n  CC       src/mongoc/libmongoc_1_0_la-mongoc-log.lo\n  CC       src/mongoc/libmongoc_1_0_la-mongoc-matcher-op.lo\n  CC       src/mongoc/libmongoc_1_0_la-mongoc-matcher.lo\n  CC       src/mongoc/libmongoc_1_0_la-mongoc-queue.lo\n  CC       src/mongoc/libmongoc_1_0_la-mongoc-read-prefs.lo\n  CC       src/mongoc/libmongoc_1_0_la-mongoc-rpc.lo\n  CC       src/mongoc/libmongoc_1_0_la-mongoc-socket.lo\n  CC       src/mongoc/libmongoc_1_0_la-mongoc-stream.lo\n  CC       src/mongoc/libmongoc_1_0_la-mongoc-stream-buffered.lo\n  CC       src/mongoc/libmongoc_1_0_la-mongoc-stream-file.lo\n  CC       src/mongoc/libmongoc_1_0_la-mongoc-stream-gridfs.lo\n  CC       src/mongoc/libmongoc_1_0_la-mongoc-stream-socket.lo\n  CC       src/mongoc/libmongoc_1_0_la-mongoc-uri.lo\n  CC       src/mongoc/libmongoc_1_0_la-mongoc-util.lo\n  CC       src/mongoc/libmongoc_1_0_la-mongoc-write-command.lo\n  CC       src/mongoc/libmongoc_1_0_la-mongoc-write-concern.lo\n  CC       src/tools/mongoc_stat-mongoc-stat.o\n  CC       tests/test_load-test-load.o\n  CC       tests/test_load-mongoc-tests.o\n  CC       tests/test_secondary-test-secondary.o\n  CC       tests/test_secondary-mongoc-tests.o\n  CC       tests/test_replica_set-test-replica-set.o\n  CC       tests/test_replica_set-ha-test.o\n  CC       tests/test_replica_set-mongoc-tests.o\n  CC       tests/test_sharded_cluster-test-sharded-cluster.o\n  CC       tests/test_sharded_cluster-ha-test.o\n  CC       tests/test_sharded_cluster-mongoc-tests.o\n  CC       tests/test_libmongoc-mock-server.o\n  CC       tests/test_libmongoc-test-libmongoc.o\n  CC       tests/test_libmongoc-test-bulk.o\n  CC       tests/test_libmongoc-test-mongoc-array.o\n  CC       tests/test_libmongoc-test-mongoc-buffer.o\n  CC       tests/test_libmongoc-test-mongoc-client.o\n  CC       tests/test_libmongoc-test-mongoc-client-pool.o\n  CC       tests/test_libmongoc-test-mongoc-collection.o\n  CC       tests/test_libmongoc-test-mongoc-cursor.o\n  CC       tests/test_libmongoc-test-mongoc-database.o\n  CC       tests/test_libmongoc-test-mongoc-gridfs.o\n  CC       tests/test_libmongoc-test-mongoc-gridfs-file-page.o\n  CC       tests/test_libmongoc-test-mongoc-list.o\n  CC       tests/test_libmongoc-test-mongoc-matcher.o\n  CC       tests/test_libmongoc-test-mongoc-queue.o\n  CC       tests/test_libmongoc-test-mongoc-read-prefs.o\n  CC       tests/test_libmongoc-test-mongoc-rpc.o\n  CC       tests/test_libmongoc-test-mongoc-stream.o\n  CC       tests/test_libmongoc-test-mongoc-uri.o\n  CC       tests/test_libmongoc-test-mongoc-write-concern.o\n  CC       tests/test_libmongoc-test-write-commands.o\n  CC       tests/test_libmongoc-TestSuite.o\n  CC       examples/example_gridfs-example-gridfs.o\n  CC       examples/mongoc_dump-mongoc-dump.o\n  CC       examples/filter_bsondump-filter-bsondump.o\n  CC       examples/example_client-example-client.o\n  CC       examples/mongoc_ping-mongoc-ping.o\n  CC       examples/mongoc_rpc_validate-mongoc-rpc-validate.o\n  CC       examples/mongoc_tail-mongoc-tail.o\n  CC       examples/find_and_modify-find-and-modify.o\n  CC       examples/example_matcher-example-matcher.o\n  CC       examples/bulk/bulk1-bulk1.o\n  CC       examples/bulk/bulk2-bulk2.o\n  CC       examples/bulk/bulk3-bulk3.o\n  CC       examples/aggregation/aggregation1-aggregation1.o\n  CCLD     libmongoc-priv.la\n  CCLD     libmongoc-1.0.la\n  CCLD     mongoc-stat\n  CCLD     test-load\n  CCLD     test-secondary\n  CCLD     test-replica-set\n  CCLD     test-sharded-cluster\n  CCLD     test-libmongoc\n  CCLD     mongoc-rpc-validate\n  CCLD     example-gridfs\n  CCLD     mongoc-dump\n  CCLD     filter-bsondump\n  CCLD     example-client\n  CCLD     mongoc-ping\n  CCLD     mongoc-tail\n  CCLD     find-and-modify\n  CCLD     example-matcher\n  CCLD     bulk1\n  CCLD     bulk2\n  CCLD     bulk3\n  CCLD     aggregation1\nmake[1]: Leaving directory `/home/vagrant/.julia/v0.4/Mongo/deps/builds/libmongoc'\nINFO: Changing Directory to /home/vagrant/.julia/v0.4/Mongo/deps/builds/libmongoc\nMaking install in src/libbson\nmake[1]: Entering directory `/home/vagrant/.julia/v0.4/Mongo/deps/builds/libmongoc/src/libbson'\nmake[2]: Entering directory `/home/vagrant/.julia/v0.4/Mongo/deps/builds/libmongoc/src/libbson'\n /bin/mkdir -p '/home/vagrant/.julia/v0.4/Mongo/deps/usr/lib'\n /bin/mkdir -p '/home/vagrant/.julia/v0.4/Mongo/deps/usr/share/doc/libbson'\n /bin/bash ./libtool   --mode=install /usr/bin/install -c   libbson-1.0.la '/home/vagrant/.julia/v0.4/Mongo/deps/usr/lib'\n /bin/mkdir -p '/home/vagrant/.julia/v0.4/Mongo/deps/usr/include/libbson-1.0'\n /usr/bin/install -c -m 644 /home/vagrant/.julia/v0.4/Mongo/deps/src/mongo-c-driver-1.0.0/src/libbson/COPYING /home/vagrant/.julia/v0.4/Mongo/deps/src/mongo-c-driver-1.0.0/src/libbson/NEWS /home/vagrant/.julia/v0.4/Mongo/deps/src/mongo-c-driver-1.0.0/src/libbson/README '/home/vagrant/.julia/v0.4/Mongo/deps/usr/share/doc/libbson'\nlibtool: install: /usr/bin/install -c .libs/libbson-1.0.so.0.0.0 /home/vagrant/.julia/v0.4/Mongo/deps/usr/lib/libbson-1.0.so.0.0.0\n /bin/mkdir -p '/home/vagrant/.julia/v0.4/Mongo/deps/usr/lib/pkgconfig'\n /usr/bin/install -c -m 644 /home/vagrant/.julia/v0.4/Mongo/deps/src/mongo-c-driver-1.0.0/src/libbson/src/bson/bcon.h /home/vagrant/.julia/v0.4/Mongo/deps/src/mongo-c-driver-1.0.0/src/libbson/src/bson/bson.h /home/vagrant/.julia/v0.4/Mongo/deps/src/mongo-c-driver-1.0.0/src/libbson/src/bson/bson-atomic.h /home/vagrant/.julia/v0.4/Mongo/deps/src/mongo-c-driver-1.0.0/src/libbson/src/bson/bson-clock.h /home/vagrant/.julia/v0.4/Mongo/deps/src/mongo-c-driver-1.0.0/src/libbson/src/bson/bson-compat.h /home/vagrant/.julia/v0.4/Mongo/deps/src/mongo-c-driver-1.0.0/src/libbson/src/bson/bson-context.h /home/vagrant/.julia/v0.4/Mongo/deps/src/mongo-c-driver-1.0.0/src/libbson/src/bson/bson-endian.h /home/vagrant/.julia/v0.4/Mongo/deps/src/mongo-c-driver-1.0.0/src/libbson/src/bson/bson-error.h /home/vagrant/.julia/v0.4/Mongo/deps/src/mongo-c-driver-1.0.0/src/libbson/src/bson/bson-iter.h /home/vagrant/.julia/v0.4/Mongo/deps/src/mongo-c-driver-1.0.0/src/libbson/src/bson/bson-json.h /home/vagrant/.julia/v0.4/Mongo/deps/src/mongo-c-driver-1.0.0/src/libbson/src/bson/bson-keys.h /home/vagrant/.julia/v0.4/Mongo/deps/src/mongo-c-driver-1.0.0/src/libbson/src/bson/bson-macros.h /home/vagrant/.julia/v0.4/Mongo/deps/src/mongo-c-driver-1.0.0/src/libbson/src/bson/bson-md5.h /home/vagrant/.julia/v0.4/Mongo/deps/src/mongo-c-driver-1.0.0/src/libbson/src/bson/bson-memory.h /home/vagrant/.julia/v0.4/Mongo/deps/src/mongo-c-driver-1.0.0/src/libbson/src/bson/bson-oid.h /home/vagrant/.julia/v0.4/Mongo/deps/src/mongo-c-driver-1.0.0/src/libbson/src/bson/bson-reader.h /home/vagrant/.julia/v0.4/Mongo/deps/src/mongo-c-driver-1.0.0/src/libbson/src/bson/bson-string.h /home/vagrant/.julia/v0.4/Mongo/deps/src/mongo-c-driver-1.0.0/src/libbson/src/bson/bson-types.h /home/vagrant/.julia/v0.4/Mongo/deps/src/mongo-c-driver-1.0.0/src/libbson/src/bson/bson-utf8.h /home/vagrant/.julia/v0.4/Mongo/deps/src/mongo-c-driver-1.0.0/src/libbson/src/bson/bson-value.h src/bson/bson-version.h /home/vagrant/.julia/v0.4/Mongo/deps/src/mongo-c-driver-1.0.0/src/libbson/src/bson/bson-writer.h src/bson/bson-stdint.h src/bson/bson-config.h '/home/vagrant/.julia/v0.4/Mongo/deps/usr/include/libbson-1.0'\n /usr/bin/install -c -m 644 ./src/libbson-1.0.pc '/home/vagrant/.julia/v0.4/Mongo/deps/usr/lib/pkgconfig'\nlibtool: install: (cd /home/vagrant/.julia/v0.4/Mongo/deps/usr/lib && { ln -s -f libbson-1.0.so.0.0.0 libbson-1.0.so.0 || { rm -f libbson-1.0.so.0 && ln -s libbson-1.0.so.0.0.0 libbson-1.0.so.0; }; })\nlibtool: install: (cd /home/vagrant/.julia/v0.4/Mongo/deps/usr/lib && { ln -s -f libbson-1.0.so.0.0.0 libbson-1.0.so || { rm -f libbson-1.0.so && ln -s libbson-1.0.so.0.0.0 libbson-1.0.so; }; })\nlibtool: install: /usr/bin/install -c .libs/libbson-1.0.lai /home/vagrant/.julia/v0.4/Mongo/deps/usr/lib/libbson-1.0.la\nlibtool: finish: PATH=\"/home/vagrant/.julia/v0.4/Mongo/deps/usr/bin:/usr/local/sbin:/usr/local/bin:/usr/sbin:/usr/bin:/sbin:/bin:/usr/games:/usr/local/games:/home/vagrant/julia/bin/:/sbin\" ldconfig -n /home/vagrant/.julia/v0.4/Mongo/deps/usr/lib\n----------------------------------------------------------------------\nLibraries have been installed in:\n   /home/vagrant/.julia/v0.4/Mongo/deps/usr/lib\n\nIf you ever happen to want to link against installed libraries\nin a given directory, LIBDIR, you must either use libtool, and\nspecify the full pathname of the library, or use the `-LLIBDIR'\nflag during linking and do at least one of the following:\n   - add LIBDIR to the `LD_LIBRARY_PATH' environment variable\n     during execution\n   - add LIBDIR to the `LD_RUN_PATH' environment variable\n     during linking\n   - use the `-Wl,-rpath -Wl,LIBDIR' linker flag\n   - have your system administrator add LIBDIR to `/etc/ld.so.conf'\n\nSee any operating system documentation about shared libraries for\nmore information, such as the ld(1) and ld.so(8) manual pages.\n----------------------------------------------------------------------\nmake[2]: Leaving directory `/home/vagrant/.julia/v0.4/Mongo/deps/builds/libmongoc/src/libbson'\nmake[1]: Leaving directory `/home/vagrant/.julia/v0.4/Mongo/deps/builds/libmongoc/src/libbson'\nmake[1]: Entering directory `/home/vagrant/.julia/v0.4/Mongo/deps/builds/libmongoc'\nmake[2]: Entering directory `/home/vagrant/.julia/v0.4/Mongo/deps/builds/libmongoc'\n /bin/mkdir -p '/home/vagrant/.julia/v0.4/Mongo/deps/usr/lib'\n /bin/mkdir -p '/home/vagrant/.julia/v0.4/Mongo/deps/usr/include/libmongoc-1.0'\n /bin/bash ./libtool   --mode=install /usr/bin/install -c   libmongoc-priv.la libmongoc-1.0.la '/home/vagrant/.julia/v0.4/Mongo/deps/usr/lib'\n /usr/bin/install -c -m 644 /home/vagrant/.julia/v0.4/Mongo/deps/src/mongo-c-driver-1.0.0/src/mongoc/mongoc.h /home/vagrant/.julia/v0.4/Mongo/deps/src/mongo-c-driver-1.0.0/src/mongoc/mongoc-array-private.h /home/vagrant/.julia/v0.4/Mongo/deps/src/mongo-c-driver-1.0.0/src/mongoc/mongoc-buffer-private.h /home/vagrant/.julia/v0.4/Mongo/deps/src/mongo-c-driver-1.0.0/src/mongoc/mongoc-bulk-operation-private.h /home/vagrant/.julia/v0.4/Mongo/deps/src/mongo-c-driver-1.0.0/src/mongoc/mongoc-bulk-operation.h /home/vagrant/.julia/v0.4/Mongo/deps/src/mongo-c-driver-1.0.0/src/mongoc/mongoc-client-pool.h /home/vagrant/.julia/v0.4/Mongo/deps/src/mongo-c-driver-1.0.0/src/mongoc/mongoc-client-private.h /home/vagrant/.julia/v0.4/Mongo/deps/src/mongo-c-driver-1.0.0/src/mongoc/mongoc-client.h /home/vagrant/.julia/v0.4/Mongo/deps/src/mongo-c-driver-1.0.0/src/mongoc/mongoc-cluster-private.h /home/vagrant/.julia/v0.4/Mongo/deps/src/mongo-c-driver-1.0.0/src/mongoc/mongoc-collection-private.h /home/vagrant/.julia/v0.4/Mongo/deps/src/mongo-c-driver-1.0.0/src/mongoc/mongoc-collection.h /home/vagrant/.julia/v0.4/Mongo/deps/src/mongo-c-driver-1.0.0/src/mongoc/mongoc-counters-private.h /home/vagrant/.julia/v0.4/Mongo/deps/src/mongo-c-driver-1.0.0/src/mongoc/mongoc-cursor-array-private.h /home/vagrant/.julia/v0.4/Mongo/deps/src/mongo-c-driver-1.0.0/src/mongoc/mongoc-cursor-cursorid-private.h /home/vagrant/.julia/v0.4/Mongo/deps/src/mongo-c-driver-1.0.0/src/mongoc/mongoc-cursor-private.h /home/vagrant/.julia/v0.4/Mongo/deps/src/mongo-c-driver-1.0.0/src/mongoc/mongoc-cursor.h /home/vagrant/.julia/v0.4/Mongo/deps/src/mongo-c-driver-1.0.0/src/mongoc/mongoc-database-private.h /home/vagrant/.julia/v0.4/Mongo/deps/src/mongo-c-driver-1.0.0/src/mongoc/mongoc-database.h /home/vagrant/.julia/v0.4/Mongo/deps/src/mongo-c-driver-1.0.0/src/mongoc/mongoc-errno-private.h /home/vagrant/.julia/v0.4/Mongo/deps/src/mongo-c-driver-1.0.0/src/mongoc/mongoc-error.h /home/vagrant/.julia/v0.4/Mongo/deps/src/mongo-c-driver-1.0.0/src/mongoc/mongoc-flags.h /home/vagrant/.julia/v0.4/Mongo/deps/src/mongo-c-driver-1.0.0/src/mongoc/mongoc-gridfs-file-list-private.h /home/vagrant/.julia/v0.4/Mongo/deps/src/mongo-c-driver-1.0.0/src/mongoc/mongoc-gridfs-file-list.h /home/vagrant/.julia/v0.4/Mongo/deps/src/mongo-c-driver-1.0.0/src/mongoc/mongoc-gridfs-file-page-private.h /home/vagrant/.julia/v0.4/Mongo/deps/src/mongo-c-driver-1.0.0/src/mongoc/mongoc-gridfs-file-page.h /home/vagrant/.julia/v0.4/Mongo/deps/src/mongo-c-driver-1.0.0/src/mongoc/mongoc-gridfs-file-private.h /home/vagrant/.julia/v0.4/Mongo/deps/src/mongo-c-driver-1.0.0/src/mongoc/mongoc-gridfs-file.h /home/vagrant/.julia/v0.4/Mongo/deps/src/mongo-c-driver-1.0.0/src/mongoc/mongoc-gridfs-private.h /home/vagrant/.julia/v0.4/Mongo/deps/src/mongo-c-driver-1.0.0/src/mongoc/mongoc-gridfs.h /home/vagrant/.julia/v0.4/Mongo/deps/src/mongo-c-driver-1.0.0/src/mongoc/mongoc-host-list-private.h /home/vagrant/.julia/v0.4/Mongo/deps/src/mongo-c-driver-1.0.0/src/mongoc/mongoc-host-list.h /home/vagrant/.julia/v0.4/Mongo/deps/src/mongo-c-driver-1.0.0/src/mongoc/mongoc-index.h /home/vagrant/.julia/v0.4/Mongo/deps/src/mongo-c-driver-1.0.0/src/mongoc/mongoc-init.h /home/vagrant/.julia/v0.4/Mongo/deps/src/mongo-c-driver-1.0.0/src/mongoc/mongoc-iovec.h /home/vagrant/.julia/v0.4/Mongo/deps/src/mongo-c-driver-1.0.0/src/mongoc/mongoc-list-private.h /home/vagrant/.julia/v0.4/Mongo/deps/src/mongo-c-driver-1.0.0/src/mongoc/mongoc-log.h /home/vagrant/.julia/v0.4/Mongo/deps/src/mongo-c-driver-1.0.0/src/mongoc/mongoc-matcher-op-private.h /home/vagrant/.julia/v0.4/Mongo/deps/src/mongo-c-driver-1.0.0/src/mongoc/mongoc-matcher-private.h /home/vagrant/.julia/v0.4/Mongo/deps/src/mongo-c-driver-1.0.0/src/mongoc/mongoc-matcher.h /home/vagrant/.julia/v0.4/Mongo/deps/src/mongo-c-driver-1.0.0/src/mongoc/mongoc-opcode.h '/home/vagrant/.julia/v0.4/Mongo/deps/usr/include/libmongoc-1.0'\n /bin/mkdir -p '/home/vagrant/.julia/v0.4/Mongo/deps/usr/share/doc/mongo-c-driver'\n /usr/bin/install -c -m 644 /home/vagrant/.julia/v0.4/Mongo/deps/src/mongo-c-driver-1.0.0/src/mongoc/mongoc-queue-private.h /home/vagrant/.julia/v0.4/Mongo/deps/src/mongo-c-driver-1.0.0/src/mongoc/mongoc-read-prefs-private.h /home/vagrant/.julia/v0.4/Mongo/deps/src/mongo-c-driver-1.0.0/src/mongoc/mongoc-read-prefs.h /home/vagrant/.julia/v0.4/Mongo/deps/src/mongo-c-driver-1.0.0/src/mongoc/mongoc-rpc-private.h /home/vagrant/.julia/v0.4/Mongo/deps/src/mongo-c-driver-1.0.0/src/mongoc/mongoc-sasl-private.h /home/vagrant/.julia/v0.4/Mongo/deps/src/mongo-c-driver-1.0.0/src/mongoc/mongoc-socket.h /home/vagrant/.julia/v0.4/Mongo/deps/src/mongo-c-driver-1.0.0/src/mongoc/mongoc-ssl-private.h /home/vagrant/.julia/v0.4/Mongo/deps/src/mongo-c-driver-1.0.0/src/mongoc/mongoc-stream-buffered.h /home/vagrant/.julia/v0.4/Mongo/deps/src/mongo-c-driver-1.0.0/src/mongoc/mongoc-stream-file.h /home/vagrant/.julia/v0.4/Mongo/deps/src/mongo-c-driver-1.0.0/src/mongoc/mongoc-stream-gridfs.h /home/vagrant/.julia/v0.4/Mongo/deps/src/mongo-c-driver-1.0.0/src/mongoc/mongoc-stream-private.h /home/vagrant/.julia/v0.4/Mongo/deps/src/mongo-c-driver-1.0.0/src/mongoc/mongoc-stream-socket.h /home/vagrant/.julia/v0.4/Mongo/deps/src/mongo-c-driver-1.0.0/src/mongoc/mongoc-stream.h /home/vagrant/.julia/v0.4/Mongo/deps/src/mongo-c-driver-1.0.0/src/mongoc/mongoc-thread-private.h /home/vagrant/.julia/v0.4/Mongo/deps/src/mongo-c-driver-1.0.0/src/mongoc/mongoc-trace.h /home/vagrant/.julia/v0.4/Mongo/deps/src/mongo-c-driver-1.0.0/src/mongoc/mongoc-uri.h /home/vagrant/.julia/v0.4/Mongo/deps/src/mongo-c-driver-1.0.0/src/mongoc/mongoc-util-private.h src/mongoc/mongoc-version.h /home/vagrant/.julia/v0.4/Mongo/deps/src/mongo-c-driver-1.0.0/src/mongoc/mongoc-write-command-private.h /home/vagrant/.julia/v0.4/Mongo/deps/src/mongo-c-driver-1.0.0/src/mongoc/mongoc-write-concern-private.h /home/vagrant/.julia/v0.4/Mongo/deps/src/mongo-c-driver-1.0.0/src/mongoc/mongoc-write-concern.h /home/vagrant/.julia/v0.4/Mongo/deps/src/mongo-c-driver-1.0.0/src/mongoc/op-delete.def /home/vagrant/.julia/v0.4/Mongo/deps/src/mongo-c-driver-1.0.0/src/mongoc/op-get-more.def /home/vagrant/.julia/v0.4/Mongo/deps/src/mongo-c-driver-1.0.0/src/mongoc/op-header.def /home/vagrant/.julia/v0.4/Mongo/deps/src/mongo-c-driver-1.0.0/src/mongoc/op-insert.def /home/vagrant/.julia/v0.4/Mongo/deps/src/mongo-c-driver-1.0.0/src/mongoc/op-kill-cursors.def /home/vagrant/.julia/v0.4/Mongo/deps/src/mongo-c-driver-1.0.0/src/mongoc/op-msg.def /home/vagrant/.julia/v0.4/Mongo/deps/src/mongo-c-driver-1.0.0/src/mongoc/op-query.def /home/vagrant/.julia/v0.4/Mongo/deps/src/mongo-c-driver-1.0.0/src/mongoc/op-reply.def /home/vagrant/.julia/v0.4/Mongo/deps/src/mongo-c-driver-1.0.0/src/mongoc/op-update.def /home/vagrant/.julia/v0.4/Mongo/deps/src/mongo-c-driver-1.0.0/src/mongoc/mongoc-counters.defs src/mongoc/mongoc-config.h '/home/vagrant/.julia/v0.4/Mongo/deps/usr/include/libmongoc-1.0'\n /bin/mkdir -p '/home/vagrant/.julia/v0.4/Mongo/deps/usr/lib/pkgconfig'\n /usr/bin/install -c -m 644 /home/vagrant/.julia/v0.4/Mongo/deps/src/mongo-c-driver-1.0.0/COPYING /home/vagrant/.julia/v0.4/Mongo/deps/src/mongo-c-driver-1.0.0/NEWS /home/vagrant/.julia/v0.4/Mongo/deps/src/mongo-c-driver-1.0.0/README.rst '/home/vagrant/.julia/v0.4/Mongo/deps/usr/share/doc/mongo-c-driver'\n /usr/bin/install -c -m 644 ./src/libmongoc-1.0.pc ./src/libmongoc-priv.pc '/home/vagrant/.julia/v0.4/Mongo/deps/usr/lib/pkgconfig'\nlibtool: install: warning: relinking `libmongoc-priv.la'\nlibtool: install: (cd /home/vagrant/.julia/v0.4/Mongo/deps/builds/libmongoc; /bin/bash /home/vagrant/.julia/v0.4/Mongo/deps/builds/libmongoc/libtool  --silent --tag CC --mode=relink gcc -O2 -D_FORTIFY_SOURCE=2 -Wl,-Bsymbolic -L/home/vagrant/.julia/v0.4/Mongo/deps/usr/lib -Wl,-rpath -Wl,/home/vagrant/.julia/v0.4/Mongo/deps/usr/lib -o libmongoc-priv.la -rpath /home/vagrant/.julia/v0.4/Mongo/deps/usr/lib src/mongoc/libmongoc_priv_la-mongoc-array.lo src/mongoc/libmongoc_priv_la-mongoc-buffer.lo src/mongoc/libmongoc_priv_la-mongoc-bulk-operation.lo src/mongoc/libmongoc_priv_la-mongoc-client.lo src/mongoc/libmongoc_priv_la-mongoc-client-pool.lo src/mongoc/libmongoc_priv_la-mongoc-cluster.lo src/mongoc/libmongoc_priv_la-mongoc-collection.lo src/mongoc/libmongoc_priv_la-mongoc-counters.lo src/mongoc/libmongoc_priv_la-mongoc-cursor.lo src/mongoc/libmongoc_priv_la-mongoc-cursor-array.lo src/mongoc/libmongoc_priv_la-mongoc-cursor-cursorid.lo src/mongoc/libmongoc_priv_la-mongoc-database.lo src/mongoc/libmongoc_priv_la-mongoc-init.lo src/mongoc/libmongoc_priv_la-mongoc-gridfs.lo src/mongoc/libmongoc_priv_la-mongoc-gridfs-file.lo src/mongoc/libmongoc_priv_la-mongoc-gridfs-file-page.lo src/mongoc/libmongoc_priv_la-mongoc-gridfs-file-list.lo src/mongoc/libmongoc_priv_la-mongoc-index.lo src/mongoc/libmongoc_priv_la-mongoc-list.lo src/mongoc/libmongoc_priv_la-mongoc-log.lo src/mongoc/libmongoc_priv_la-mongoc-matcher-op.lo src/mongoc/libmongoc_priv_la-mongoc-matcher.lo src/mongoc/libmongoc_priv_la-mongoc-queue.lo src/mongoc/libmongoc_priv_la-mongoc-read-prefs.lo src/mongoc/libmongoc_priv_la-mongoc-rpc.lo src/mongoc/libmongoc_priv_la-mongoc-socket.lo src/mongoc/libmongoc_priv_la-mongoc-stream.lo src/mongoc/libmongoc_priv_la-mongoc-stream-buffered.lo src/mongoc/libmongoc_priv_la-mongoc-stream-file.lo src/mongoc/libmongoc_priv_la-mongoc-stream-gridfs.lo src/mongoc/libmongoc_priv_la-mongoc-stream-socket.lo src/mongoc/libmongoc_priv_la-mongoc-uri.lo src/mongoc/libmongoc_priv_la-mongoc-util.lo src/mongoc/libmongoc_priv_la-mongoc-write-command.lo src/mongoc/libmongoc_priv_la-mongoc-write-concern.lo src/libbson/libbson-1.0.la -lrt )\nlibtool: install: /usr/bin/install -c .libs/libmongoc-priv.so.0.0.0T /home/vagrant/.julia/v0.4/Mongo/deps/usr/lib/libmongoc-priv.so.0.0.0\nlibtool: install: (cd /home/vagrant/.julia/v0.4/Mongo/deps/usr/lib && { ln -s -f libmongoc-priv.so.0.0.0 libmongoc-priv.so.0 || { rm -f libmongoc-priv.so.0 && ln -s libmongoc-priv.so.0.0.0 libmongoc-priv.so.0; }; })\nlibtool: install: (cd /home/vagrant/.julia/v0.4/Mongo/deps/usr/lib && { ln -s -f libmongoc-priv.so.0.0.0 libmongoc-priv.so || { rm -f libmongoc-priv.so && ln -s libmongoc-priv.so.0.0.0 libmongoc-priv.so; }; })\nlibtool: install: /usr/bin/install -c .libs/libmongoc-priv.lai /home/vagrant/.julia/v0.4/Mongo/deps/usr/lib/libmongoc-priv.la\nlibtool: install: warning: relinking `libmongoc-1.0.la'\nlibtool: install: (cd /home/vagrant/.julia/v0.4/Mongo/deps/builds/libmongoc; /bin/bash /home/vagrant/.julia/v0.4/Mongo/deps/builds/libmongoc/libtool  --silent --tag CC --mode=relink gcc -O2 -D_FORTIFY_SOURCE=2 -Wl,-Bsymbolic -no-undefined -export-symbols-regex \"^mongoc_\" -rpath /home/vagrant/.julia/v0.4/Mongo/deps/usr/lib -L/home/vagrant/.julia/v0.4/Mongo/deps/usr/lib -Wl,-rpath -Wl,/home/vagrant/.julia/v0.4/Mongo/deps/usr/lib -o libmongoc-1.0.la -rpath /home/vagrant/.julia/v0.4/Mongo/deps/usr/lib src/mongoc/libmongoc_1_0_la-mongoc-array.lo src/mongoc/libmongoc_1_0_la-mongoc-buffer.lo src/mongoc/libmongoc_1_0_la-mongoc-bulk-operation.lo src/mongoc/libmongoc_1_0_la-mongoc-client.lo src/mongoc/libmongoc_1_0_la-mongoc-client-pool.lo src/mongoc/libmongoc_1_0_la-mongoc-cluster.lo src/mongoc/libmongoc_1_0_la-mongoc-collection.lo src/mongoc/libmongoc_1_0_la-mongoc-counters.lo src/mongoc/libmongoc_1_0_la-mongoc-cursor.lo src/mongoc/libmongoc_1_0_la-mongoc-cursor-array.lo src/mongoc/libmongoc_1_0_la-mongoc-cursor-cursorid.lo src/mongoc/libmongoc_1_0_la-mongoc-database.lo src/mongoc/libmongoc_1_0_la-mongoc-init.lo src/mongoc/libmongoc_1_0_la-mongoc-gridfs.lo src/mongoc/libmongoc_1_0_la-mongoc-gridfs-file.lo src/mongoc/libmongoc_1_0_la-mongoc-gridfs-file-page.lo src/mongoc/libmongoc_1_0_la-mongoc-gridfs-file-list.lo src/mongoc/libmongoc_1_0_la-mongoc-index.lo src/mongoc/libmongoc_1_0_la-mongoc-list.lo src/mongoc/libmongoc_1_0_la-mongoc-log.lo src/mongoc/libmongoc_1_0_la-mongoc-matcher-op.lo src/mongoc/libmongoc_1_0_la-mongoc-matcher.lo src/mongoc/libmongoc_1_0_la-mongoc-queue.lo src/mongoc/libmongoc_1_0_la-mongoc-read-prefs.lo src/mongoc/libmongoc_1_0_la-mongoc-rpc.lo src/mongoc/libmongoc_1_0_la-mongoc-socket.lo src/mongoc/libmongoc_1_0_la-mongoc-stream.lo src/mongoc/libmongoc_1_0_la-mongoc-stream-buffered.lo src/mongoc/libmongoc_1_0_la-mongoc-stream-file.lo src/mongoc/libmongoc_1_0_la-mongoc-stream-gridfs.lo src/mongoc/libmongoc_1_0_la-mongoc-stream-socket.lo src/mongoc/libmongoc_1_0_la-mongoc-uri.lo src/mongoc/libmongoc_1_0_la-mongoc-util.lo src/mongoc/libmongoc_1_0_la-mongoc-write-command.lo src/mongoc/libmongoc_1_0_la-mongoc-write-concern.lo src/libbson/libbson-1.0.la -lrt )\nlibtool: install: /usr/bin/install -c .libs/libmongoc-1.0.so.0.0.0T /home/vagrant/.julia/v0.4/Mongo/deps/usr/lib/libmongoc-1.0.so.0.0.0\nlibtool: install: (cd /home/vagrant/.julia/v0.4/Mongo/deps/usr/lib && { ln -s -f libmongoc-1.0.so.0.0.0 libmongoc-1.0.so.0 || { rm -f libmongoc-1.0.so.0 && ln -s libmongoc-1.0.so.0.0.0 libmongoc-1.0.so.0; }; })\nlibtool: install: (cd /home/vagrant/.julia/v0.4/Mongo/deps/usr/lib && { ln -s -f libmongoc-1.0.so.0.0.0 libmongoc-1.0.so || { rm -f libmongoc-1.0.so && ln -s libmongoc-1.0.so.0.0.0 libmongoc-1.0.so; }; })\nlibtool: install: /usr/bin/install -c .libs/libmongoc-1.0.lai /home/vagrant/.julia/v0.4/Mongo/deps/usr/lib/libmongoc-1.0.la\nlibtool: finish: PATH=\"/home/vagrant/.julia/v0.4/Mongo/deps/usr/bin:/usr/local/sbin:/usr/local/bin:/usr/sbin:/usr/bin:/sbin:/bin:/usr/games:/usr/local/games:/home/vagrant/julia/bin/:/sbin\" ldconfig -n /home/vagrant/.julia/v0.4/Mongo/deps/usr/lib\n----------------------------------------------------------------------\nLibraries have been installed in:\n   /home/vagrant/.julia/v0.4/Mongo/deps/usr/lib\n\nIf you ever happen to want to link against installed libraries\nin a given directory, LIBDIR, you must either use libtool, and\nspecify the full pathname of the library, or use the `-LLIBDIR'\nflag during linking and do at least one of the following:\n   - add LIBDIR to the `LD_LIBRARY_PATH' environment variable\n     during execution\n   - add LIBDIR to the `LD_RUN_PATH' environment variable\n     during linking\n   - use the `-Wl,-rpath -Wl,LIBDIR' linker flag\n   - have your system administrator add LIBDIR to `/etc/ld.so.conf'\n\nSee any operating system documentation about shared libraries for\nmore information, such as the ld(1) and ld.so(8) manual pages.\n----------------------------------------------------------------------\n /bin/mkdir -p '/home/vagrant/.julia/v0.4/Mongo/deps/usr/bin'\n  /bin/bash ./libtool   --mode=install /usr/bin/install -c mongoc-stat '/home/vagrant/.julia/v0.4/Mongo/deps/usr/bin'\nlibtool: install: /usr/bin/install -c .libs/mongoc-stat /home/vagrant/.julia/v0.4/Mongo/deps/usr/bin/mongoc-stat\nmake[2]: Leaving directory `/home/vagrant/.julia/v0.4/Mongo/deps/builds/libmongoc'\nmake[1]: Leaving directory `/home/vagrant/.julia/v0.4/Mongo/deps/builds/libmongoc'\nINFO: Package database updated\n\n>>> 'Pkg.test(\"Mongo\")' log\nPackage was unable to be tested.\n>>> End of log","licfile":"LICENSE.md","license":"BSD 3-clause"}