{"gitdate":"2013-11-22 00:58:17 -0500","exit_code":"254","name":"OpenSlide","jlver":"0.4","gitsha":"c46cfa1e354660d3cd08e3447f6e620621e523d6","status":"no_tests","version":"0.0.1","url":"http://github.com/ihnorton/OpenSlide.jl","log":">>> 'Pkg.add(\"OpenSlide\")' log\nINFO: Cloning cache of OpenSlide from git://github.com/ihnorton/OpenSlide.jl.git\nINFO: Installing OpenSlide v0.0.1\nINFO: Package database updated\n\n>>> 'Pkg.test(\"OpenSlide\")' log\nNo tests found.\n>>> End of log","licfile":"LICENSE.md","license":"MIT"}