{"gitdate":"2015-09-20 14:31:30 +0530","exit_code":"0","name":"Patchwork","jlver":"0.4","gitsha":"b3383a5ef529862f3640374aac8ee14077c284f6","status":"tests_pass","version":"0.1.8","url":"http://github.com/shashi/Patchwork.jl","log":">>> 'Pkg.add(\"Patchwork\")' log\nINFO: Installing Benchmark v0.1.0\nINFO: Installing FactCheck v0.4.0\nINFO: Installing FunctionalCollections v0.1.2\nINFO: Installing Patchwork v0.1.8\nINFO: Package database updated\n\n>>> 'Pkg.test(\"Patchwork\")' log\nJulia Version 0.4.0-rc2+10\nCommit d8930a0 (2015-09-20 15:38 UTC)\nPlatform Info:\n  System: Linux (x86_64-unknown-linux-gnu)\n  CPU: Intel(R) Core(TM) i7-6700K CPU @ 4.00GHz\n  WORD_SIZE: 64\n  BLAS: libopenblas (USE64BITINT DYNAMIC_ARCH NO_AFFINITY Prescott)\n  LAPACK: libopenblas\n  LIBM: libopenlibm\n  LLVM: libLLVM-3.3\nINFO: Testing Patchwork\nWARNING: Base.String is deprecated, use AbstractString instead.\nWARNING: Union(args...) is deprecated, use Union{args...} instead.\n in depwarn at deprecated.jl:73\n in call at deprecated.jl:50\n in include at ./boot.jl:261\n in include_from_node1 at ./loading.jl:304\n in include at ./boot.jl:261\n in include_from_node1 at ./loading.jl:304\n in require at ./loading.jl:243\n in include at ./boot.jl:261\n in include_from_node1 at ./loading.jl:304\n in require at ./loading.jl:243\n in include at ./boot.jl:261\n in include_from_node1 at ./loading.jl:304\n in include at ./boot.jl:261\n in include_from_node1 at ./loading.jl:304\n in process_options at ./client.jl:308\n in _start at ./client.jl:411\nwhile loading /home/vagrant/.julia/v0.4/FunctionalCollections/src/PersistentArrayMap.jl, in expression starting on line 58\nWARNING: Union(args...) is deprecated, use Union{args...} instead.\n in depwarn at deprecated.jl:73\n in call at deprecated.jl:50\n in include at ./boot.jl:261\n in include_from_node1 at ./loading.jl:304\n in include at ./boot.jl:261\n in include_from_node1 at ./loading.jl:304\n in require at ./loading.jl:243\n in include at ./boot.jl:261\n in include_from_node1 at ./loading.jl:304\n in require at ./loading.jl:243\n in include at ./boot.jl:261\n in include_from_node1 at ./loading.jl:304\n in include at ./boot.jl:261\n in include_from_node1 at ./loading.jl:304\n in process_options at ./client.jl:308\n in _start at ./client.jl:411\nwhile loading /home/vagrant/.julia/v0.4/FunctionalCollections/src/PersistentHashMap.jl, in expression starting on line 222\nWARNING: Base.Nothing is deprecated, use Void instead.\nWARNING: Base.Nothing is deprecated, use Void instead.\nWARNING: Base.Uint is deprecated, use UInt64 instead.\nWARNING: Union(args...) is deprecated, use Union{args...} instead.\n in depwarn at deprecated.jl:73\n in call at deprecated.jl:50\n in include at ./boot.jl:261\n in include_from_node1 at ./loading.jl:304\n in include at ./boot.jl:261\n in include_from_node1 at ./loading.jl:304\n in require at ./loading.jl:243\n in include at ./boot.jl:261\n in include_from_node1 at ./loading.jl:304\n in require at ./loading.jl:243\n in include at ./boot.jl:261\n in include_from_node1 at ./loading.jl:304\n in include at ./boot.jl:261\n in include_from_node1 at ./loading.jl:304\n in process_options at ./client.jl:308\n in _start at ./client.jl:411\nwhile loading /home/vagrant/.julia/v0.4/FunctionalCollections/src/PersistentSet.jl, in expression starting on line 47\nWARNING: Union(args...) is deprecated, use Union{args...} instead.\n in depwarn at deprecated.jl:73\n in call at deprecated.jl:50\n in include at ./boot.jl:261\n in include_from_node1 at ./loading.jl:304\n in include at ./boot.jl:261\n in include_from_node1 at ./loading.jl:304\n in require at ./loading.jl:243\n in include at ./boot.jl:261\n in include_from_node1 at ./loading.jl:304\n in require at ./loading.jl:243\n in include at ./boot.jl:261\n in include_from_node1 at ./loading.jl:304\n in include at ./boot.jl:261\n in include_from_node1 at ./loading.jl:304\n in process_options at ./client.jl:308\n in _start at ./client.jl:411\nwhile loading /home/vagrant/.julia/v0.4/FunctionalCollections/src/PersistentSet.jl, in expression starting on line 53\nWARNING: Union(args...) is deprecated, use Union{args...} instead.\n in depwarn at deprecated.jl:73\n in call at deprecated.jl:50\n in include at ./boot.jl:261\n in include_from_node1 at ./loading.jl:304\n in include at ./boot.jl:261\n in include_from_node1 at ./loading.jl:304\n in require at ./loading.jl:243\n in include at ./boot.jl:261\n in include_from_node1 at ./loading.jl:304\n in require at ./loading.jl:243\n in include at ./boot.jl:261\n in include_from_node1 at ./loading.jl:304\n in include at ./boot.jl:261\n in include_from_node1 at ./loading.jl:304\n in process_options at ./client.jl:308\n in _start at ./client.jl:411\nwhile loading /home/vagrant/.julia/v0.4/FunctionalCollections/src/PersistentList.jl, in expression starting on line 60\nWARNING: Union(args...) is deprecated, use Union{args...} instead.\n in depwarn at deprecated.jl:73\n in call at deprecated.jl:50\n in include at ./boot.jl:261\n in include_from_node1 at ./loading.jl:304\n in include at ./boot.jl:261\n in include_from_node1 at ./loading.jl:304\n in require at ./loading.jl:243\n in include at ./boot.jl:261\n in include_from_node1 at ./loading.jl:304\n in require at ./loading.jl:243\n in include at ./boot.jl:261\n in include_from_node1 at ./loading.jl:304\n in include at ./boot.jl:261\n in include_from_node1 at ./loading.jl:304\n in process_options at ./client.jl:308\n in _start at ./client.jl:411\nwhile loading /home/vagrant/.julia/v0.4/FunctionalCollections/src/PersistentList.jl, in expression starting on line 61\nWARNING: Base.Nothing is deprecated, use Void instead.\nWARNING: Union(args...) is deprecated, use Union{args...} instead.\n in depwarn at deprecated.jl:73\n in call at deprecated.jl:50\n in include at ./boot.jl:261\n in include_from_node1 at ./loading.jl:304\n in require at ./loading.jl:243\n in include at ./boot.jl:261\n in include_from_node1 at ./loading.jl:304\n in include at ./boot.jl:261\n in include_from_node1 at ./loading.jl:304\n in process_options at ./client.jl:308\n in _start at ./client.jl:411\nwhile loading /home/vagrant/.julia/v0.4/Patchwork/src/Patchwork.jl, in expression starting on line 33\nWARNING: Base.String is deprecated, use AbstractString instead.\nWARNING: Base.String is deprecated, use AbstractString instead.\nWARNING: Base.String is deprecated, use AbstractString instead.\nWARNING: Base.String is deprecated, use AbstractString instead.\nWARNING: Base.String is deprecated, use AbstractString instead.\nWARNING: Base.String is deprecated, use AbstractString instead.\nWARNING: Base.String is deprecated, use AbstractString instead.\nWARNING: Base.Nothing is deprecated, use Void instead.\nWARNING: Union(args...) is deprecated, use Union{args...} instead.\n in depwarn at deprecated.jl:73\n in call at deprecated.jl:50\n in include at ./boot.jl:261\n in include_from_node1 at ./loading.jl:304\n in include at ./boot.jl:261\n in include_from_node1 at ./loading.jl:304\n in require at ./loading.jl:243\n in include at ./boot.jl:261\n in include_from_node1 at ./loading.jl:304\n in include at ./boot.jl:261\n in include_from_node1 at ./loading.jl:304\n in process_options at ./client.jl:308\n in _start at ./client.jl:411\nwhile loading /home/vagrant/.julia/v0.4/Patchwork/src/writers.jl, in expression starting on line 19\nTesting Diffs\n  > testing are_equal\n  > things that should return empty patches\n  > testing Overwrite\n20 facts verified.\nTesting Nodes\n  > testing counts\n5 facts verified.\nTesting nested node creation\n1 fact verified.\nINFO: Patchwork tests passed\n\n>>> End of log","licfile":"LICENSE.md","license":"MIT"}